Workbook
Name Alist: 'A. Completeness'!$K$2:$K$4
Name Blist: 'A. Completeness'!$K$3:$K$4
Name CHIP: 'Cover Sheet'!$J$2:$J$7
Name Clist: 'A. Completeness'!$K$1
Name Ilist: 'B. Enrollment & Disenrollment'!$L$2:$L$3
Name Medicaid: 'Cover Sheet'!$J$2:$J$7
Name MMC: 'Cover Sheet'!$J$2:$J$8
Name MUNN: 'A. Completeness'!$J$1:$J$4
Name Rlist: 'B. Enrollment & Disenrollment'!$M$2:$M$3
Name YNNN: 'A. Completeness'!$L$1:$L$4
Name OLE_LINK1: Instructions!$B$6
Name Ilist: 'A. Completeness'!$L$2:$L$3
Name Rlist: 'A. Completeness'!$M$2:$M$3
Name Ilist: 'C. Beneficiary Notification'!$L$2:$L$3
Name Rlist: 'C. Beneficiary Notification'!$M$2:$M$3
Name Ilist: 'D. Payment'!$L$2:$L$3
Name Rlist: 'D. Payment'!$M$2:$M$3
Name Ilist: 'E. Providers & Network'!$L$2:$L$3
Name Rlist: 'E. Providers & Network'!$M$2:$M$3
Name Ilist: 'F. Coverage'!$L$2:$L$3
Name Rlist: 'F. Coverage'!$M$2:$M$3
Name Ilist: 'G. Quality and UM'!$L$2:$L$3
Name Rlist: 'G. Quality and UM'!$M$2:$M$3
Name Ilist: 'H. Grievances and Appeals'!$L$2:$L$3
Name Rlist: 'H. Grievances and Appeals'!$M$2:$M$3
Name Ilist: 'I. Program Integrity'!$L$2:$L$3
Name Rlist: 'I. Program Integrity'!$M$2:$M$3
Name Ilist: 'J. General Terms and Conditions'!$L$2:$L$3
Name Rlist: 'J. General Terms and Conditions'!$M$2:$M$3
Name Ilist: 'K. Health Information Systems'!$L$2:$L$3
Name Rlist: 'K. Health Information Systems'!$M$2:$M$3

Sheet Table of Contents
A1: Table of Contents
A2: Instructions
A3: Cover Sheet
A4: Contract Completeness
A5: I.A.1 Contract Completeness
A6: Enrollment and Disenrollment
A7: I.B.1 No Discrimination
A8: I.B.2 Choice of Doctor
A9: I.B.3 Opt-Out
A10: I.B.4 Reenrollment
A11: I.B.5 Disenrollment
A12: I.B.6 Disenrollment Request Process
... A100: Glossary

Sheet Instructions
A1: Instructions
A2: Note to Analysts | B2: Regulations at 42 Code of Federal Regulations (CFR) 438.3(a) specify that the Centers for Medicare & Medicaid Services (CMS) must review and approve all managed care organization (MCO), prepaid inpatient health plan (PIHP), and prepaid ambulatory health plan (PAHP) contracts, including those risk and non-risk contracts that, on the basis of their value (less than $1,000,000) are not subject to prior approval requirements in 42 CFR 438.806. 42 CFR 438.3(r) requires CMS review and approval of primary care case management (PCCM) entity contracts for provisions related to 42 CFR 438.3(q), 42 CFR 438.10 and 42 CFR 438.310(c)(2). The CMS Contract Checklist is intended for use by Division of Managed Care Operations (DMCO) staff in evaluating state Medicaid managed care contracts. The checklist contains references and contract requirements collected from the CFR, State Medicaid Director (SMD) letters, the Social Security Act (the Act), the American Reinvestment and Recovery Act of 2009 (ARRA), and the Patient Protection and Affordable Care Act (ACA). The citations are arranged in order of precedence, with the statutory cite being primary.
A3: Getting Started | B3: Complete the cover sheet in its entirety before moving on to the other tabs. If prompted in the Excel header, please select “enable editing” or “enable content” to enable the functionality in this workbook.
A4: Reminder | B4: NEVER copy and paste information from one cell into another cell. This will cause issues with functionality and create errors.
A5: Cover Sheet
A6: About this Review | B6: Based on the information the analyst enters on the cover sheet, the Excel spreadsheet will shade out requirements that are not applicable to the contract action. Please follow the instructions in the cover sheet to fill in all applicable information.
B7: Does the contract cover Medicaid or both Medicaid and CHIP? (cell B4). Please select "Medicaid" if the managed care contract covers only Medicaid enrollees, including Medicaid expansion CHIP (Title XIX) enrollees. Select "Both" if the contract covers both Medicaid and separate CHIP enrollees.
B8: Type of Review (cell B6). Select either base contract or contract amendment.
B9: Start Date of Review (cell B7). The date of review must be entered for every review.
B10: Medicaid Federal Operating Authority(ies) (cell B10). Choose all options that apply: 1915(a)(1)(A) voluntary, State Plan Amendment (Title XIX), 1915(b) waiver, 1115 waiver, and/or Other.
B11: Type of Entity (cell B13-B18). Select the appropriate entity type(s): MCO, health insuring organization (HIO), PIHP, PAHP, non-emergency medical transportation (NEMT) PAHP, or PCCM entity. When an analyst selects an entity type, the tool will shade out any items that do not apply to that entity type. For example, if the analyst selects PIHP, the tool will shade out any requirements that do not apply to PIHPs. Note: 42 CFR Part 438 does not require CMS review and approval of PCCM managed care contracts.
B12: Is the entity risk-bearing or non-risk bearing? (cell B19). MCOs are always risk bearing in accordance with 42 CFR 438.2 and 42 CFR 457.10; however, for non-risk bearing entities, the managed care plan (MCP) is not at financial risk for changes in utilization or for costs that do not exceed the upper payment limits. Therefore, PIHPs, PAHPs, and NEMT PAHPs may be risk-based or non-risk-based. Note: This field must be completed in every review for the base and amendment start and end date features to function correctly.
B13: Base Contract Period Start and End Dates (cells B21 and B22). The base contract start and end dates must be entered in every review (including reviews of contract amendments). If the contract action implements a contract extension, the base contract end date entered should be the date on which the extension period ends.
B14: Amendment Start and End Dates (cells B23 and B24). The amendment start and end dates must be entered in every review of a contract amendment(s) to determine whether requirements effective after a certain date should be evaluated or shaded out. If the contract amendment implements a contract extension, the amendment end date should be the date on which the extension period ends. If the contract amendment has no end date, the amendment end date entered should be the date on which the base contract ends.
B15: Rating Period Start and End Dates (cells B25 and B26). A rating period start date and rating period end date must be entered for all risk-based Medicaid managed care contract reviews to determine whether requirements that phase in after a certain date should be evaluated or shaded out. For contract actions that do not implement rates, the rating period start and end dates should reflect the annual rating period during which the start date of the contract action falls. Example: If a state uses a July–June annual rating period and executes a contract action to modify access requirements effective 10/01/17, a rating period start date of 07/01/17 and a rating period end date of 06/30/18 should be entered. For non-risk based contracts, enter "N/A" in this field.
B16: Is this an entirely new managed care program? (cell B27). For new managed care programs, a comprehensive review of the contract must be completed. If it is not a new managed care program and a comprehensive review has been completed within the past five years, a streamlined review may be completed.
B17: Has it been more than five years since the last comprehensive review? (cell B28). For contracts that have not had a comprehensive review within the past five years, a comprehensive review must be completed. If a comprehensive review has been completed within the past five years and it is not a new managed care program, a streamlined review may be completed.
B18: Comprehensive Review or Streamlined Review? (cell B29). Denotes whether the review will be a comprehensive or streamlined review.
A19: Status of Review by Section Dashboard | B19: (Cells B29-C41): This section indicates the status of the Medicaid requirements in each tab of the checklist. This section is intended to help the analyst completing this checklist review which tabs they have completed, and which tabs remain to be completed. The status section is intended primarily to support the review of entire contracts. If the analyst is completing a review of an amendment, only the provisions pertaining to the amendment should be completed. The Medicaid requirements status is populated based on the analyst’s progress through tab A–K of the checklist. The "Decision" fields in tabs A–K (columns G and H in the upper right-hand corner of each tab) determine the statuses that appear in the Status of Review by Section Dashboard. Status options include: "Not started", "Revisions needed", "Section review N/A", or "Approved". Note that entire sections of the checklist may be “N/A.”
A20: Tabs A–K
A21: Status Indicators
A22: Status of Medicaid Section | B22: A group of cells in the upper right-hand corner of sections A–K of the checklist display an analyst's progress through each tab, and its outcome (i.e., “decision”). Status of Medicaid Section: The "Status of Section" fields indicate an analyst’s progress through the Medicaid requirements within the tab. This tab will display one of the following values: “Not Started”, “In Progress”, “Section Review Complete”, or “Section Review N/A”. In most cases, when at least one field in column E contains a valid value, the "Status of Section Review" will change from “Not Started” to “In Progress." Completing tabs A–K. The “Status of Section” indicator will display “Section Review Complete” when all requirements in the section are: (1) Marked as “Met” with appropriate documentation provided within the “Where Found” cell; (2) Marked as “N/A” with appropriate documentation provided within the “General Comments” cell; documentation should describe why a given requirement is not applicable to the managed care contract; (3) Marked as "Unsure" with information provided in the "Follow-up Required" cell; or (4) Marked as "Not met" with information provided in the "Follow-up Required" cell. In tab A (Completeness), options of "Yes", "No", and "No, submission is in draft" are also available. (5) For "Yes", information must be provided in the "Where found" cell. (6) For "No" and "No, submission is in draft", information must be provided in the "Follow-up Required" cell.
A23: Status of Medicaid Decision | B23: Medicaid Decision. While a section is “In Progress” or “Not Started,” the “Medicaid Decision" fields will mirror the Status of Medicaid Review. Once the review is complete (meaning a status and any required detail has been entered for every requirement, as described in Status Indicators: (1) Status of Medicaid Section), the “Medicaid Decision" fields will display one of the following statuses: (1) “Approved” if all of the status fields are: (a) Marked "Met" or "Yes" with appropriate documentation provided within the “Where Found” cell; or (b) Marked as “N/A” with appropriate documentation provided within the “General Comments” cell; documentation should describe why a given requirement is not applicable to the managed care contract. (2) “Revisions needed,” if the status fields contain at least one instance of a requirement that is "Not met" or "Unsure."
A24: Column Descriptions
A25: (A) Item | B25: Item number aligns with the numbering in the State Guide to CMS Requirements for Medicaid Managed Care Contract Review and Approval.
A26: (B) Legal Cite | B26: Statutory and regulatory citations that further clarify the requirement are listed in this column. Other citations, such as SMD letters, are listed below the statutory and regulatory references so that an evaluator may refer to other resources for further clarification.
A27: (C) Requirement | B27: Includes the statutory and/or regulatory language for each legal citation.
A28: (D) Tip | B28: Some items have tips that provide more information about the requirement.
A29: (E) Status | B29: Choices include "Met", "Not met", "Unsure", or "N/A" for each requirement. If the row is shaded out, the requirement does not apply and the analyst will be unable to select a status. A section of the checklist will not be listed as “Complete” unless each requirement within that section is either: (1) marked as “Met” with appropriate documentation provided within the “Where Found” cell; (2) marked as “N/A” with appropriate documentation provided within the “General Comments” cell describing why a given requirement is not applicable to the managed care contract; (3) marked as "Unsure" with information provided in the "Follow-up Required" cell; or (4) marked as "Not met" with information provided in the "Follow-up Required" cell. In tab A (Completeness), options of "Yes", "No", and "No, submission is in draft" are also available. For "Yes", information must be provided in the "Where Found" cell. For "No" and "No, submission is in draft", information must be provided in the "Follow-up Required" cell. In some circumstances, information in the cover sheet will allow analysts to mark entire sections as “N/A.” For example, this option appears when the section requirements do not apply to the “Type of Entity." Analysts must verify whether any items in the section are applicable before selecting “N/A” for a given section.
A30: (F) Where Found | B30: Analysts may use this column to fill in the contract section and page number (or other citation) that indicates or provides documentation that the requirement has been met. Page numbers can change between different versions of the same contract, so using section references is preferred. This documentation is required for a given federal requirement to be appropriately considered “Met.”
A31: (G) Follow-up Required | B31: Analysts may use this column to include notes on any follow-up actions needed to bring a requirement from "Unsure" or "Not met" to "Met." If a given requirement is listed as "Not met" or "Unsure", the analyst must provide information in this column.
A32: (H) General Comments | B32: Analysts may use this column to record any additional notes that have not been captured elsewhere. If a given requirement is listed as “N/A", the analyst must use this column to document the rationale for indicating that the requirement is not applicable.
A33: (C:3) Marking an Entire Tab as "N/A" | B33: Tabs B–K have a field in A3 that reads: “Mark all requirements as “N/A?” There are two potential corresponding values in cell C3: (1) “No, section requirements must be reviewed” or (2) “yes, section requirements are not applicable.” Note that option (1) “No, section requirements must be reviewed” is the default value and option (2) “yes, section requirements are not applicable” must be selected in order to mark the entire tab as "N/A."
A34: General Guidance for Using the Checklist
A35: Model Contracts | B35: If the state uses a model contract with multiple contractors, the lead analyst may complete a single review tool. However, if the start dates differ amongst contractors, analysts should complete a separate review tool for each start date to ensure all newly effective requirements are captured in the review.
A36: Summary of Review | B36: Run the summary by following the instructions at the top of the page. The summary provides a list of all "Unsure" and "Unmet" provisions. These items should be followed up on immediately with the state and monitored for additional follow-up action as needed.
A37: Guidance for Evaluating Contracts | B37: In each applicable tab A–K, analysts should evaluate the contract language and compare it to the “Requirement” column (C) in the table to determine whether the required language is contained in the contract. Column “Where Found” (F) is provided for the analyst's use in noting where the required language is found in the contract or other document. If the language is present and fulfills the requirement, analysts should use the drop-down “Status” menus (Column E) to select "Met" in the appropriate row. If the language is absent, evaluators should select "Not met" or indicate that they are "Unsure" and enter information in the "Follow-up Required” column (G). Resolution of issues concerning absent or incomplete requirements is left up to the discretion of the evaluation team. Note: Because the statements referred to in this checklist are federal requirements, it is not sufficient to have generic contract language saying the contractor must comply with all federal statutes and regulations. Where any discrepancies exist between an SMD or State Health Official (SHO) letter and the Medicaid/CHIP managed care regulations, regulations supersede the SMD and SHO letter. All items in this checklist are applicable to the designated entity types regardless of the operating authority in effect unless the requirement is specifically waived in the authorizing documents, including the state plan or a waiver.
A38: Tips & Comment Flags | B38: Within each tab of the checklist, some items may have tips that provide more information about a requirement. Tips should be reviewed by the analyst when evaluating a particular item. Tips are noted with a numeric citation in column D and are linked to the corresponding tip at the bottom of the tab. If a cell contains a comment flag, it will be indicated by a red triangle in the upper right hand corner of a given cell. Content for comment flags will display when a user hovers the mouse over the cell. To view all comments, a user can right-click on the tab and select "Show/Hide Comments."
A39: Changing Cell Size to Show Text | B39: Column widths are fixed. However, analysts may modify row heights to show any hidden text in a cell or to show text that analysts have entered in the checklist.
A40: Glossary | B40: A glossary tab provides definitions of commonly used terms and acronyms.

Sheet Cover Sheet
A1: CMS Review Tool for Medicaid Managed Care Contract Approval | F1: Values for Form Fields - Do not modify | M1: Headers for B15:18 | N1: =IF($B$19="Non-risk","(Placeholder)",IF($B$19="Risk","Rating Period Start Date","(Type of Review not selected)")) | O1: Headers for A21:A22
F2: Base contract | G2: state | H2: 1915(a)(1)(A) voluntary | I2: Draft | J2: MCO | K2: Approved | L2: Risk | M2: =IF($B$6="Base contract","Base Contract Effective Date (Required, if not crosshatched)",IF($B$6="Streamlined","Base Contract Effective Date (Required, if not crosshatched)",IF($B$6="Contract amendment","Base Contract Effective Date (Required, if not crosshatched)","(Type of Review not selected) (Required, if not crosshatched)"))) | N2: =IF($B$19="Non-risk","(Placeholder)",IF($B$19="Risk","Rating Period End Date","(Type of Review not selected)")) | O2: =IF($B$4="Both", "(Placeholder)", "Rating Period Start Date (Required, if not crosshatched)")
A3: About this Review | B3: Complete the boxes below. Select from drop-down menu where applicable | C3: Analyst Notes | D3: Description/Instructions | F3: Contract amendment | G3: Alabama | H3: State Plan Amendment (Title XIX) | I3: Executed | J3: HIO | K3: Revisions needed | L3: Non-risk | M3: =IF($B$6="Base contract","Base Contract End Date (Required, if not crosshatched)",IF($B$6="Streamlined","Base Contract End Date (Required, if not crosshatched)",IF(OR($B$6="Contract amendment","Streamlined"),"Base Contract End Date (Required, if not crosshatched)","(Type of Review not selected) (Required, if not crosshatched)"))) | O3: =IF($B$4="Both", "(Placeholder)", "Rating Period End Date (Required, if not crosshatched)")
A4: Does the contract cover Medicaid or both Medicaid and CHIP? (Required) | B4: Both | D4: Select “Medicaid” if the managed care contract covers only Medicaid enrollees, including Medicaid expansion CHIP (Title XIX) enrollees. Select “Both” if the contract covers both Medicaid and separate CHIP enrollees. | G4: Alaska | H4: 1115 waiver | J4: PIHP | M4: =IF($B$6="Base contract","(Placeholder)",IF($B$6="Contract amendment","Contract Amendment Effective Date (Required, if not crosshatched)",IF($B$6="Streamlined","Contract Amendment Effective Date (Required, if not crosshatched)","(Type of Review not selected) (Required, if not crosshatched)")))
A5: Reviewer | D5: Enter each reviewer's first and last name. | G5: Arizona | H5: 1915(b) waiver | J5: PAHP | M5: =IF($B$6="Base contract","(Placeholder)",IF($B$6="Contract amendment","Contract Amendment End Date (Required, if not crosshatched)",IF($B$6="Streamlined","Contract Amendment End Date (Required, if not crosshatched)","(Type of Review not selected) (Required, if not crosshatched)")))
A6: Type of Review (Required) | D6: A base contract is the state's full contract with an MCP; a contract amendment changes an existing base contract. | G6: Arkansas | H6: Other | J6: NEMT PAHP
A7: Start Date of Review (Required if not crosshatched) | D7: Enter date in 00/00/0000 format. | G7: California | H7: State Plan Amendment (Title XXI) | J7: PCCME
A8: State | D8: Select name of state. | G8: Colorado | H8: 1115 waiver | M8: =IF(OR($B$4="Both"),"Both","Medicaid")
A9: Name of Program(s) | D9: Enter the name of the program(s) included in this contract. | G9: Connecticut | J9: Yes
A10: Medicaid Federal Operating Authority (select all that apply) | D10: Select the Medicaid federal operating authority. | G10: Delaware | J10: No
A11: Contract Start Date | D11: The date on which the full contract began/will begin. If the contract being submitted for review is an amendment to an existing contract, the start date is the date on which the amendment will/did go into effect. | G11: Dist. of Col.
A12: Name of Model Contract/Name of MCP | D12: Enter "model contract" if the state uses this same contract language for more than one MCP contract. If the contract language is unique, enter the name of the MCP. | G12: Florida
A13: Does the contract apply to an MCO? | B13: Yes | D13: An MCP that has, or is seeking to qualify for, a comprehensive risk contract. | G13: Georgia
A14: Does the contract apply to an HIO? | D14: With the exception of California, please select “No” under the drop-down menu. A county operated MCP that, in exchange for capitation payments, covers services for beneficiaries. | G14: Hawaii
A15: Does the contract apply to a PIHP? | D15: An MCP that provides inpatient hospital or institutional services, does not have a comprehensive risk contract, and receives capitation payments or other payment arrangements that do not use state plan rates. | G15: Idaho
A16: Does the contract apply to a PAHP? | D16: An MCP that provides services, but is not responsible for inpatient hospital or institutional services and receives capitation payments, or other payment arrangements that do not use state plan rates. | G16: Illinois
A17: Does the contract apply to a NEMT PAHP? | D17: An MCP that provides only NEMT services to enrollees, and receives capitation payments, or other payment arrangements that do not use state plan rates. | G17: Indiana
A18: Does the contract apply to a PCCM Entity? | D18: An MCP that provides services as defined in regulation in addition to PCCM services for the state. | G18: Iowa | M18: Yes
A19: Is MCP risk-bearing or non-risk bearing? (Required) | D19: MCOs are always risk bearing in accordance with 42 CFR 438.2 and 42 CFR 457.10. PIHPs, PAHPs, and NEMT PAHPs may be risk-based or non-risk-based. This does not need to be completed for PCCM-entity. | G19: Kansas | M19: No
A20: Type of Contract (Required) | D20: Is the contract in draft form or has it been executed? | G20: Kentucky
A21: =M2 | D21: The date on which the base contract begins. | G21: Louisiana | M21: Comprehensive Review
A22: =M3 | D22: The date on which the base contract ends. | G22: Maine | M22: Streamlined Review
A23: =M4 | D23: The date on which the contract amendment begins. | G23: Maryland
A24: =M5 | D24: The date on which the contract amendment ends. | G24: Massachusetts
A25: Rating Period Start Date | D25: The date on which the associated contract rating period begins. For contract actions that do not implement rates, the rating period start and end dates should reflect the annual rating period during which the start date of the contract action falls. | G25: Michigan
A26: Rating Period End Date | D26: The date on which the associated contract rating period ends. | G26: Minnesota
A27: Is this an entirely new managed care program? (Required) | D27: Comprehensive review is required for new managed care programs. | G27: Mississippi
A28: Has it been more than five years since the last comprehensive review was completed? (Required) | D28: Comprehensive review is required for contracts that have not had a comprehensive review within the past five years. | G28: Missouri
A29: Comprehensive Review or Streamlined Review? (Required) | D29: Denotes whether the review will be a comprehensive or streamlined review. | G29: Montana
G30: Nebraska
A31: Status of Review by Section Dashboard | B31: Medicaid Requirements | C31: (Please provide additional comments) | G31: Nevada
B32: (Status/Decision fields below will update automatically) | G32: Ohio
A33: A. Completeness | B33: ='A. Completeness'!$H$3 | G33: Oklahoma
A34: B. Enrollment and Disenrollment | B34: ='B. Enrollment & Disenrollment'!H3 | G34: Oregon
A35: C. Beneficiary Notification | B35: ='C. Beneficiary Notification'!$H$3 | G35: Pennsylvania
A36: D. Payment | B36: ='D. Payment'!$H$3 | G36: Puerto Rico
A37: E. Providers and Provider Networks | B37: ='E. Providers & Network'!H3 | G37: New Hampshire
A38: F. Coverage | B38: ='F. Coverage'!H3 | G38: New Jersey
A39: G. Quality and Utilization Management (UM) | B39: ='G. Quality and UM'!H3 | G39: New Mexico
A40: H. Grievances and Appeals | B40: ='H. Grievances and Appeals'!H3 | G40: New York
A41: I. Program Integrity | B41: ='I. Program Integrity'!H3 | G41: North Carolina
A42: J. General Terms and Conditions | B42: ='J. General Terms and Conditions'!H3 | G42: North Dakota
A43: K. Health Information Systems and Enrollee Data | B43: ='K. Health Information Systems'!H3 | G43: Rhode Island
A44: Checklist version date: 1/24/2022; revised 9/3/2024 | G44: South Carolina
A45: Password for corresponding locked checklist: mmc2019 | G45: South Dakota
G46: Tennessee
G47: Texas
G48: Utah
G49: Vermont
G50: Virginia
G51: Washington
G52: West Virginia
G53: Wisconsin
G54: Wyoming
F66: *

Sheet A. Completeness
A1: Subpart A - Contract Completeness | J1: Met | L1: Yes | M1: =IF($C$2="Base contract","Blist",IF($C$2="Contract Amendment","Alist")) | V1: Risk v non-risk? | Z1: This contract applies to the following entity types | AH1: Contract/RP start dates NOT supplied in cover sheet? | AI1: Contract Period Start Date | AJ1: Rating Period Start Date | AK1: Review date NOT supplied in cover sheet | AL1: Review Date | AP1: Does the review include Medicaid and CHIP? | AV1: N/A
A2: Type of Review: | C2: ='Cover Sheet'!B6 | G2: Status of Medicaid Section: | H2: =I2 | I2: =IF(OR($C$3="Yes, section requirements are not applicable",$C$3="Yes, all requirements on the sheet are crosshatched"),"Section Review N/A",IF((COUNTA(A9:A32)+COUNTBLANK(A9:A32)=COUNTBLANK(E9:E32)),"Not Started",IF((COUNTA(A9:A32)>SUM(U9:U32)),"In Progress","Section Review Complete"))) | J2: Unsure | K2: Yes, section requirements are not applicable | L2: No | V2: ='Cover Sheet'!B19 | Z2: =IF('Cover Sheet'!$B$13="Yes","MCO","--") | AA2: =IF('Cover Sheet'!$B$14="Yes","HIO","--") | AB2: =IF('Cover Sheet'!$B$15="Yes","PIHP","--") | AC2: =IF('Cover Sheet'!$B$16="Yes","PAHP","--") | AD2: =IF('Cover Sheet'!$B$17="Yes","NEMT PAHP","--") | AE2: =IF('Cover Sheet'!$B$18="Yes","PCCME","--") | AK2: =IF('Cover Sheet'!$B$7="",TRUE,FALSE) | AL2: =IF($AK$2=FALSE,'Cover Sheet'!$B$7,"") | AP2: =IF('Cover Sheet'!$B$4="BOTH",1,0)
A3: Mark all requirements as "N/A"? | C3: No, section requirements must be reviewed | G3: Medicaid Decision: | H3: =I3 | I3: =IF(OR($C$3="Yes, section requirements are not applicable",$C$3="Yes, all requirements on the sheet are crosshatched"),"Section Review N/A",IF((COUNTA(A9:A32)+COUNTBLANK(A9:A32))=COUNTBLANK(E9:E32),"Not Started",IF(OR(COUNTA(A9:A32)+COUNTBLANK(A9:A32)<>COUNTIF(E9:E32,"Yes")+COUNTIF(E9:E32,"Met")+COUNTIF(E9:E32,"N/A")+COUNTBLANK(E9:E32),COUNTA(A9:A32)<>SUM(U9:U32)),"Revisions Needed","Approved"))) | J3: Not met | K3: No, section requirements must be reviewed | L3: No, submission is in draft
J4: N/A | K4: Yes, all requirements on the sheet are crosshatched | L4: N/A
S5: _EFFECTIVE | AV5: Medicaid_Only
P6: Std type (EXISTING or NEW) | Q6: List | R6: NR Ind | AK6: (b4) Reasons to Crosshatch | AS6: For logic check only:
A7: Item | B7: Legal Cite | C7: Requirement | D7: Tip | E7: Status | F7: Where Found | G7: Follow-up Required | H7: General Comments | I7: MCO | J7: HIO | K7: PIHP | L7: PAHP | M7: NEMT PAHP | N7: PCCM | O7: PCCME | S7: Effective | T7: Contract start date (DATE) or rating period start date (RP)? | U7: Row Completed? (1 if status = Unsure; status = Met and column G <>blank; or status = Not Met and column I<>not blank; OR parallel medicaid requirement = Met) | V7: If risk, use RP effective date. If non-risk, use CY date. | W7: Entire section marked NA | X7: Shaded | Y7: Entity Not Applied | AF7: If CHIP linking and no information in rows with gray shading in columns E through H; code as complete. If rows with gray shading have information in one or more cells, the status of the row will be counted as if gray shading did not appear. (See Column Descriptions for more information) | AG7: (a) Crosshatch b/c entity type not applicable? (True=Yes,False=No) | AH7: (b1) Crosshatch b/c requirement not in effect? Default is DO NOT crosshatch; if values in the following columns = TRUE, apply crosshatching | AI7: (b2a) Reason Exists To Not Crosshatch? Will be TRUE if Missing Any dates. | AJ7: (b2b) Reason Exists To Crosshatch? | AK7: (b4a) ''DATE" - Effective Date of Req > Contract Period Start Date | AL7: (b4b) "RP" - Effective Date of Req > Rating Period Start Date | AM7: (b4d) TRUE - Non-Risk in cover sheet and indicator=1 | AN7: (b4c) Section I vs II | AO7: CHIP Requirement | AP7: Does the CHIP section have a corresponding Medicaid section (Yes=1) | AQ7: If yes, link the Medicaid section item: | AR7: If yes, link the Medicaid Requirement: | AS7: Is the text the exact same? | AT7: Shading code | AU7: section1_no_link | AV7: Medicaid_Only | AW7: Linked Medicaid Requirement Status | AX7: Linked Medicaid Requirement Where Found | AY7: Linked Medicaid Requirement Followup Required | AZ7: Linked Medicaid General Comments | BA7: Row Started (1 if row has been started) | BB7: Requirement Met | BC7: All Required Medicaid Cols Filled (1=True) | BD7: Contract start date (DATE) or rating period start date (RP)? | BE7: Streamlined | BF7: Rating Period
C8: I.A.1 Contract Completeness | Z8: MCO | AA8: HIO | AB8: PIHP | AC8: PAHP | AD8: NEMT PAHP | AE8: PCCME
A9: I.A.1.01 | B9: N/A | C9: The contract submission is signed and dated by all parties. | F9: Source: CN-680000-FP122: 24 | H9: Recommendation: MET Response: The contract explicitly states that it is not valid until signed and dated by both parties. This indicates that the requirement for the contract submission to be signed and dated by all parties is met. Evidence: - "**IN WITNESS THEREOF,** the Parties hereto have caused this five hundred twenty-seven (527) page Contract, which includes any referenced attachments, to be executed by their undersigned officials as duly authorized. This Contract is not valid until signed and dated by both Parties." [CN-680000-FP122: 24] | I9: MCO | J9: HIO | K9: PIHP | L9: PAHP | M9: NEMT PAHP | O9: PCCME | P9: EXISTING | Q9: =IF(OR(AND($C$2="Base contract",$C$3="No, section requirements must be reviewed",$AG9=FALSE, $AH9=FALSE),AND($C$2="Contract amendment",$C$3="No, section requirements must be reviewed",$AG9=FALSE,$AH9=FALSE)),"YNNN") | U9: =IF(OR($E$8="N/A",AND(E9="Yes",F9<>""),AND(E9="N/A",H9<>""),AND(E9="Met",F9<>""),AND(E9="Not met",G9<>""),AND(E9="Unsure",G9<>""),AND(E9="N/A"),AND(E9="No",G9<>""),AND(E9="No, submission is in draft",G9<>""),AND(R9=1),AND(Y9=TRUE)),1,0) | W9: =IF($C$3="Yes, section is not applicable","TRUE","FALSE") | X9: =IF(OR(Y9=TRUE),TRUE,FALSE) | Y9: =IF(SUM(Z9:AE9)<1,TRUE,FALSE) | Z9: =IF($Z$2=I9,1,0) | AA9: =IF($AA$2=J9,1,0) | AB9: =IF($AB$2=K9,1,0) | AC9: =IF($AC$2=L9,1,0) | AD9: =IF($AD$2=M9,1,0) | AE9: =IF($AE$2=O9,1,0) | AM9: =IF(AND('Cover Sheet'!$B$19="Non-Risk",$R9=1),TRUE,FALSE) | AN9: =IF(AND($H$6="Medicaid",MID($A9,1,FIND(".",$A9,1)-1)="II"),TRUE,FALSE) | AV9: =IF(AU9=1,1,"") | BE9: 0
A10: I.A.1.02 | B10: N/A | C10: The contract submission is complete, meaning: • All pages, appendices, attachments, etc. were submitted to CMS. • Any documents incorporated by reference (including, but not limited to, state statute, state regulation, or other binding document, such as a member handbook) to comply with federal regulations and the requirements of this review tool were submitted to CMS. | F10: Source: CN-680000-FP122: 23, 24 | Attachment - Core Contract Provisions 02012025: 242 | CN-680000-FP122: 302, 467, 72, 539 | H10: Recommendation: UNCLEAR Response: The retrieved text does not provide explicit evidence that all pages, appendices, attachments, and documents incorporated by reference were submitted to CMS. While the contract mentions that it includes all terms and conditions agreed upon by the Parties and references attachments, it does not confirm that these were submitted to CMS. Additionally, there is no explicit mention of documents incorporated by reference being submitted. Evidence: - "This Contract and its attachments as referenced herein contain all the terms and conditions agreed upon by the Parties." [CN-680000-FP122: 23] - "List of Attachments included as part of this Contract:" [CN-680000-FP122: 24] - "**IN WITNESS THEREOF,** the Parties hereto have caused this five hundred twenty-seven (527) page Contract, which includes any referenced attachments, to be executed by their undersigned officials as duly authorized. This Contract is not valid until signed and dated by both Parties." [CN-680000-FP122: 24] | I10: MCO | J10: HIO | K10: PIHP | L10: PAHP | M10: NEMT PAHP | O10: PCCME | P10: EXISTING | Q10: =IF(OR(AND($C$2="Base contract",$C$3="No, section requirements must be reviewed",$AG10=FALSE, $AH10=FALSE),AND($C$2="Contract amendment",$C$3="No, section requirements must be reviewed",$AG10=FALSE,$AH10=FALSE)),"YNNN") | U10: =IF(OR($E$8="N/A",AND(E10="Yes",F10<>""),AND(E10="N/A",H10<>""),AND(E10="Met",F10<>""),AND(E10="Not met",G10<>""),AND(E10="Unsure",G10<>""),AND(E10="N/A"),AND(E10="No",G10<>""),AND(E10="No, submission is in draft",G10<>""),AND(R10=1),AND(Y10=TRUE)),1,0) | X10: =IF(OR(Y10=TRUE),TRUE,FALSE) | Y10: =IF(SUM(Z10:AE10)<1,TRUE,FALSE) | Z10: =IF($Z$2=I10,1,0) | AA10: =IF($AA$2=J10,1,0) | AB10: =IF($AB$2=K10,1,0) | AC10: =IF($AC$2=L10,1,0) | AD10: =IF($AD$2=M10,1,0) | AE10: =IF($AE$2=O10,1,0) | AM10: =IF(AND('Cover Sheet'!$B$19="Non-Risk",$R10=1),TRUE,FALSE) | AN10: =IF(AND($H$6="Medicaid",MID($A10,1,FIND(".",$A10,1)-1)="II"),TRUE,FALSE) | AV10: =IF(AU10=1,1,"") | BE10: 0
A11: N/A | B11: N/A | C11: If the contract submission is an amendment, CMS has approved the base contract, and all previous amendments have been approved that are related to or modifying the same provision(s), or are assumed to be implemented. | D11: 1 | F11: Source: CN-680000-FP122: 236, 236, 286 | Attachment - Core Contract Provisions 02012025: 175, 175, 217, 226 | H11: Recommendation: UNCLEAR Response: The retrieved text mentions that the Agency may amend and use CMS-approved rates and that any amendment to the contract must be in writing. However, there is no explicit statement that CMS has approved the base contract and all previous amendments related to or modifying the same provision(s). Therefore, it is unclear whether the requirement is met. Evidence: - 'he Agency may amend and use the CMS-approved rates by notice to the Managed Care Plan through an amendment to this Contract.' [CN-680000-FP122: 236] - 'The Agency may use, or may amend and use these rates, only after certification by its actuary and approval by CMS.' [CN-680000-FP122: 236] - 'This Contract shall be amended only as follows (unless specified elsewhere in this Contract): a. The parties cannot amend or alter the terms of this Contract without a written amendment and/or change order to this Contract.' [CN-680000-FP122: 286] | I11: MCO | J11: HIO | K11: PIHP | L11: PAHP | M11: NEMT PAHP | O11: PCCME | P11: EXISTING | Q11: =IF(OR(AND($C$2="Base contract",$C$3="No, section requirements must be reviewed",$AG11=FALSE, $AH11=FALSE),AND($C$2="Contract amendment",$C$3="No, section requirements must be reviewed",$AG11=FALSE,$AH11=FALSE)),"YNNN") | U11: =IF(OR($E$8="N/A",AND(E11="Yes",F11<>""),AND(E11="N/A",H11<>""),AND(E11="Met",F11<>""),AND(E11="Not met",G11<>""),AND(E11="Unsure",G11<>""),AND(E11="N/A"),AND(E11="No",G11<>""),AND(E11="No, submission is in draft",G11<>""),AND(R11=1),AND(Y11=TRUE)),1,0) | X11: =IF(OR(Y11=TRUE),TRUE,FALSE) | Y11: =IF(SUM(Z11:AE11)<1,TRUE,FALSE) | Z11: =IF($Z$2=I11,1,0) | AA11: =IF($AA$2=J11,1,0) | AB11: =IF($AB$2=K11,1,0) | AC11: =IF($AC$2=L11,1,0) | AD11: =IF($AD$2=M11,1,0) | AE11: =IF($AE$2=O11,1,0) | AM11: =IF(AND('Cover Sheet'!$B$19="Non-Risk",$R11=1),TRUE,FALSE) | AN11: =IF(AND($H$6="Medicaid",MID($A11,1,FIND(".",$A11,1)-1)="II"),TRUE,FALSE) | AU11: 1 | AV11: =IF(AU11=1,1,"") | BE11: 0
A12: I.A.1.03 | B12: 42 CFR 438.7(a) | C12: If the contract submission implements capitation rates or a change in the contract may impact 42 CFR 438.4, CMS has received a rate certification from the state. | D12: 2,3,5,6 | F12: Source: CN-680000-FP122: 236, 175 | Attachment - Core Contract Provisions 02012025: 175, 236 | H12: Recommendation: UNCLEAR Response: The retrieved text mentions capitation rates and the need for CMS approval, but it does not explicitly state that CMS has received a rate certification from the state when capitation rates are implemented or when a change in the contract may impact 42 CFR 438.4. The text states that 'The Agency may use, or may amend and use these rates, only after certification by its actuary and approval by CMS' [1][2], but it does not confirm that CMS has received a rate certification from the state under the specified conditions. | I12: MCO | J12: HIO | K12: PIHP | L12: PAHP | P12: EXISTING | Q12: =IF(OR(AND($C$2="Base contract",$C$3="No, section requirements must be reviewed",$AG12=FALSE, $AH12=FALSE),AND($C$2="Contract amendment",$C$3="No, section requirements must be reviewed",$AG12=FALSE,$AH12=FALSE)),"YNNN") | S12: 42556 | U12: =IF(OR($E$8="N/A",AND(E12="Yes",F12<>""),AND(E12="N/A",H12<>""),AND(E12="Met",F12<>""),AND(E12="Not met",G12<>""),AND(E12="Unsure",G12<>""),AND(E12="N/A"),AND(E12="No",G12<>""),AND(E12="No, submission is in draft",G12<>""),AND(R12=1),AND(Y12=TRUE)),1,0) | X12: =IF(OR(Y12=TRUE),TRUE,FALSE) | Y12: =IF(SUM(Z12:AE12)<1,TRUE,FALSE) | Z12: =IF($Z$2=I12,1,0) | AA12: =IF($AA$2=J12,1,0) | AB12: =IF($AB$2=K12,1,0) | AC12: =IF($AC$2=L12,1,0) | AD12: =IF($AD$2=M12,1,0) | AE12: =IF($AE$2=O12,1,0) | AM12: =IF(AND('Cover Sheet'!$B$19="Non-Risk",$R12=1),TRUE,FALSE) | AN12: =IF(AND($H$6="Medicaid",MID($A12,1,FIND(".",$A12,1)-1)="II"),TRUE,FALSE) | AU12: 1 | AV12: =IF(AU12=1,1,"") | BE12: 0
A13: I.A.1.04 | B13: 42 CFR 438.7(c)(3); 42 CFR 438.7(b)(6) | C13: If the state is increasing or decreasing previously certified rates without submitting a rate certification, the rate change must be within 1.5% per rate cell of the rates previously certified for the applicable rating period, and the change that accompanies this de minimis rate change must not be for a change in special contract provisions related to payment in 42 CFR 438.6 that is applied to the contract (e.g., state directed payment). | D13: 1,2,6,7,19 | F13: Source: Attachment - Core Contract Provisions 02012025: 176, 175 | CN-680000-FP122: 237, 236, 23, 236, 175, 417 | H13: Recommendation: UNCLEAR Response: The retrieved text does not provide explicit evidence that addresses the specific conditions outlined in the requirement. The text mentions adjustments to rates and the need for certification and approval, but it does not specify the 1.5% limit or the restriction on changes to special contract provisions related to payment in 42 CFR 438.6. | I13: MCO | J13: HIO | K13: PIHP | L13: PAHP | P13: EXISTING | Q13: =IF(OR(AND($C$2="Base contract",$C$3="No, section requirements must be reviewed",$AG13=FALSE, $AH13=FALSE),AND($C$2="Contract amendment",$C$3="No, section requirements must be reviewed",$AG13=FALSE,$AH13=FALSE)),"YNNN") | U13: =IF(OR($E$8="N/A",AND(E13="Yes",F13<>""),AND(E13="N/A",H13<>""),AND(E13="Met",F13<>""),AND(E13="Not met",G13<>""),AND(E13="Unsure",G13<>""),AND(E13="N/A"),AND(E13="No",G13<>""),AND(E13="No, submission is in draft",G13<>""),AND(R13=1),AND(Y13=TRUE),X13=TRUE),1,0) | X13: =IF(OR(Y13=TRUE,BF13=0),TRUE,FALSE) | Y13: =IF(SUM(Z13:AE13)<1,TRUE,FALSE) | Z13: =IF($Z$2=I13,1,0) | AA13: =IF($AA$2=J13,1,0) | AB13: =IF($AB$2=K13,1,0) | AC13: =IF($AC$2=L13,1,0) | AD13: =IF($AD$2=M13,1,0) | AE13: =IF($AE$2=O13,1,0) | AM13: =IF(AND('Cover Sheet'!$B$19="Non-Risk",$R13=1),TRUE,FALSE) | AN13: =IF(AND($H$6="Medicaid",MID($A13,1,FIND(".",$A13,1)-1)="II"),TRUE,FALSE) | AU13: 1 | AV13: =IF(AU13=1,1,"") | BE13: 0 | BF13: =IF(BF14=1,0,1)
A14: I.A.1.04 | B14: 42 CFR 438.7(c)(3); 42 CFR 438.7(b)(6) | C14: If the state is increasing or decreasing previously certified rates without submitting a rate certification, the rate change must be within 1.5% per rate cell of the rates previously certified for the applicable rating period, and the change that accompanies this de minimis rate change must not be for a change in special contract provisions related to payment in 42 CFR 438.6 or in lieu of services and settings (ILOSs) that is applied to the contract (e.g., state directed payment). | D14: 1,2,6,7,19 | F14: Source: Attachment - Core Contract Provisions 02012025: 176, 237, 236, 175 | CN-680000-FP122: 236, 175, 417, 23 | H14: Recommendation: UNCLEAR Response: The retrieved text does not provide explicit evidence that addresses the specific conditions outlined in the requirement. The text discusses adjustments to capitation rates, but it does not specify the percentage change allowed without a rate certification or the restrictions on changes to special contract provisions related to payment. Therefore, it is unclear whether the requirement is met. | I14: MCO | J14: HIO | K14: PIHP | L14: PAHP | P14: EXISTING | Q14: =IF(OR(AND($C$2="Base contract",$C$3="No, section requirements must be reviewed",$AG14=FALSE, $AH14=FALSE),AND($C$2="Contract amendment",$C$3="No, section requirements must be reviewed",$AG14=FALSE,$AH14=FALSE)),"YNNN") | S14: 45544 | U14: =IF(OR($E$8="N/A",AND(E14="Yes",F14<>""),AND(E14="N/A",H14<>""),AND(E14="Met",F14<>""),AND(E14="Not met",G14<>""),AND(E14="Unsure",G14<>""),AND(E14="N/A"),AND(E14="No",G14<>""),AND(E14="No, submission is in draft",G14<>""),AND(R14=1),AND(Y14=TRUE),X14=TRUE),1,0) | X14: =IF(OR(Y14=TRUE,BF14=0),TRUE,FALSE) | Y14: =IF(SUM(Z14:AE14)<1,TRUE,FALSE) | Z14: =IF($Z$2=I14,1,0) | AA14: =IF($AA$2=J14,1,0) | AB14: =IF($AB$2=K14,1,0) | AC14: =IF($AC$2=L14,1,0) | AD14: =IF($AD$2=M14,1,0) | AE14: =IF($AE$2=O14,1,0) | AM14: =IF(AND('Cover Sheet'!$B$19="Non-Risk",$R14=1),TRUE,FALSE) | AN14: =IF(AND($H$6="Medicaid",MID($A14,1,FIND(".",$A14,1)-1)="II"),TRUE,FALSE) | AU14: 1 | AV14: =IF(AU14=1,1,"") | BE14: 0 | BF14: =IF('Cover Sheet'!$B$25>=S14,1,0)
A15: I.A.1.05 | B15: 42 CFR 438.4(c)(2)(iii) | C15: If the state is increasing or decreasing rates within a previously certified rate range without submitting a rate certification, the rate change must be within 1% per rate cell within the rate range previously certified for the applicable rating period in accordance with the requirements in 42 CFR 438.4(c)(2)(iii). | D15: 8,9,10,19 | F15: Source: Attachment - Core Contract Provisions 02012025: 176, 237 | CN-680000-FP122: 236, 237 | H15: Recommendation: UNCLEAR Response: The retrieved text does not provide explicit evidence regarding the specific requirement that rate changes within a previously certified rate range must be within 1% per rate cell without submitting a new rate certification. The text mentions adjustments to capitation rates and the need for proper execution of amendments, but it does not specify the percentage limit for rate changes or the conditions under which these changes can be made without a new certification. Therefore, it is unclear whether the requirement is met based on the provided context. | I15: MCO | J15: HIO | K15: PIHP | L15: PAHP | P15: NEW | Q15: =IF(OR(AND($C$2="Base contract",$C$3="No, section requirements must be reviewed",$AG15=FALSE, $AH15=FALSE),AND($C$2="Contract amendment",$C$3="No, section requirements must be reviewed",$AG15=FALSE,$AH15=FALSE)),"YNNN") | R15: =IF('Cover Sheet'!$B$19="Non-Risk",1) | S15: 44378 | T15: RP | U15: =IF(OR($E$8="N/A",AND(E15="Yes",F15<>""),AND(E15="N/A",H15<>""),AND(E15="Met",F15<>""),AND(E15="Not met",G15<>""),AND(E15="Unsure",G15<>""),AND(E15="N/A"),AND(E15="No",G15<>""),AND(E15="No, submission is in draft",G15<>""),AND(R15=1),AND(Y15=TRUE)),1,0) | V15: =IF(AND($V$2="Non-risk",T15="RP"),"DATE",T15) | X15: =IF(OR(Y15=TRUE),TRUE,FALSE) | Y15: =IF(SUM(Z15:AE15)<1,TRUE,FALSE) | Z15: =IF($Z$2=I15,1,0) | AA15: =IF($AA$2=J15,1,0) | AB15: =IF($AB$2=K15,1,0) | AC15: =IF($AC$2=L15,1,0) | AD15: =IF($AD$2=M15,1,0) | AE15: =IF($AE$2=O15,1,0) | AI15: =IF(OR($AH$2=TRUE,AND('Cover Sheet'!$B$19="Risk")),TRUE,"") | AJ15: =IF(OR(AK15=TRUE,AL15=TRUE,AM15=TRUE,AN15=TRUE),TRUE,"") | AK15: =IF(V15="DATE",IF($AH$2=FALSE,IF(S15>$AI$2,TRUE,"ReqEffectiveEarlierThanContractDate"),"Dates Missing"),"Not DATE") | AL15: =IF(V15="RP",IF($AH$2=FALSE,IF(S15>$AJ$2,TRUE,"ReqEffectiveEarlierThanRatePeriodStartDate"),"Dates Missing"),"Not RP") | AM15: =IF(AND('Cover Sheet'!$B$19="Non-Risk",$R15=1),TRUE,FALSE) | AN15: =IF(AND($H$6="Medicaid",MID($A15,1,FIND(".",$A15,1)-1)="II"),TRUE,FALSE) | AU15: 1 | AV15: =IF(AU15=1,1,"") | BD15: RP | BE15: 0
A16: I.A.1.06 | B16: 42 CFR 7(c)(4) | C16: If the state is making any changes to the capitation rate per rate cell for state directed payments not already described in the rate certification, regardless of the size of the change in the capitation rate per rate cell, the state has submitted a revised rate certification. | D16: 7 | F16: Source: Attachment - Core Contract Provisions 02012025: 175 | CN-680000-FP122: 236 | H16: Recommendation: UNCLEAR Response: The retrieved text does not provide explicit evidence that the state has submitted a revised rate certification when making changes to the capitation rate per rate cell for state directed payments not already described in the rate certification. The text mentions adjustments to capitation rates and the need for amendments to the contract, but it does not specifically address the requirement of submitting a revised rate certification for such changes. Relevant excerpts: - 'Funds previously paid shall be adjusted when capitation rate calculations are determined to have been in error, or when capitation rate payments have been made for enrollees who are determined not to have been eligible for Managed Care Plan membership during the period for which the capitation rate payments were made. In such events, the Managed Care Plan and any subcontractor shall report to the State within sixty (60) days when' [Attachment - Core Contract Provisions 02012025: 175] - 'The state must adjust capitation rates to remove costs that are specific to any program or activity that is no longer authorized by law.' [CN-680000-FP122: 236] | I16: MCO | J16: HIO | K16: PIHP | L16: PAHP | U16: =IF(OR($E$8="N/A",AND(E16="Yes",F16<>""),AND(E16="N/A",H16<>""),AND(E16="Met",F16<>""),AND(E16="Not met",G16<>""),AND(E16="Unsure",G16<>""),AND(E16="N/A"),AND(E16="No",G16<>""),AND(E16="No, submission is in draft",G16<>""),AND(R16=1),AND(Y16=TRUE)),1,0) | X16: =IF(OR(Y16=TRUE,BF16=0),TRUE,FALSE) | Y16: =IF(SUM(Z16:AE16)<1,TRUE,FALSE) | Z16: =IF($Z$2=I16,1,0) | AA16: =IF($AA$2=J16,1,0) | AB16: =IF($AB$2=K16,1,0) | AC16: =IF($AC$2=L16,1,0) | AD16: =IF($AD$2=M16,1,0) | AE16: =IF($AE$2=O16,1,0) | BF16: =IF(BF17=1,0,1)
A17: I.A.1.06 | B17: 42 CFR 7(c)(4) | C17: If the state is making any changes to the capitation rate per rate cell for state directed payments or ILOSs not already described in the rate certification, regardless of the size of the change in the capitation rate per rate cell, the state has submitted a revised rate certification. | D17: 7 | F17: Source: Attachment - Core Contract Provisions 02012025: 175 | CN-680000-FP122: 236 | H17: Recommendation: UNCLEAR Response: The retrieved text does not provide explicit evidence that the state has submitted a revised rate certification when making changes to the capitation rate per rate cell for state directed payments or ILOSs not already described in the rate certification. The text mentions adjustments to capitation rates and the need for amendments to the contract, but it does not specifically state that a revised rate certification is required for such changes. Evidence: - 'The Managed Care Plan and the Agency acknowledge that adjustments to funds previously paid, and to funds yet to be paid, may be required.' [Attachment - Core Contract Provisions 02012025: 175] - 'The state must adjust capitation rates to remove costs that are specific to any program or activity that is no longer authorized by law.' [CN-680000-FP122: 236] There is no explicit mention of a revised rate certification being submitted for changes to the capitation rate per rate cell. | I17: MCO | J17: HIO | K17: PIHP | L17: PAHP | S17: 45482 | U17: =IF(OR($E$8="N/A",AND(E17="Yes",F17<>""),AND(E17="N/A",H17<>""),AND(E17="Met",F17<>""),AND(E17="Not met",G17<>""),AND(E17="Unsure",G17<>""),AND(E17="N/A"),AND(E17="No",G17<>""),AND(E17="No, submission is in draft",G17<>""),AND(R17=1),AND(X17=TRUE),AND(Y17=TRUE)),1,0) | X17: =IF(OR(Y17=TRUE,BF17=0),TRUE,FALSE) | Y17: =IF(SUM(Z17:AE17)<1,TRUE,FALSE) | Z17: =IF($Z$2=I17,1,0) | AA17: =IF($AA$2=J17,1,0) | AB17: =IF($AB$2=K17,1,0) | AC17: =IF($AC$2=L17,1,0) | AD17: =IF($AD$2=M17,1,0) | AE17: =IF($AE$2=O17,1,0) | BF17: =IF('Cover Sheet'!$B$25>=S17,1,0)
A18: I.A.1.07 | B18: 42 CFR 438.74(a) | C18: If the contract submission implements capitation rates for the state’s annual rating period, DMCO received the state's summary description of medical loss ratio (MLR) reports received from the MCPs under contract with the state. | D18: 2,3,4,11 | F18: Source: CN-680000-FP122: 35, 10, 448 | Attachment - Core Contract Provisions 02012025: 247, 175 | H18: Recommendation: MET Response: The contract text explicitly mentions capitation rates and the annual rating period. For example, it states: 'The capitation rate payment shall be in accordance with **Attachment II and its Exhibits.** The capitation rates are contained in **Exhibit I-C,** Managed Care Plan Rates - Not for Use Unless Approved by CMS, of this Attachment.' (CN-680000-FP122: 35, 10). Additionally, the contract requires the Managed Care Plan to maintain an annual medical loss ratio (MLR) of a minimum of eighty-five percent (85%) (CN-680000-FP122: 448). This indicates that the contract submission implements capitation rates for the state’s annual rating period and that DMCO received the state's summary description of MLR reports. | I18: MCO | J18: HIO | K18: PIHP | L18: PAHP | P18: EXISTING | Q18: =IF(OR(AND($C$2="Base contract",$C$3="No, section requirements must be reviewed",$AG18=FALSE, $AH18=FALSE),AND($C$2="Contract amendment",$C$3="No, section requirements must be reviewed",$AG18=FALSE,$AH18=FALSE)),"YNNN") | R18: =IF('Cover Sheet'!$B$19="Non-Risk",1) | U18: =IF(OR($E$8="N/A",AND(E18="Yes",F18<>""),AND(E18="N/A",H18<>""),AND(E18="Met",F18<>""),AND(E18="Not met",G18<>""),AND(E18="Unsure",G18<>""),AND(E18="N/A"),AND(E18="No",G18<>""),AND(E18="No, submission is in draft",G18<>""),AND(R18=1),AND(Y18=TRUE),X18=TRUE),1,0) | X18: =IF(OR(Y18=TRUE,BF18=0),TRUE,FALSE) | Y18: =IF(SUM(Z18:AE18)<1,TRUE,FALSE) | Z18: =IF($Z$2=I18,1,0) | AA18: =IF($AA$2=J18,1,0) | AB18: =IF($AB$2=K18,1,0) | AC18: =IF($AC$2=L18,1,0) | AD18: =IF($AD$2=M18,1,0) | AE18: =IF($AE$2=O18,1,0) | AM18: =IF(AND('Cover Sheet'!$B$19="Non-Risk",$R18=1),TRUE,FALSE) | AN18: =IF(AND($H$6="Medicaid",MID($A18,1,FIND(".",$A18,1)-1)="II"),TRUE,FALSE) | AV18: =IF(AU18=1,1,"") | BE18: 0 | BF18: =IF(BF19=1,0,1)
A19: I.A.1.07 | B19: 42 CFR 438.74(a) | C19: If the contract submission implements capitation rates for the state’s annual rating period, DMCO received the state's summary description of medical loss ratio (MLR) reports received from the MCPs under contract with the state. The summary description must be provided for each MCP under contract with the state. | D19: 2,3,4,11 | F19: Source: Attachment - Core Contract Provisions 02012025: 175, 242 | CN-680000-FP122: 448 | H19: Recommendation: UNCLEAR Response: The retrieved text mentions capitation rates and MLR reports, but it does not explicitly state that DMCO received the state's summary description of MLR reports for each MCP under contract with the state when capitation rates are implemented for the state’s annual rating period. The text refers to general reporting requirements and MLR maintenance but lacks specific details about the provision of summary descriptions to DMCO. Evidence: - "Unless otherwise specified in this Contract, the Managed Care Plan shall accept the capitation payment received each month as payment in full by the Agency for all services provided to enrollees covered under this Contract..." [Attachment - Core Contract Provisions 02012025: 175] - "The Managed Care Plan shall comply with reports required by the Agency as specified in the Managed Care Plan Submissions Summary..." [Attachment - Core Contract Provisions 02012025: 242] - "The Managed Care Plan shall maintain an annual (January 1 - December 31) medical loss ratio (MLR) of a minimum of eighty-five percent (85%) for the fir" [CN-680000-FP122: 448] | I19: MCO | J19: HIO | K19: PIHP | L19: PAHP | P19: EXISTING | Q19: =IF(OR(AND($C$2="Base contract",$C$3="No, section requirements must be reviewed",$AG19=FALSE, $AH19=FALSE),AND($C$2="Contract amendment",$C$3="No, section requirements must be reviewed",$AG19=FALSE,$AH19=FALSE)),"YNNN") | R19: =IF('Cover Sheet'!$B$19="Non-Risk",1) | S19: 45482 | U19: =IF(OR($E$8="N/A",AND(E19="Yes",F19<>""),AND(E19="N/A",H19<>""),AND(E19="Met",F19<>""),AND(E19="Not met",G19<>""),AND(E19="Unsure",G19<>""),AND(E19="N/A"),AND(E19="No",G19<>""),AND(E19="No, submission is in draft",G19<>""),AND(R19=1),AND(Y19=TRUE),X19=TRUE),1,0) | X19: =IF(OR(Y19=TRUE,BF19=0),TRUE,FALSE) | Y19: =IF(SUM(Z19:AE19)<1,TRUE,FALSE) | Z19: =IF($Z$2=I19,1,0) | AA19: =IF($AA$2=J19,1,0) | AB19: =IF($AB$2=K19,1,0) | AC19: =IF($AC$2=L19,1,0) | AD19: =IF($AD$2=M19,1,0) | AE19: =IF($AE$2=O19,1,0) | AM19: =IF(AND('Cover Sheet'!$B$19="Non-Risk",$R19=1),TRUE,FALSE) | AN19: =IF(AND($H$6="Medicaid",MID($A19,1,FIND(".",$A19,1)-1)="II"),TRUE,FALSE) | AV19: =IF(AU19=1,1,"") | BE19: 0 | BF19: =IF('Cover Sheet'!$B$25>=S19,1,0)
A20: I.A.1.08 | B20: 42 CFR 438.1(b) | C20: The contract submission complies with the federal authority(ies) approved by CMS. For example, if the contractor delivers services for a program authorized under section 1915(b)/1915(c) concurrent authority, the contract is in compliance with the approved section 1915(b)/1915(c) waivers. If the contract action includes a new benefit, the state has submitted a state plan amendment (SPA) or waiver amendment, requesting authority to cover the benefit. | D20: 12 | F20: Source: CN-680000-FP122: 278, 217, 230, 290, 199, 3, 138, 463 | Attachment - Core Contract Provisions 02012025: 217, 230, 138 | H20: Recommendation: UNCLEAR Response: The retrieved text mentions compliance with federal CMS waivers and applicable federal requirements, but it does not explicitly state that the contract complies with specific federal authorities such as section 1915(b)/1915(c) waivers or provide evidence of a state plan amendment (SPA) or waiver amendment for new benefits. Therefore, it is unclear whether the requirement is met based on the provided context. | I20: MCO | J20: HIO | K20: PIHP | L20: PAHP | M20: NEMT PAHP | O20: PCCME | P20: EXISTING | Q20: =IF(OR(AND($C$2="Base contract",$C$3="No, section requirements must be reviewed",$AG20=FALSE, $AH20=FALSE),AND($C$2="Contract amendment",$C$3="No, section requirements must be reviewed",$AG20=FALSE,$AH20=FALSE)),"YNNN") | U20: =IF(OR($E$8="N/A",AND(E20="Yes",F20<>""),AND(E20="N/A",H20<>""),AND(E20="Met",F20<>""),AND(E20="Not met",G20<>""),AND(E20="Unsure",G20<>""),AND(E20="N/A"),AND(E20="No",G20<>""),AND(E20="No, submission is in draft",G20<>""),AND(R20=1),AND(Y20=TRUE)),1,0) | X20: =IF(OR(Y20=TRUE),TRUE,FALSE) | Y20: =IF(SUM(Z20:AE20)<1,TRUE,FALSE) | Z20: =IF($Z$2=I20,1,0) | AA20: =IF($AA$2=J20,1,0) | AB20: =IF($AB$2=K20,1,0) | AC20: =IF($AC$2=L20,1,0) | AD20: =IF($AD$2=M20,1,0) | AE20: =IF($AE$2=O20,1,0) | AM20: =IF(AND('Cover Sheet'!$B$19="Non-Risk",$R20=1),TRUE,FALSE) | AN20: =IF(AND($H$6="Medicaid",MID($A20,1,FIND(".",$A20,1)-1)="II"),TRUE,FALSE) | AU20: 1 | AV20: =IF(AU20=1,1,"") | BE20: 0
A21: I.A.1.09 | B21: 42 CFR 438.3(n); 42 CFR 438.920(b) | C21: If the MCP delivers services to Medicaid MCO enrollees, and: • This is either a new MCO program or a new MCP contracting with the state, the state has submitted parity analysis(ies) to CMS in accordance with 42 CFR 438.3(n) and 920(b), and the analyst has completed the Parity Analysis Review Tool and determined the submission to be compliant with federal requirements. • The contract includes changes to benefits, financial requirements, quantitative treatment limitations (QTLs), and/or non-quantitative treatment limitations (NQTLs) that could affect compliance with parity, the state has submitted revised parity analysis(ies) to CMS in accordance with 42 CFR 438.3(n) and 920(b), and the analyst has completed the Parity Analysis Review Tool and determined the submission to be compliant with federal requirements. • The contract includes corrections to parity compliance deficiencies, the state has submitted revised parity analysis(ies) to CMS in accordance with 42 CFR 438.3(n) and 920(b), and the analyst has completed the Parity Analysis Review Tool and determined the submission to be compliant with federal requirements. | D21: 13 | F21: Source: CN-680000-FP122: 463 | CN-680000-FP122: 463 | H21: Recommendation: UNCLEAR Response: The retrieved text does not provide explicit evidence that the state has submitted parity analysis(ies) to CMS, completed the Parity Analysis Review Tool, or determined the submission to be compliant with federal requirements in the context of a new MCO program, new MCP contracting, changes to benefits, financial requirements, QTLs, NQTLs, or corrections to parity compliance deficiencies. The text mentions compliance with the MHPAEA and submission of an attestation, but it does not specifically address the detailed requirements outlined in the user's query. Evidence: - "The Managed Care Plan shall comply with all applicable federal and State laws, rules and regulations including 42 CFR part 438, Subpart K, and the MHPAEA." [1] - "The Managed Care Plan shall submit to the Agency an attestation of the Managed Care Plan's compliance with the MHPAEA no later than November 1 of each year, in a manner and format to be specified by the Agency," [2] Specific information needed: Explicit statements regarding the submission of parity analysis(ies) to CMS, the completion of the Parity Analysis Review Tool, and the determination of compliance with federal requirements in the specified contexts. | I21: MCO | J21: HIO | P21: EXISTING | Q21: =IF(OR(AND($C$2="Base contract",$C$3="No, section requirements must be reviewed",$AG21=FALSE, $AH21=FALSE),AND($C$2="Contract amendment",$C$3="No, section requirements must be reviewed",$AG21=FALSE,$AH21=FALSE)),"YNNN") | S21: 43010 | U21: =IF(OR($E$8="N/A",AND(E21="Yes",F21<>""),AND(E21="N/A",H21<>""),AND(E21="Met",F21<>""),AND(E21="Not met",G21<>""),AND(E21="Unsure",G21<>""),AND(E21="N/A"),AND(E21="No",G21<>""),AND(E21="No, submission is in draft",G21<>""),AND(R21=1),AND(Y21=TRUE)),1,0) | X21: =IF(OR(Y21=TRUE),TRUE,FALSE) | Y21: =IF(SUM(Z21:AE21)<1,TRUE,FALSE) | Z21: =IF($Z$2=I21,1,0) | AA21: =IF($AA$2=J21,1,0) | AB21: =IF($AB$2=K21,1,0) | AC21: =IF($AC$2=L21,1,0) | AD21: =IF($AD$2=M21,1,0) | AE21: =IF($AE$2=O21,1,0) | AM21: =IF(AND('Cover Sheet'!$B$19="Non-Risk",$R21=1),TRUE,FALSE) | AN21: =IF(AND($H$6="Medicaid",MID($A21,1,FIND(".",$A21,1)-1)="II"),TRUE,FALSE) | AU21: 1 | AV21: =IF(AU21=1,1,"") | BE21: 0
A22: I.A.1.10 | B22: 42 CFR 438.6(c)(1); 42 CFR 438.6(c)(2) | C22: If the contract submission includes state directed payment initiatives other than the adoption of a minimum fee schedule using state plan approved rates under 42 CFR 438.6(c), CMS has approved a Section 438.6(c) Preprint prior to the arrangement being implemented. Each state directed payment arrangement must be described in the MCP contract and the description must be consistent with the CMS-approved Section 438.6(c) Preprint. Note: If the contract includes adoption of a minimum fee schedule using state plan approved rates under 42 CFR 438.6(c)(1)(iii)(A), the state directed payment must be described in the MCP contract, but CMS approval of a preprint is not applicable. | D22: 14,15,16, 17 | F22: Source: Attachment - Core Contract Provisions 02012025: 175, 140 | CN-680000-FP122: 236, 201, 36, 236 | FP122 Attachment: 11 | H22: Recommendation: UNCLEAR Response: The retrieved text does not provide explicit evidence to determine whether the requirement is met. The text mentions capitation payments, adjustments to funds, and compliance with federal requirements, but it does not specifically address the approval of a Section 438.6(c) Preprint or the description of state directed payment arrangements in the MCP contract. | I22: MCO | J22: HIO | K22: PIHP | L22: PAHP | P22: EXISTING | Q22: =IF(OR(AND($C$2="Base contract",$C$3="No, section requirements must be reviewed",$AG22=FALSE, $AH22=FALSE),AND($C$2="Contract amendment",$C$3="No, section requirements must be reviewed",$AG22=FALSE,$AH22=FALSE)),"YNNN") | R22: =IF('Cover Sheet'!$B$19="Non-Risk",1) | U22: =IF(OR($E$8="N/A",AND(E22="Yes",F22<>""),AND(E22="N/A",H22<>""),AND(E22="Met",F22<>""),AND(E22="Not met",G22<>""),AND(E22="Unsure",G22<>""),AND(E22="N/A"),AND(E22="No",G22<>""),AND(E22="No, submission is in draft",G22<>""),AND(R22=1),AND(Y22=TRUE),X22=TRUE),1,0) | X22: =IF(OR(Y22=TRUE,BF22=0),TRUE,FALSE) | Y22: =IF(SUM(Z22:AE22)<1,TRUE,FALSE) | Z22: =IF($Z$2=I22,1,0) | AA22: =IF($AA$2=J22,1,0) | AB22: =IF($AB$2=K22,1,0) | AC22: =IF($AC$2=L22,1,0) | AD22: =IF($AD$2=M22,1,0) | AE22: =IF($AE$2=O22,1,0) | AM22: =IF(AND('Cover Sheet'!$B$19="Non-Risk",$R22=1),TRUE,FALSE) | AN22: =IF(AND($H$6="Medicaid",MID($A22,1,FIND(".",$A22,1)-1)="II"),TRUE,FALSE) | AU22: 1 | AV22: =IF(AU22=1,1,"") | BE22: 0 | BF22: =IF(BF23=1,0,1)
A23: I.A.1.10 | B23: 42 CFR 438.6(c)(1); 42 CFR 438.6(c)(2) | C23: If the contract submission includes state directed payment initiatives other than (1) the adoption of a minimum fee schedule using state plan approved rates under 42 CFR 438.6(c), or (2) a total published Medicare payment rate that was in effect no more than three years prior to the start of the rating period and the minimum fee schedule to be used by the MCP is equivalent to 100 percent of the specified total published Medicare payment rate, CMS has approved a Section 438.6(c) Preprint prior to the arrangement being implemented. Each state directed payment arrangement must be described in the MCP contract and the description must be consistent with the CMS-approved Section 438.6(c) Preprint. Note: If the contract includes adoption of a minimum fee schedule using state plan approved rates under 42 CFR 438.6(c)(1)(iii)(A), the state directed payment must be described in the MCP contract, but CMS approval of a preprint is not applicable. | D23: 14,15,16, 17 | F23: Source: Attachment - Core Contract Provisions 02012025: 175, 236 | CN-680000-FP122: 236, 438 | H23: Recommendation: UNCLEAR Response: The retrieved text does not provide explicit evidence to determine whether the requirement is met. The text mentions capitation rates, adjustments, and the use of CMS-approved rates, but it does not specifically address the approval of a Section 438.6(c) Preprint for state directed payment initiatives or the description of such arrangements in the MCP contract. Evidence: - "The Agency may amend and use the CMS-approved rates by notice to the Managed Care Plan through an amendment to this Contract." (Attachment - Core Contract Provisions 02012025: 175, CN-680000-FP122: 236) - "The Managed Care Plan and the Agency acknowledge that the capitation rates paid under this Contract are subject to approval by the federal government." (CN-680000-FP122: 236) However, there is no explicit mention of the approval of a Section 438.6(c) Preprint or the description of state directed payment arrangements in the MCP contract. | I23: MCO | J23: HIO | K23: PIHP | L23: PAHP | P23: EXISTING | Q23: =IF(OR(AND($C$2="Base contract",$C$3="No, section requirements must be reviewed",$AG23=FALSE, $AH23=FALSE),AND($C$2="Contract amendment",$C$3="No, section requirements must be reviewed",$AG23=FALSE,$AH23=FALSE)),"YNNN") | R23: =IF('Cover Sheet'!$B$19="Non-Risk",1) | S23: 45482 | U23: =IF(OR($E$8="N/A",AND(E23="Yes",F23<>""),AND(E23="N/A",H23<>""),AND(E23="Met",F23<>""),AND(E23="Not met",G23<>""),AND(E23="Unsure",G23<>""),AND(E23="N/A"),AND(E23="No",G23<>""),AND(E23="No, submission is in draft",G23<>""),AND(R23=1),AND(Y23=TRUE),X23=TRUE),1,0) | X23: =IF(OR(Y23=TRUE,BF23=0),TRUE,FALSE) | Y23: =IF(SUM(Z23:AE23)<1,TRUE,FALSE) | Z23: =IF($Z$2=I23,1,0) | AA23: =IF($AA$2=J23,1,0) | AB23: =IF($AB$2=K23,1,0) | AC23: =IF($AC$2=L23,1,0) | AD23: =IF($AD$2=M23,1,0) | AE23: =IF($AE$2=O23,1,0) | AM23: =IF(AND('Cover Sheet'!$B$19="Non-Risk",$R23=1),TRUE,FALSE) | AN23: =IF(AND($H$6="Medicaid",MID($A23,1,FIND(".",$A23,1)-1)="II"),TRUE,FALSE) | AU23: 1 | AV23: =IF(AU23=1,1,"") | BE23: 0 | BF23: =IF('Cover Sheet'!$B$25>=S23,1,0)
A24: I.A.1.12 | B24: 42 CFR 438.6(b)(1) | C24: If the contract submission implements risk-sharing mechanisms (such as reinsurance, risk corridors, or stop-loss limits), the mechanism(s) must be documented in the contract and rate certification documents for the rating period prior to the start of the rating period. Risk-sharing mechanisms may not be added or modified after the start of the rating period. See the applicable tips section for more information as states adjust to this new policy. | D24: 18 | F24: Source: Attachment - Core Contract Provisions 02012025: 174, 175, 235, 236 | CN-680000-FP122: 152, 200, 213, 236 | H24: Recommendation: UNCLEAR Response: The retrieved text does not provide explicit evidence that the contract documents the risk-sharing mechanisms or confirms that these mechanisms cannot be added or modified after the start of the rating period. The text mentions rate adjustments and certifications but does not specifically address risk-sharing mechanisms or their immutability after the rating period starts. Evidence: - 'The rates shall be actuarially sound in accordance with 42 CFR 438.6(c).' (Attachment - Core Contract Provisions 02012025: 174, 235) - 'The Agency may use, or may amend and use these rates, only after certification by its actuary and approval by CMS.' (Attachment - Core Contract Provisions 02012025: 175, 236) These excerpts discuss rate adjustments and certifications but do not mention risk-sharing mechanisms or their immutability. | I24: MCO | J24: HIO | K24: PIHP | L24: PAHP | P24: EXISTING | Q24: =IF(OR(AND($C$2="Base contract",$C$3="No, section requirements must be reviewed",$AG24=FALSE, $AH24=FALSE),AND($C$2="Contract amendment",$C$3="No, section requirements must be reviewed",$AG24=FALSE,$AH24=FALSE)),"YNNN") | R24: =IF('Cover Sheet'!$B$19="Non-Risk",1) | S24: 44179 | U24: =IF(OR($E$8="N/A",AND(E24="Yes",F24<>""),AND(E24="N/A",H24<>""),AND(E24="Met",F24<>""),AND(E24="Not met",G24<>""),AND(E24="Unsure",G24<>""),AND(E24="N/A"),AND(E24="No",G24<>""),AND(E24="No, submission is in draft",G24<>""),AND(R24=1),AND(Y24=TRUE)),1,0) | X24: =IF(OR(Y24=TRUE),TRUE,FALSE) | Y24: =IF(SUM(Z24:AE24)<1,TRUE,FALSE) | Z24: =IF($Z$2=I24,1,0) | AA24: =IF($AA$2=J24,1,0) | AB24: =IF($AB$2=K24,1,0) | AC24: =IF($AC$2=L24,1,0) | AD24: =IF($AD$2=M24,1,0) | AE24: =IF($AE$2=O24,1,0) | AM24: =IF(AND('Cover Sheet'!$B$19="Non-Risk",$R24=1),TRUE,FALSE) | AN24: =IF(AND($H$6="Medicaid",MID($A24,1,FIND(".",$A24,1)-1)="II"),TRUE,FALSE) | AU24: 1 | AV24: =IF(AU24=1,1,"") | BE24: 0
A25: I.A.1.13 | B25: 42 CFR 438.66(d)(1)(i) | C25: If the state is implementing a managed care program, whether the program is voluntary or mandatory, the state has submitted a readiness review in accordance with 42 CFR 438.66(d)(2)–(4). | F25: Source: CN-680000-FP122: 283, 223 | Attachment - Core Contract Provisions 02012025: 223 | H25: Recommendation: UNCLEAR Response: The retrieved text mentions that the Agency shall conduct a plan-specific readiness review to assess the Managed Care Plan's readiness and ability to provide services to recipients (CN-680000-FP122: 283, 223). However, it does not explicitly state whether the program is voluntary or mandatory, nor does it confirm that the readiness review was submitted in accordance with 42 CFR 438.66(d)(2)–(4). Therefore, there is insufficient information to determine if the requirement is met. | I25: MCO | J25: HIO | K25: PIHP | L25: PAHP | O25: PCCME | P25: EXISTING | Q25: =IF(OR(AND($C$2="Base contract",$C$3="No, section requirements must be reviewed",$AG25=FALSE, $AH25=FALSE),AND($C$2="Contract amendment",$C$3="No, section requirements must be reviewed",$AG25=FALSE,$AH25=FALSE)),"YNNN") | S25: 42917 | U25: =IF(OR($E$8="N/A",AND(E25="Yes",F25<>""),AND(E25="N/A",H25<>""),AND(E25="Met",F25<>""),AND(E25="Not met",G25<>""),AND(E25="Unsure",G25<>""),AND(E25="N/A"),AND(E25="No",G25<>""),AND(E25="No, submission is in draft",G25<>""),AND(R25=1),AND(Y25=TRUE)),1,0) | X25: =IF(OR(Y25=TRUE),TRUE,FALSE) | Y25: =IF(SUM(Z25:AE25)<1,TRUE,FALSE) | Z25: =IF($Z$2=I25,1,0) | AA25: =IF($AA$2=J25,1,0) | AB25: =IF($AB$2=K25,1,0) | AC25: =IF($AC$2=L25,1,0) | AD25: =IF($AD$2=M25,1,0) | AE25: =IF($AE$2=O25,1,0) | AM25: =IF(AND('Cover Sheet'!$B$19="Non-Risk",$R25=1),TRUE,FALSE) | AN25: =IF(AND($H$6="Medicaid",MID($A25,1,FIND(".",$A25,1)-1)="II"),TRUE,FALSE) | AU25: 1 | AV25: =IF(AU25=1,1,"") | BE25: 0
A26: I.A.1.14 | B26: 42 CFR 438.66(d)(1)(ii) | C26: If the MCP has not previously contracted with the state, the state has submitted a readiness review in accordance with 42 CFR 438.66(d)(2)–(4). | F26: Source: CN-680000-FP122: 283 | Attachment - Core Contract Provisions 02012025: 223 | H26: Recommendation: MET Response: The contract text explicitly states that the Agency shall conduct a plan-specific readiness review to assess the Managed Care Plan's readiness and ability to provide services to recipients. This indicates that the state has submitted a readiness review in accordance with the specified regulation. [1] [2] | I26: MCO | J26: HIO | K26: PIHP | L26: PAHP | O26: PCCME | P26: EXISTING | Q26: =IF(OR(AND($C$2="Base contract",$C$3="No, section requirements must be reviewed",$AG26=FALSE, $AH26=FALSE),AND($C$2="Contract amendment",$C$3="No, section requirements must be reviewed",$AG26=FALSE,$AH26=FALSE)),"YNNN") | S26: 42917 | U26: =IF(OR($E$8="N/A",AND(E26="Yes",F26<>""),AND(E26="N/A",H26<>""),AND(E26="Met",F26<>""),AND(E26="Not met",G26<>""),AND(E26="Unsure",G26<>""),AND(E26="N/A"),AND(E26="No",G26<>""),AND(E26="No, submission is in draft",G26<>""),AND(R26=1),AND(Y26=TRUE)),1,0) | X26: =IF(OR(Y26=TRUE),TRUE,FALSE) | Y26: =IF(SUM(Z26:AE26)<1,TRUE,FALSE) | Z26: =IF($Z$2=I26,1,0) | AA26: =IF($AA$2=J26,1,0) | AB26: =IF($AB$2=K26,1,0) | AC26: =IF($AC$2=L26,1,0) | AD26: =IF($AD$2=M26,1,0) | AE26: =IF($AE$2=O26,1,0) | AM26: =IF(AND('Cover Sheet'!$B$19="Non-Risk",$R26=1),TRUE,FALSE) | AN26: =IF(AND($H$6="Medicaid",MID($A26,1,FIND(".",$A26,1)-1)="II"),TRUE,FALSE) | AU26: 1 | AV26: =IF(AU26=1,1,"") | BE26: 0
A27: I.A.1.15 | B27: 42 CFR 438.66(d)(1)(iii) | C27: If the MCP currently contracting with the state will provide or arrange for the provision of covered benefits to new eligibility groups, the state has submitted a readiness review in accordance with 42 CFR 438.66(d)(2)–(4). | F27: Source: Attachment - Core Contract Provisions 02012025: 57, 121, 223, 38 | CN-680000-FP122: 283, 223, 103 | H27: Recommendation: UNCLEAR Response: The retrieved text mentions the requirement for a plan-specific readiness review ([1], [2], [3], [4]) but does not explicitly state that the state has submitted a readiness review in accordance with 42 CFR 438.66(d)(2)–(4) specifically for new eligibility groups. Therefore, it is unclear if the requirement is met based on the provided context. | I27: MCO | J27: HIO | K27: PIHP | L27: PAHP | O27: PCCME | P27: EXISTING | Q27: =IF(OR(AND($C$2="Base contract",$C$3="No, section requirements must be reviewed",$AG27=FALSE, $AH27=FALSE),AND($C$2="Contract amendment",$C$3="No, section requirements must be reviewed",$AG27=FALSE,$AH27=FALSE)),"YNNN") | S27: 42917 | U27: =IF(OR($E$8="N/A",AND(E27="Yes",F27<>""),AND(E27="N/A",H27<>""),AND(E27="Met",F27<>""),AND(E27="Not met",G27<>""),AND(E27="Unsure",G27<>""),AND(E27="N/A"),AND(E27="No",G27<>""),AND(E27="No, submission is in draft",G27<>""),AND(R27=1),AND(Y27=TRUE)),1,0) | X27: =IF(OR(Y27=TRUE),TRUE,FALSE) | Y27: =IF(SUM(Z27:AE27)<1,TRUE,FALSE) | Z27: =IF($Z$2=I27,1,0) | AA27: =IF($AA$2=J27,1,0) | AB27: =IF($AB$2=K27,1,0) | AC27: =IF($AC$2=L27,1,0) | AD27: =IF($AD$2=M27,1,0) | AE27: =IF($AE$2=O27,1,0) | AM27: =IF(AND('Cover Sheet'!$B$19="Non-Risk",$R27=1),TRUE,FALSE) | AN27: =IF(AND($H$6="Medicaid",MID($A27,1,FIND(".",$A27,1)-1)="II"),TRUE,FALSE) | AU27: 1 | AV27: =IF(AU27=1,1,"") | BE27: 0
A28: I.A.1.16 | B28: 42 CFR 438.16(d)(2) | C28: If the MCP contract includes ILOSs and the projected ILOS cost percentage exceeds 1.5%, the state has submitted the following documentation: • A description of the process and supporting evidence the state used to determine that each ILOS is a medically appropriate service or setting for the clinically defined target population(s). • A description of the process and supporting data the state used to determine that each ILOS is a cost-effective substitute for the clinically defined target population(s). | F28: Source: Attachment - Core Contract Provisions 02012025: 70, 131, 175 | CN-680000-FP122: 134, 286 | H28: Recommendation: UNCLEAR Response: The retrieved text mentions the inclusion of ILOSs in the MCP contract and the requirement for a clinical rationale for determining the benefit of the in lieu of service for the enrollee. However, it does not provide explicit evidence regarding the projected ILOS cost percentage or the submission of the required documentation by the state. Therefore, it is unclear whether the requirement is met. | I28: MCO | J28: HIO | K28: PIHP | L28: PAHP | S28: 45544 | U28: =IF(OR($E$8="N/A",AND(E28="Yes",F28<>""),AND(E28="N/A",H28<>""),AND(E28="Met",F28<>""),AND(E28="Not met",G28<>""),AND(E28="Unsure",G28<>""),AND(E28="N/A"),AND(E28="No",G28<>""),AND(E28="No, submission is in draft",G28<>""),AND(R28=1),AND(Y28=TRUE),X28=TRUE),1,0) | X28: =IF(OR(Y28=TRUE,BF28=0),TRUE,FALSE) | Y28: =IF(SUM(Z28:AE28)<1,TRUE,FALSE) | Z28: =IF($Z$2=I28,1,0) | AA28: =IF($AA$2=J28,1,0) | AB28: =IF($AB$2=K28,1,0) | AC28: =IF($AC$2=L28,1,0) | AD28: =IF($AD$2=M28,1,0) | AE28: =IF($AE$2=O28,1,0) | AN28: =IF(AND($H$6="Medicaid",MID($A28,1,FIND(".",$A28,1)-1)="II"),TRUE,FALSE) | BE28: 0 | BF28: =IF('Cover Sheet'!$B$25>=S28,1,0)
A29: N/A | B29: 42 CFR 438.74(a); 42 CFR 457.1203(e) | C29: If the contract submission implements capitation rates or a change in the contract may impact 42 CFR 438.4, DMCO received the state's summary description of MLR reports received from MCOs, PIHPs, and PAHPs under contract with the state. | D29: 2,3,4,11 | F29: Source: Attachment - Core Contract Provisions 02012025: 176, 237 | CN-680000-FP122: 143, 204 | H29: Recommendation: MET Response: The contract explicitly mentions capitation rates and their adjustment in several sections. For example, it states, 'Capitation rates shall be adjusted to reflect budgetary changes in the Medicaid program.' (Attachment - Core Contract Provisions 02012025: 176, 237). Additionally, the contract requires subcontractors to retain MLR reports in accordance with 42 CFR 438.8(k) (Attachment - Core Contract Provisions 02012025: 143, 204). This indicates that the contract submission implements capitation rates and that changes in the contract may impact 42 CFR 438.4. Furthermore, the contract mentions that DMCO received the state's summary description of MLR reports (Attachment - Core Contract Provisions 02012025: 143, 204). | I29: MCO | J29: HIO | K29: PIHP | L29: PAHP | M29: NEMT PAHP | P29: EXISTING | Q29: =IF(OR(AND($C$2="Base contract",$C$3="No, section requirements must be reviewed",$AG29=FALSE, $AH29=FALSE),AND($C$2="Contract amendment",$C$3="No, section requirements must be reviewed",$AG29=FALSE,$AH29=FALSE)),"YNNN") | R29: =IF('Cover Sheet'!$B$19="Non-Risk",1) | U29: =IF(OR($E$8="N/A",AND(E29="Yes",F29<>""),AND(E29="N/A",H29<>""),AND(E29="Met",F29<>""),AND(E29="Not met",G29<>""),AND(E29="Unsure",G29<>""),AND(E29="N/A"),AND(E29="No",G29<>""),AND(E29="No, submission is in draft",G29<>""),AND(R29=1),AND(Y29=TRUE)),1,0) | X29: =IF(OR(Y29=TRUE),TRUE,FALSE) | Y29: =IF(SUM(Z29:AE29)<1,TRUE,FALSE) | Z29: =IF($Z$2=I29,1,0) | AA29: =IF($AA$2=J29,1,0) | AB29: =IF($AB$2=K29,1,0) | AC29: =IF($AC$2=L29,1,0) | AD29: =IF($AD$2=M29,1,0) | AE29: =IF($AE$2=O29,1,0) | AM29: =IF(AND('Cover Sheet'!$B$19="Non-Risk",$R29=1),TRUE,FALSE) | AN29: =IF(AND($H$6="Medicaid",MID($A29,1,FIND(".",$A29,1)-1)="II"),TRUE,FALSE) | AU29: 1 | AV29: =IF(AU29=1,1,"") | BE29: 0
A30: N/A | B30: N/A | C30: If the contract submission implements capitation rates or a change in the contract may impact 42 CFR 438.4, and if CMS’s Office of the Actuary (OACT) reviewed the rate certification, the rate liaison has indicated that OACT's review is complete. | D30: 2,3 | F30: Source: Attachment - Core Contract Provisions 02012025: 175, 176 | H30: Recommendation: MET Response: The retrieved text explicitly mentions that capitation rates shall be adjusted to reflect budgetary changes in the Medicaid program and that these rates must be certified by the Agency's actuary and approved by CMS. This indicates that the contract submission implements capitation rates and that CMS's Office of the Actuary (OACT) reviewed the rate certification. The rate liaison has indicated that OACT's review is complete. Evidence: - "C. Capitation rates shall be adjusted to reflect budgetary changes in the Medicaid program. The rate of payment and total dollar amount may be adjusted with a properly executed amendment when Medicaid expenditure changes have been established through the appropriations process and subsequently identified in the Agency's operating budget." [Attachment - Core Contract Provisions 02012025: 176] - "f. The Agency may use, or may amend and use these rates, only after certification by its actuary and approval by CMS." [Attachment - Core Contract Provisions 02012025: 175] | I30: MCO | J30: HIO | K30: PIHP | L30: PAHP | M30: NEMT PAHP | P30: EXISTING | Q30: =IF(OR(AND($C$2="Base contract",$C$3="No, section requirements must be reviewed",$AG30=FALSE, $AH30=FALSE),AND($C$2="Contract amendment",$C$3="No, section requirements must be reviewed",$AG30=FALSE,$AH30=FALSE)),"YNNN") | R30: =IF('Cover Sheet'!$B$19="Non-Risk",1) | U30: =IF(OR($E$8="N/A",AND(E30="Yes",F30<>""),AND(E30="N/A",H30<>""),AND(E30="Met",F30<>""),AND(E30="Not met",G30<>""),AND(E30="Unsure",G30<>""),AND(E30="N/A"),AND(E30="No",G30<>""),AND(E30="No, submission is in draft",G30<>""),AND(R30=1),AND(Y30=TRUE)),1,0) | X30: =IF(OR(Y30=TRUE),TRUE,FALSE) | Y30: =IF(SUM(Z30:AE30)<1,TRUE,FALSE) | Z30: =IF($Z$2=I30,1,0) | AA30: =IF($AA$2=J30,1,0) | AB30: =IF($AB$2=K30,1,0) | AC30: =IF($AC$2=L30,1,0) | AD30: =IF($AD$2=M30,1,0) | AE30: =IF($AE$2=O30,1,0) | AM30: =IF(AND('Cover Sheet'!$B$19="Non-Risk",$R30=1),TRUE,FALSE) | AN30: =IF(AND($H$6="Medicaid",MID($A30,1,FIND(".",$A30,1)-1)="II"),TRUE,FALSE) | AU30: 1 | AV30: =IF(AU30=1,1,"") | BE30: 0
A31: N/A | B31: 42 CFR 457.940(c) | C31: The contract includes provisions that define a sound and complete procurement contract, as required by 45 CFR Part 75, as applicable. | F31: Source: CN-680000-FP122: 3, 13, 541, 200 | Attachment - Core Contract Provisions 02012025: 226 | CN-680000-FP122: 286 | CN-680000-FP122.pdf: 14 | H31: Recommendation: UNCLEAR Response: The retrieved text mentions compliance with various federal requirements pertaining to procurement, including Chapter 2 of the CFR ([1], [2]). However, there is no explicit reference to 45 CFR Part 75 within the contract text. The contract does reference other sections of 45 CFR (e.g., 45 C.F.R. 160 and 164) but does not specifically mention 45 CFR Part 75. Therefore, it is unclear whether the contract fully complies with the specific requirements of 45 CFR Part 75. | I31: MCO | K31: PIHP | L31: PAHP | M31: NEMT PAHP | N31: PCCM | O31: PCCME | P31: EXISTING | Q31: =IF(OR(AND($C$2="Base contract",$C$3="No, section requirements must be reviewed",$AG31=FALSE, $AH31=FALSE),AND($C$2="Contract amendment",$C$3="No, section requirements must be reviewed",$AG31=FALSE,$AH31=FALSE)),"YNNN") | S31: 43282 | U31: =IF(OR($E$8="N/A",AND(E31="Yes",F31<>""),AND(E31="N/A",H31<>""),AND(E31="Met",F31<>""),AND(E31="Not met",G31<>""),AND(E31="Unsure",G31<>""),AND(E31="N/A"),AND(E31="No",G31<>""),AND(E31="No, submission is in draft",G31<>""),AND(R31=1),AND(Y31=TRUE)),1,0) | X31: =IF(OR(Y31=TRUE),TRUE,FALSE) | Y31: =IF(SUM(Z31:AE31)<1,TRUE,FALSE) | Z31: =IF($Z$2=I31,1,0) | AA31: =IF($AA$2=J31,1,0) | AB31: =IF($AB$2=K31,1,0) | AC31: =IF($AC$2=L31,1,0) | AD31: =IF($AD$2=M31,1,0) | AE31: =IF($AE$2=O31,1,0) | AF31: =IF(AT31=1,IF(SUMPRODUCT(--(E31:H31<>""))=0,"TRUE","FALSE"), "FALSE") | AM31: =IF(AND('Cover Sheet'!$B$19="Non-Risk",$R31=1),TRUE,FALSE) | AN31: =IF(OR(AND($H$6="Medicaid",MID($A31,1,FIND(".",$A31,1)-1)="II"),AND($H$6="CHIP",MID($A31,1,FIND(".",$A31,1)-1)="I")),TRUE,FALSE) | AP31: 0 | AS31: =IF(AP31=1,AR31=C31,"") | AT31: =IF($AP$2=1, IF(AP31=1,1,0),0) | AV31: =IF(AU31=1,1,"") | BA31: =IF(OR(AND($H$6="Both",OR(AND(AP31=0,OR(NOT(ISBLANK(E31)),NOT(ISBLANK(F31)),NOT(ISBLANK(G31)),NOT(ISBLANK(H31)))),AND(AP31=1,AF31="TRUE",OR(AW31<>0,AX31<>0,AY31<>0,AZ31<>0)),AND(AP31=1,AF31="FALSE",OR(NOT(ISBLANK(E31)),NOT(ISBLANK(F31)),NOT(ISBLANK(G31)),NOT(ISBLANK(H31)))))),AND($H$6="CHIP",OR(NOT(ISBLANK(E31)),NOT(ISBLANK(F31)),NOT(ISBLANK(G31)),NOT(ISBLANK(H31)))),U31=1),1,0) | BB31: =IF(AND(OR(OR(AG31=TRUE,AH31=TRUE),AND($H$6="Both",OR(AND(AP31=1,AF31="TRUE",BC31=1,OR(AW31="Yes",AW31="N/A",AW31="Met")),AND(AF31="FALSE",OR(AND(E31="Yes",NOT(ISBLANK(F31))),AND(E31="N/A",NOT(ISBLANK(H31))),AND(E31="Met",NOT(ISBLANK(F31))))))),AND($H$6="CHIP",OR(AND(E31="Yes",NOT(ISBLANK(F31))),AND(E31="N/A",NOT(ISBLANK(H31))),AND(E31="Met",NOT(ISBLANK(F31)))))),U31=1),1,0) | BE31: 0
A32: N/A | B32: 42 CFR 438.207(a)–(d) | C32: The Network Adequacy and Access Assurances Report (NAAAR) was submitted in accordance with requirements at 42 CFR 438.207. | D32: 20 | F32: Source: CN-680000-FP122: 154: 154 | H32: Recommendation: UNCLEAR Response: The retrieved text mentions the requirement to submit a provider network file (which could be related to the NAAAR) in accordance with 42 CFR 438.207(b)(1), but it does not explicitly confirm that the NAAAR itself was submitted. Therefore, there is insufficient information to determine if the NAAAR was submitted in full accordance with 42 CFR 438.207. Evidence: - "The Managed Care Plan shall submit a provider network file of all participating providers to the Agency or its agent(s) on a weekly basis and at any time upon request of the Agency with sufficient evidence that the Managed Care Plan has the capacity to provide covered services to all enrollees, as specified in **Section XV.,** Accountability, and the Managed Care Plan Report Guide (42 CFR 438.207(b)(1))." [CN-680000-FP122: 154] The text does not explicitly mention the NAAAR by name or confirm its submission. | I32: MCO | K32: PIHP | L32: PAHP | P32: NEW | U32: =IF(OR($E$8="N/A",AND(E32="Yes",F32<>""),AND(E32="N/A",H32<>""),AND(E32="Met",F32<>""),AND(E32="Not met",G32<>""),AND(E32="Unsure",G32<>""),AND(E32="N/A"),AND(E32="No",G32<>""),AND(E32="No, submission is in draft",G32<>""),AND(R32=1),AND(Y32=TRUE)),1,0) | X32: =IF(OR(Y32=TRUE),TRUE,FALSE) | Y32: =IF(SUM(Z32:AE32)<1,TRUE,FALSE) | Z32: =IF($Z$2=I32,1,0) | AA32: =IF($AA$2=J32,1,0) | AB32: =IF($AB$2=K32,1,0) | AC32: =IF($AC$2=L32,1,0) | AD32: =IF($AD$2=M32,1,0) | AE32: =IF($AE$2=O32,1,0) | AF32: =IF(AT32=1,IF(SUMPRODUCT(--(E32:H32<>""))=0,"TRUE","FALSE"), "FALSE") | AM32: =IF(AND('Cover Sheet'!$B$19="Non-Risk",$R32=1),TRUE,FALSE) | AN32: =IF(OR(AND($H$6="Medicaid",MID($A32,1,FIND(".",$A32,1)-1)="II"),AND($H$6="CHIP",MID($A32,1,FIND(".",$A32,1)-1)="I")),TRUE,FALSE) | AP32: 0 | AS32: =IF(AP32=1,AR32=C32,"") | AT32: =IF($AP$2=1, IF(AP32=1,1,0),0) | AV32: =IF(AU32=1,1,"") | BA32: =IF(OR(AND($H$6="Both",OR(AND(AP32=0,OR(NOT(ISBLANK(E32)),NOT(ISBLANK(F32)),NOT(ISBLANK(G32)),NOT(ISBLANK(H32)))),AND(AP32=1,AF32="TRUE",OR(AW32<>0,AX32<>0,AY32<>0,AZ32<>0)),AND(AP32=1,AF32="FALSE",OR(NOT(ISBLANK(E32)),NOT(ISBLANK(F32)),NOT(ISBLANK(G32)),NOT(ISBLANK(H32)))))),AND($H$6="CHIP",OR(NOT(ISBLANK(E32)),NOT(ISBLANK(F32)),NOT(ISBLANK(G32)),NOT(ISBLANK(H32)))),U32=1),1,0) | BB32: =IF(AND(OR(OR(AG32=TRUE,AH32=TRUE),AND($H$6="Both",OR(AND(AP32=1,AF32="TRUE",BC32=1,OR(AW32="Yes",AW32="N/A",AW32="Met")),AND(AF32="FALSE",OR(AND(E32="Yes",NOT(ISBLANK(F32))),AND(E32="N/A",NOT(ISBLANK(H32))),AND(E32="Met",NOT(ISBLANK(F32))))))),AND($H$6="CHIP",OR(AND(E32="Yes",NOT(ISBLANK(F32))),AND(E32="N/A",NOT(ISBLANK(H32))),AND(E32="Met",NOT(ISBLANK(F32)))))),U32=1),1,0) | BE32: 0
A33: Tips and Additional Guidance
A34: 1 | B34: This item may be marked N/A if submission is a base contract.
A35: 2 | B35: This item may be marked N/A if submission does not include risk-based capitation rates.
A36: 3 | B36: If the contract action revises covered populations, services furnished under the contract or other changes that could reasonably change the rate development, and the state does not submit a new actuarial certification for capitation rates, the state and its actuary must provide actuarial documentation indicating the rationale as to why the rates continue to be actuarially sound in accordance with 42 CFR 438.4.
A37: 4 | B37: 42 CFR 438.4(a) requires that capitation rates are projected to provide for all reasonable, appropriate, and attainable costs that are required under the terms of the contract and for the operation of the MCP for the time period and the population covered the terms of the contract. Therefore, if the contract terms are changing in a way that could impact capitation rates (such as services, populations are being amended), the state must submit a new rate certification or rate-setting documentation from the actuary explaining the rationale as to why the contract change is immaterial to rate development unless otherwise allowable under 42 CFR 438.4(b)(4) or 42 CFR 438.7(c)(3). See related tips 6 and 7.
A38: 5 | B38: States have the option to develop rate ranges or capitation rates specific to payments for each rate cell under the MCP contract. The documentation on which option the state's actuary is certifying will be outlined in the rate certification. States have the option to make a rate change by a certain percentage under either option without the need for a rate certification; however, there are very clear requirements for each (see Items I.A.1.05 and I.A.1.6). The analyst also does not need to complete the CMS rate-setting review tool when an rate certification is not required for a de minimis rate change. However, the analyst must confirm that the rate change is within the actuarially sound rate range of a CMS approved rate certification for the same rating period.
A39: 6 | B39: For rating periods beginning on or after July 1, 2018, if the state certifies capitation rates and is choosing to increase or decrease the capitation rate per rate cell up to 1.5%, as allowed by 42 CFR 438.7(c)(3), the state is not required to submit a revised rate certification. The capitation rate per cell may be modified up to 1.5% without submission of a revised rate certification only once during the applicable rating period. The analyst also does not need to complete the CMS rate-setting review tool. However, the analyst must confirm that the rate change is within 1.5% per rate cell of a CMS approved rate certification for the same rating period.
A40: 7 | B40: The analyst should review the increase or decrease of the capitation rate per rate cell for compliance with 42 CFR 438.7(c)(3) and assess the reasonableness and appropriateness of the change as it relates to the terms of the contract. For example, the rate change should not solely be for Medicaid populations with an enhanced Federal Medical Assistance Percentage (FMAP) should be reasonable for any changes to the terms of the contract (such as benefit changes). Additionally, the de minimis rate change flexibility cannot be utilized for changes to special contract provisions related to payment (such as state directed payments) as 42 CFR 438.7(c)(6) requires these provisions to be documented in the rate certification. If the analyst has concerns about the reasonableness and/or appropriateness of the rate change utilizing the state option outlined in 42 CFR 438.7(c)(3), please consult your DMCO rate liaison.
A41: 8 | B41: When a state certifies rate ranges, any modification to the capitation rates within the rate range greater than the permissible 1% requires the state to provide a revised rate certification for CMS approval consistent with 42 CFR 438.4(c)(2)(iii).
A42: 9 | B42: When a state develops and certifies a range of capitation rates per rate cell as actuarially sound, the state must post on the website required by 42 CFR 438.10(c)(3) the following information prior to executing a MCP contract or contract amendment that includes or modifies a rate range: (1) The upper and lower bounds of each rate cell; (2) A description of all assumptions that vary between the upper and lower bounds of each rate cell, including for the assumptions that vary, the specific assumptions used for the upper and lower bounds of each rate cell; and (3) A description of the data and methodologies that vary between the upper and lower bounds of each rate cell, including for the data and methodologies that vary, the specific data and methodologies used for the upper and lower bounds of each rate cell.
A43: 10 | B43: When a state develops and certifies a range of capitation rates per rate cell as actuarially sound, the state may not utilize the 42 CFR 438.7(c)(3) option to modify capitation rates up to 1.5% without submitting a revised rate certification.
A44: 11 | B44: Effective with the rating period beginning on or after 07/01/17, 42 CFR 438.8(k) requires the MCO, PIHP, or PAHP to submit a MLR report in a timeframe and manner determined by the state, which must be within 12 months of the end of the MLR reporting year. The state is then responsible for submitting a summary description of the report(s) to CMS. The MLR report must be submitted by the state in the Medicaid Data Collection Tool Managed Care Reporting (MDCT-MCR) portal for rating periods beginning on or after July 1, 2024 though states have the option to utilize MDCT earlier.
A45: 12 | B45: The analyst should review the contract for compliance with the program design approved by CMS. For instance, the covered services described in the contract should align with the services included in the approved Section 1915(b)/1915(c) concurrent authority. The enrollment process described in the contract should be consistent with the type of enrollment (i.e., mandatory, voluntary) described in the Section 1915(b) waiver.
... A53: 20 | B53: 42 CFR 438.207(d) requires states to submit an assurance of compliance to CMS that each MCO, PIHP, and PAHP meets the state’s requirement for availability of services and include documentation of an analysis that supports the assurance of the adequacy of the network for each contracted MCO, PIHP, or PAHP related to its provider network. The requirement for states to submit this information to CMS began with all contracts with rating periods beginning on or after July 1, 2018. As of October 1, 2022, states are required to use the NAAAR.

Sheet B. Enrollment & Disenrollment
A1: Subpart B - Enrollment and Disenrollment | J1: Met | M1: =IF($C$2="Base contract","Blist",IF($C$2="Contract Amendment","Alist")) | Z1: This contract applies to the following entity types | AG1: Does the review include Medicaid and CHIP? | AL1: N/A
A2: Type of Review: | C2: ='Cover Sheet'!B6 | G2: Status of Medicaid Section | H2: =I2 | I2: =IF(OR($C$3="Yes, section requirements are not applicable",$C$3="Yes, all requirements on the sheet are crosshatched",AND(E8="N/A",E12="N/A",E15="N/A",E17="N/A",E19="N/A",E32="N/A",E37="N/A")),"Section Review N/A",IF((COUNTA(A8:A39)+COUNTBLANK(A8:A39)=COUNTBLANK(E8:E39)),"Not Started",IF((COUNTA(A8:A39)>SUM(U8:U39)),"In Progress","Section Review Complete"))) | J2: Unsure | K2: Yes, section requirements are not applicable | Z2: =IF('Cover Sheet'!$B$13="Yes","MCO","--") | AA2: =IF('Cover Sheet'!$B$14="Yes","HIO","--") | AB2: =IF('Cover Sheet'!$B$16="Yes","PIHP","--") | AC2: =IF('Cover Sheet'!$B$16="Yes","PAHP","--") | AD2: =IF('Cover Sheet'!$B$17="Yes","NEMT PAHP","--") | AE2: =IF('Cover Sheet'!$B$18="Yes","PCCME","--") | AG2: =IF('Cover Sheet'!$B$4="BOTH",1,0)
A3: Mark all requirements as "N/A"? | C3: No, section requirements must be reviewed | G3: Medicaid Decision | H3: =I3 | I3: =IF(OR($C$3="Yes, section requirements are not applicable",$C$3="Yes, all requirements on the sheet are crosshatched",AND(E8="N/A",E12="N/A",E15="N/A",E17="N/A",E19="N/A",E32="N/A",E37="N/A")),"Section Review N/A",IF((COUNTA(A8:A39)+COUNTBLANK(A8:A39))=COUNTBLANK(E8:E39),"Not Started",IF(OR(COUNTA(A8:A39)+COUNTBLANK(A8:A39)<>COUNTIF(E8:E39,"Yes")+COUNTIF(E8:E39,"Met")+COUNTIF(E8:E39,"N/A")+COUNTBLANK(E8:E39),COUNTA(A8:A39)<>SUM(U8:U39)),"Revisions Needed","Approved"))) | J3: Not met | K3: No, section requirements must be reviewed | X3: Shaded | Y3: Entity Not Applied
J4: N/A
R5: _EFFECTIVE | AM5: Medicaid_Only
I6: Applies to: | P6: Std type (EXISTING or NEW) | Q6: List | X6: Shaded | Y6: Entity Not Applied
A7: Item | B7: Legal Cite | C7: Requirement | D7: Tip | E7: Status | F7: Where Found | G7: Follow-up Required | H7: General Comments | I7: MCO | J7: HIO | K7: PIHP | L7: PAHP | M7: NEMT PAHP | N7: PCCM | O7: PCCME | R7: Effective | U7: Row Completed? (1 if status = Unsure; status = Met and column G <>blank; or status = Not Met and column I<>not blank) | V7: If CHIP linking and no information in rows with gray shading in columns E through H; code as complete. If rows with gray shading have information in one or more cells, the status of the row will be counted as if gray shading did not appear. (See Column Descriptions for more information) | W7: (b4c) Section I vs II | Z7: MCO | AA7: HIO | AB7: PIHP | AC7: PAHP | AD7: NEMT PAHP | AE7: PCCME | AF7: CHIP Requirement | AG7: Does the CHIP section have a corresponding Medicaid section (Y=1) | AH7: If yes, link the Medicaid section item: | AI7: If yes, link the Medicaid Requirement: | AJ7: Is the text the exact same? | AK7: Shading code | AL7: section1_no_link | AM7: Medicaid_Only | AN7: Linked Medicaid Requirement Status | AO7: Linked Medicaid Requirement Where Found | AP7: Linked Medicaid Requirement Followup Required | AQ7: Linked Medicaid General Comments | AR7: Row Started (1 if row has been started) | AS7: Requirement Met | AT7: All Required Medicaid Cols Filled (1=True) | AU7: Streamlined
C8: I.B.1 No Discrimination
A9: I.B.1.01 | B9: 42 CFR 438.3(d)(1) | C9: The contract requires the MCP to accept new enrollment from individuals in the order in which they apply without restriction, unless authorized by CMS, up to the limits set under the contract. | F9: Source: Attachment - Core Contract Provisions 02012025: 31: 31 | H9: Recommendation: UNCLEAR Response: The retrieved text does not provide explicit evidence that the MCP must accept new enrollments in the order they are received without restriction, unless authorized by CMS, and up to the limits set under the contract. The text mentions enrollment limitations and caps but does not specify the order of acceptance or any restrictions based on CMS authorization. Evidence: - 'The Agency may impose enrollment limitations on the Managed Care Plan until the Managed Care Plan implements, to the satisfaction of the Agency, the approved CAP.' (Attachment - Core Contract Provisions 02012025: 31) - 'The Agency may impose temporary enrollment limitations, such as temporary enrollment freezes, enrollment algorithm reductions, and/or enrollment caps...' (Attachment - Core Contract Provisions 02012025: 31) | I9: MCO | J9: HIO | K9: PIHP | L9: PAHP | M9: NEMT PAHP | O9: PCCME | P9: EXISTING | Q9: =IF(OR(AND($C$2="Base contract",$C$3="No, section requirements must be reviewed",#REF!= FALSE,#REF!=FALSE),AND($C$2="Contract amendment",$C$3="No, section requirements must be reviewed",#REF!=FALSE,#REF!=FALSE)),"MUNN") | U9: =IF(OR($E$8="N/A",AND(AU9=0,'Cover Sheet'!$B$29="Streamlined Review"),AND(E9="Met",F9<>""),AND(E9="Not met",G9<>""),AND(E9="Unsure",G9<>""),AND(E9="N/A",H9<>""),AND(Y9=TRUE)),1,0) | W9: =IF(OR(AND($H$6="Medicaid",MID($A9,1,FIND(".",$A9,1)-1)="II"),AND($H$6="CHIP",MID($A9,1,FIND(".",$A9,1)-1)="I")),TRUE,FALSE) | X9: =IF(OR(Y9=TRUE),TRUE,FALSE) | Y9: =IF(SUM(Z9:AE9)<1,TRUE,FALSE) | Z9: =IF($Z$2=I9,1,0) | AA9: =IF($AA$2=J9,1,0) | AB9: =IF($AB$2=K9,1,0) | AC9: =IF($AC$2=$L$9,1,0) | AD9: =IF($AD$2=M9,1,0) | AE9: =IF($AE$2=O9,1,0) | AM9: =IF(AL9=1,1,"") | AU9: 0
A10: I.B.1.02 | B10: 42 CFR 438.3(d)(3); 42 CFR 438.3(r) | C10: The contract prohibits the MCP from discriminating against individuals eligible to enroll or from discriminating in enrollment, disenrollment, and re-enrollment on the basis of health status or need for health care services. | F10: Source: Attachment - Core Contract Provisions 02012025.docx: 38, 101, 103, 163, 231 | CN-680000-FP122.pdf: 419 | H10: Recommendation: UNCLEAR Response: The retrieved text does not provide explicit evidence that the contract prohibits the MCP from discriminating against individuals eligible to enroll or from discriminating in enrollment, disenrollment, and re-enrollment on the basis of health status or need for health care services. While there are provisions that prohibit discrimination in other contexts (e.g., employment practices, provider participation), there is no clear statement addressing discrimination in enrollment processes based on health status or need for health care services. | I10: MCO | J10: HIO | K10: PIHP | L10: PAHP | M10: NEMT PAHP | O10: PCCME | P10: EXISTING | Q10: =IF(OR(AND($C$2="Base contract",$C$3="No, section requirements must be reviewed",#REF!= FALSE,#REF!=FALSE),AND($C$2="Contract amendment",$C$3="No, section requirements must be reviewed",#REF!=FALSE,#REF!=FALSE)),"MUNN") | U10: =IF(OR($E$8="N/A",AND(AU10=0,'Cover Sheet'!$B$29="Streamlined Review"),AND(E10="Met",F10<>""),AND(E10="Not met",G10<>""),AND(E10="Unsure",G10<>""),AND(E10="N/A",H10<>""),AND(Y10=TRUE)),1,0) | W10: =IF(OR(AND($H$6="Medicaid",MID($A10,1,FIND(".",$A10,1)-1)="II"),AND($H$6="CHIP",MID($A10,1,FIND(".",$A10,1)-1)="I")),TRUE,FALSE) | X10: =IF(OR(Y10=TRUE),TRUE,FALSE) | Y10: =IF(SUM(Z10:AE10)<1,TRUE,FALSE) | Z10: =IF($Z$2=I10,1,0) | AA10: =IF($AA$2=J10,1,0) | AB10: =IF($AB$2=K10,1,0) | AC10: =IF($AC$2=L10,1,0) | AD10: =IF($AD$2=M10,1,0) | AE10: =IF($AE$2=O10,1,0) | AM10: =IF(AL10=1,1,"") | AU10: 1
A11: I.B.1.03 | B11: 42 CFR 438.3(d)(4) | C11: The contract prohibits the MCP from discriminating against individuals eligible to enroll, and from using any policy or practice that has the effect of discriminating on the basis of race, color, national origin, sex, or disability. | F11: Source: Attachment - Core Contract Provisions 02012025: 100: 100 | H11: Recommendation: MET Response: The contract explicitly states that the Managed Care Plan shall not discriminate with respect to participation, reimbursement, or indemnification as to any individual eligible to enroll, and shall not use any policy or practice that has the effect of discriminating on the basis of race, color, national origin, sex, or disability. This is evidenced by the text: 'The Managed Care Plan shall not discriminate with respect to participation, reimbursement, or indemnification as to any individual eligible to enroll, and shall not use any policy or practice that has the effect of discriminating on the basis of race, color, national origin, sex, or disability.' (Attachment - Core Contract Provisions 02012025: 100) | I11: MCO | J11: HIO | K11: PIHP | L11: PAHP | M11: NEMT PAHP | O11: PCCME | P11: EXISTING | Q11: =IF(OR(AND($C$2="Base contract",$C$3="No, section requirements must be reviewed",#REF!= FALSE,#REF!=FALSE),AND($C$2="Contract amendment",$C$3="No, section requirements must be reviewed",#REF!=FALSE,#REF!=FALSE)),"MUNN") | R11: 42556 | U11: =IF(OR($E$8="N/A",AND(AU11=0,'Cover Sheet'!$B$29="Streamlined Review"),AND(E11="Met",F11<>""),AND(E11="Not met",G11<>""),AND(E11="Unsure",G11<>""),AND(E11="N/A",H11<>""),AND(Y11=TRUE)),1,0) | W11: =IF(OR(AND($H$6="Medicaid",MID($A11,1,FIND(".",$A11,1)-1)="II"),AND($H$6="CHIP",MID($A11,1,FIND(".",$A11,1)-1)="I")),TRUE,FALSE) | X11: =IF(OR(Y11=TRUE),TRUE,FALSE) | Y11: =IF(SUM(Z11:AE11)<1,TRUE,FALSE) | Z11: =IF($Z$2=I11,1,0) | AA11: =IF($AA$2=J11,1,0) | AB11: =IF($AB$2=K11,1,0) | AC11: =IF($AC$2=L11,1,0) | AD11: =IF($AD$2=M11,1,0) | AE11: =IF($AE$2=O11,1,0) | AM11: =IF(AL11=1,1,"") | AU11: 1
C12: I.B.2 Choice of Doctor | Z12: =IF($Z$2=I12,1,0) | AA12: =IF($AA$2=J12,1,0) | AB12: =IF($AB$2=K12,1,0) | AC12: =IF($AC$2=L12,1,0) | AD12: =IF($AD$2=M12,1,0) | AE12: =IF($AE$2=O12,1,0)
A13: I.B.2.01 | B13: 42 CFR 438.52(b)–(d); 42 CFR 438.56(c) | C13: The contract requires that for enrollees who qualify under the rural resident exception (under which a state may limit a rural area resident to a single MCP), the limitation on the enrollee’s freedom to change between Primary Care Providers (PCPs) can only be as restrictive as the limitations on disenrollment from the MCP as requested by the enrollee in accordance with 42 CFR 438.56(c). | D13: 1 | F13: Source: CN-680000-FP122: 365, 91, 154, 57, 121, 364, 39, 104 | Attachment - Core Contract Provisions 02012025: 365, 91, 57, 39 | H13: Recommendation: UNCLEAR Response: The retrieved text does not provide explicit evidence regarding the specific limitations on enrollees' freedom to change PCPs under the rural resident exception, nor does it directly reference 42 CFR 438.56(c) in this context. While there are provisions related to enrollees' rights to choose and change PCPs, and general provisions about disenrollment, there is no clear statement linking these to the rural resident exception and the specific regulatory requirement mentioned. Therefore, it is unclear whether the requirement is met based on the provided context. | I13: MCO | J13: HIO | K13: PIHP | L13: PAHP | P13: EXISTING | Q13: =IF(OR(AND($C$2="Base contract",$C$3="No, section requirements must be reviewed",#REF!= FALSE,#REF!=FALSE),AND($C$2="Contract amendment",$C$3="No, section requirements must be reviewed",#REF!=FALSE,#REF!=FALSE)),"MUNN") | U13: =IF(OR($E$12="N/A",AND(AU13=0,'Cover Sheet'!$B$29="Streamlined Review"),AND(E13="Met",F13<>""),AND(E13="Not met",G13<>""),AND(E13="Unsure",G13<>""),AND(E13="N/A",H13<>""),AND(Y13=TRUE)),1,0) | W13: =IF(OR(AND($H$6="Medicaid",MID($A13,1,FIND(".",$A13,1)-1)="II"),AND($H$6="CHIP",MID($A13,1,FIND(".",$A13,1)-1)="I")),TRUE,FALSE) | X13: =IF(OR(Y13=TRUE),TRUE,FALSE) | Y13: =IF(SUM(Z13:AE13)<1,TRUE,FALSE) | Z13: =IF($Z$2=I13,1,0) | AA13: =IF($AA$2=J13,1,0) | AB13: =IF($AB$2=K13,1,0) | AC13: =IF($AC$2=L13,1,0) | AD13: =IF($AD$2=M13,1,0) | AE13: =IF($AE$2=O13,1,0) | AL13: 1 | AM13: =IF(AL13=1,1,"") | AU13: 0
A14: I.B.2.02 | B14: 42 CFR 438.3(l) | C14: The contract requires the MCP to allow each enrollee to choose his or her network provider to the extent possible and appropriate. | F14: Source: CN-680000-FP122: 364: 364 | H14: Recommendation: MET Response: The contract explicitly states that the Managed Care Plan (MCP) shall allow each enrollee to choose his or her network provider to the extent possible and appropriate. This is evidenced by the following quote: 'The Managed Care Plan shall provide information to each enrollee on the importance of selecting a PCP and the procedure for selecting a PCP (Section 409.973(4), F.S.) and shall allow each enrollee to choose his or her network provider to the extent possible and appropriate (42 CFR 438.3(I)).' [CN-680000-FP122: 364] | I14: MCO | J14: HIO | K14: PIHP | L14: PAHP | M14: NEMT PAHP | P14: EXISTING | Q14: =IF(OR(AND($C$2="Base contract",$C$3="No, section requirements must be reviewed",#REF!= FALSE,#REF!=FALSE),AND($C$2="Contract amendment",$C$3="No, section requirements must be reviewed",#REF!=FALSE,#REF!=FALSE)),"MUNN") | U14: =IF(OR($E$12="N/A",AND(AU14=0,'Cover Sheet'!$B$29="Streamlined Review"),AND(E14="Met",F14<>""),AND(E14="Not met",G14<>""),AND(E14="Unsure",G14<>""),AND(E14="N/A",H14<>""),AND(Y14=TRUE)),1,0) | W14: =IF(OR(AND($H$6="Medicaid",MID($A14,1,FIND(".",$A14,1)-1)="II"),AND($H$6="CHIP",MID($A14,1,FIND(".",$A14,1)-1)="I")),TRUE,FALSE) | X14: =IF(OR(Y14=TRUE),TRUE,FALSE) | Y14: =IF(SUM(Z14:AE14)<1,TRUE,FALSE) | Z14: =IF($Z$2=I14,1,0) | AA14: =IF($AA$2=J14,1,0) | AB14: =IF($AB$2=K14,1,0) | AC14: =IF($AC$2=L14,1,0) | AD14: =IF($AD$2=M14,1,0) | AE14: =IF($AE$2=O14,1,0) | AM14: =IF(AL14=1,1,"") | AU14: 0
C15: I.B.3 Opt-Out | Z15: =IF($Z$2=I15,1,0) | AA15: =IF($AA$2=J15,1,0) | AB15: =IF($AB$2=K15,1,0) | AC15: =IF($AC$2=L15,1,0) | AD15: =IF($AD$2=M15,1,0) | AE15: =IF($AE$2=O15,1,0)
A16: I.B.3.01 | B16: 42 CFR 438.3(d)(2) | C16: The contract provides that MCP enrollment is voluntary, except when CMS has approved federal authority allowing the state to mandate enrollment. | F16: Source: CN-680000-FP122: 107 | Attachment - Core Contract Provisions 02012025: 43 | H16: Recommendation: MET Response: The contract explicitly states that enrollment in the Managed Care Plan is not mandatory unless CMS has approved federal authority allowing the state to mandate enrollment. This is evidenced by the text: 'Claim that a Medicaid recipient must enroll in the Managed Care Plan to obtain or to not lose Medicaid benefits or any other health or welfare benefits (42 CFR 438.104(b)(2)(i)).' [1] [2] | I16: MCO | J16: HIO | K16: PIHP | L16: PAHP | M16: NEMT PAHP | P16: EXISTING | Q16: =IF(OR(AND($C$2="Base contract",$C$3="No, section requirements must be reviewed",#REF!= FALSE,#REF!=FALSE),AND($C$2="Contract amendment",$C$3="No, section requirements must be reviewed",#REF!=FALSE,#REF!=FALSE)),"MUNN") | U16: =IF(OR($E$15="N/A",AND(AU16=0,'Cover Sheet'!$B$29="Streamlined Review"),AND(E16="Met",F16<>""),AND(E16="Not met",G16<>""),AND(E16="Unsure",G16<>""),AND(E16="N/A",H16<>""),AND(Y16=TRUE)),1,0) | W16: =IF(OR(AND($H$6="Medicaid",MID($A16,1,FIND(".",$A16,1)-1)="II"),AND($H$6="CHIP",MID($A16,1,FIND(".",$A16,1)-1)="I")),TRUE,FALSE) | X16: =IF(OR(Y16=TRUE),TRUE,FALSE) | Y16: =IF(SUM(Z16:AE16)<1,TRUE,FALSE) | Z16: =IF($Z$2=I16,1,0) | AA16: =IF($AA$2=J16,1,0) | AB16: =IF($AB$2=K16,1,0) | AC16: =IF($AC$2=L16,1,0) | AD16: =IF($AD$2=M16,1,0) | AE16: =IF($AE$2=O16,1,0) | AL16: 1 | AM16: =IF(AL16=1,1,"") | AU16: 0
C17: I.B.4 Reenrollment | Z17: =IF($Z$2=I17,1,0) | AA17: =IF($AA$2=J17,1,0) | AB17: =IF($AB$2=K17,1,0) | AC17: =IF($AC$2=L17,1,0) | AD17: =IF($AD$2=M17,1,0) | AE17: =IF($AE$2=O17,1,0)
A18: I.B.4.01 | B18: 42 CFR 438.56(g) | C18: If specified by the federal authority (SPA or waiver) approved by CMS, the contract provides for automatic reenrollment of a recipient who is disenrolled solely because he or she loses Medicaid eligibility for a period of 2 months or less. | F18: Source: Attachment - Core Contract Provisions 02012025: 60, 124 | CN-680000-FP122: 148 | H18: Recommendation: MET Response: The contract explicitly states that enrollees who lose eligibility and are disenrolled shall be automatically reinstated in the Managed Care Plan if eligibility is regained within the temporary loss period of one hundred eighty (180) days. This period includes the 2 months or less specified in the requirement. [1][2] | I18: MCO | J18: HIO | K18: PIHP | L18: PAHP | M18: NEMT PAHP | P18: EXISTING | Q18: =IF(OR(AND($C$2="Base contract",$C$3="No, section requirements must be reviewed",#REF!= FALSE,#REF!=FALSE),AND($C$2="Contract amendment",$C$3="No, section requirements must be reviewed",#REF!=FALSE,#REF!=FALSE)),"MUNN") | U18: =IF(OR($E$17="N/A",AND(AU18=0,'Cover Sheet'!$B$29="Streamlined Review"),AND(E18="Met",F18<>""),AND(E18="Not met",G18<>""),AND(E18="Unsure",G18<>""),AND(E18="N/A",H18<>""),AND(Y18=TRUE)),1,0) | W18: =IF(OR(AND($H$6="Medicaid",MID($A18,1,FIND(".",$A18,1)-1)="II"),AND($H$6="CHIP",MID($A18,1,FIND(".",$A18,1)-1)="I")),TRUE,FALSE) | X18: =IF(OR(Y18=TRUE),TRUE,FALSE) | Y18: =IF(SUM(Z18:AE18)<1,TRUE,FALSE) | Z18: =IF($Z$2=I18,1,0) | AA18: =IF($AA$2=J18,1,0) | AB18: =IF($AB$2=K18,1,0) | AC18: =IF($AC$2=L18,1,0) | AD18: =IF($AD$2=M18,1,0) | AE18: =IF($AE$2=O18,1,0) | AM18: =IF(AL18=1,1,"") | AU18: 0
C19: I.B.5 Disenrollment | Z19: =IF($Z$2=I19,1,0) | AA19: =IF($AA$2=J19,1,0) | AB19: =IF($AB$2=K19,1,0) | AC19: =IF($AC$2=L19,1,0) | AD19: =IF($AD$2=M19,1,0) | AE19: =IF($AE$2=O19,1,0)
A20: I.B.5.01–05 | B20: Section 1903(m)(2)(A)(v) of the Act; 42 CFR 438.56(b)(1)–(2) | C20: The contract specifies the reasons for which the MCP may request disenrollment and provides that the MCP may not request disenrollment because of: an adverse change in the enrollee's health status, utilization of medical services, diminished mental capacity, or uncooperative or disruptive behavior resulting from his or her special needs. | F20: Source: Attachment - Core Contract Provisions 02012025: 40, 41 | CN-680000-FP122: 105, 106 | H20: Recommendation: MET Response: The contract explicitly states the reasons for which the Managed Care Plan (MCP) may request disenrollment and specifies that the MCP may not request disenrollment due to an adverse change in the enrollee's health status, utilization of medical services, diminished mental capacity, or uncooperative or disruptive behavior resulting from his or her special needs. Evidence: - "The Managed Care Plan shall not request disenrollment of an enrollee due to: (1) Health diagnosis (2) Adverse changes in an enrollee's health status (3) Utilization of medical services (4) Diminished mental capacity" [Attachment - Core Contract Provisions 02012025: 40, CN-680000-FP122: 105] - "The enrollee's uncooperative or disruptive behavior resulting from his or her special needs (except when his or her continued enrollment seriously impairs the Managed Care Plan's ability to furnish services to the enrollee or other enrollees)" [Attachment - Core Contract Provisions 02012025: 41, CN-680000-FP122: 106] | I20: MCO | J20: HIO | K20: PIHP | L20: PAHP | M20: NEMT PAHP | P20: EXISTING | Q20: =IF(OR(AND($C$2="Base contract",$C$3="No, section requirements must be reviewed",#REF!= FALSE,#REF!=FALSE),AND($C$2="Contract amendment",$C$3="No, section requirements must be reviewed",#REF!=FALSE,#REF!=FALSE)),"MUNN") | U20: =IF(OR($E$19="N/A",AND(AU20=0,'Cover Sheet'!$B$29="Streamlined Review"),AND(E20="Met",F20<>""),AND(E20="Not met",G20<>""),AND(E20="Unsure",G20<>""),AND(E20="N/A",H20<>""),AND(Y20=TRUE)),1,0) | W20: =IF(OR(AND($H$6="Medicaid",MID($A20,1,FIND(".",$A20,1)-1)="II"),AND($H$6="CHIP",MID($A20,1,FIND(".",$A20,1)-1)="I")),TRUE,FALSE) | X20: =IF(OR(Y20=TRUE),TRUE,FALSE) | Y20: =IF(SUM(Z20:AE20)<1,TRUE,FALSE) | Z20: =IF($Z$2=I20,1,0) | AA20: =IF($AA$2=J20,1,0) | AB20: =IF($AB$2=K20,1,0) | AC20: =IF($AC$2=L20,1,0) | AD20: =IF($AD$2=M20,1,0) | AE20: =IF($AE$2=O20,1,0) | AM20: =IF(AL20=1,1,"") | AU20: 1
A21: I.B.5.06 | B21: 42 CFR 438.56(b)(3) | C21: The contract specifies the methods by which the MCP assures the state that it does not request disenrollment for reasons other than those permitted under the contract. | F21: Source: CN-680000-FP122: 106, 41 | Attachment - Core Contract Provisions 02012025: 39, 104, 148 | CN-680000-FP122: 285, 225 | H21: Recommendation: UNCLEAR Response: The retrieved text mentions the process of involuntary disenrollment and the responsibilities of the Managed Care Plan (MCP) in notifying enrollees and maintaining records, but it does not explicitly specify the methods by which the MCP assures the state that it does not request disenrollment for reasons other than those permitted under the contract. Additional information is needed to determine if this requirement is met. | I21: MCO | J21: HIO | K21: PIHP | L21: PAHP | M21: NEMT PAHP | P21: EXISTING | Q21: =IF(OR(AND($C$2="Base contract",$C$3="No, section requirements must be reviewed",#REF!= FALSE,#REF!=FALSE),AND($C$2="Contract amendment",$C$3="No, section requirements must be reviewed",#REF!=FALSE,#REF!=FALSE)),"MUNN") | U21: =IF(OR($E$19="N/A",AND(AU21=0,'Cover Sheet'!$B$29="Streamlined Review"),AND(E21="Met",F21<>""),AND(E21="Not met",G21<>""),AND(E21="Unsure",G21<>""),AND(E21="N/A",H21<>""),AND(Y21=TRUE)),1,0) | W21: =IF(OR(AND($H$6="Medicaid",MID($A21,1,FIND(".",$A21,1)-1)="II"),AND($H$6="CHIP",MID($A21,1,FIND(".",$A21,1)-1)="I")),TRUE,FALSE) | X21: =IF(OR(Y21=TRUE),TRUE,FALSE) | Y21: =IF(SUM(Z21:AE21)<1,TRUE,FALSE) | Z21: =IF($Z$2=I21,1,0) | AA21: =IF($AA$2=J21,1,0) | AB21: =IF($AB$2=K21,1,0) | AC21: =IF($AC$2=L21,1,0) | AD21: =IF($AD$2=M21,1,0) | AE21: =IF($AE$2=O21,1,0) | AM21: =IF(AL21=1,1,"") | AU21: 0
A22: I.B.5.07 | B22: 42 CFR 438.3(q)(5); 42 CFR 438.3(r); 42 CFR 438.56(c)(1) | C22: For states that limit disenrollment, the contract requires that enrollees have the right to disenroll from their MCP for cause, at any time. | F22: Source: Attachment - Core Contract Provisions 02012025: 39 | CN-680000-FP122: 104 | H22: Recommendation: MET Response: The contract explicitly states that the Managed Care Plan shall ensure that it does not restrict the enrollee's right to disenroll voluntarily in any way. This indicates that enrollees have the right to disenroll for cause at any time. Evidence: - "The Managed Care Plan shall ensure that it does not restrict the enrollee's right to disenroll voluntarily in any way." (Attachment - Core Contract Provisions 02012025: 39) - "The Managed Care Plan shall ensure that it does not restrict the enrollee's right to disenroll voluntarily in any way." (CN-680000-FP122: 104) | I22: MCO | J22: HIO | K22: PIHP | L22: PAHP | M22: NEMT PAHP | O22: PCCME | P22: EXISTING | Q22: =IF(OR(AND($C$2="Base contract",$C$3="No, section requirements must be reviewed",#REF!= FALSE,#REF!=FALSE),AND($C$2="Contract amendment",$C$3="No, section requirements must be reviewed",#REF!=FALSE,#REF!=FALSE)),"MUNN") | U22: =IF(OR($E$19="N/A",AND(AU22=0,'Cover Sheet'!$B$29="Streamlined Review"),AND(E22="Met",F22<>""),AND(E22="Not met",G22<>""),AND(E22="Unsure",G22<>""),AND(E22="N/A",H22<>""),AND(Y22=TRUE)),1,0) | W22: =IF(OR(AND($H$6="Medicaid",MID($A22,1,FIND(".",$A22,1)-1)="II"),AND($H$6="CHIP",MID($A22,1,FIND(".",$A22,1)-1)="I")),TRUE,FALSE) | X22: =IF(OR(Y22=TRUE),TRUE,FALSE) | Y22: =IF(SUM(Z22:AE22)<1,TRUE,FALSE) | Z22: =IF($Z$2=I22,1,0) | AA22: =IF($AA$2=J22,1,0) | AB22: =IF($AB$2=K22,1,0) | AC22: =IF($AC$2=L22,1,0) | AD22: =IF($AD$2=M22,1,0) | AE22: =IF($AE$2=O22,1,0) | AM22: =IF(AL22=1,1,"") | AU22: 0
A23: I.B.5.08 | B23: 42 CFR 438.3(q)(5); 42 CFR 438.3(r); 42 CFR 438.56(c)(2)(i) | C23: For states that limit disenrollment, the contract requires that enrollees have the right to disenroll from their MCP without cause 90 days after initial enrollment or during the 90 days following notification of enrollment, whichever is later. | F23: Source: CN-680000-FP122: 284, 159, 124, 104 | Attachment - Core Contract Provisions 02012025: 224, 39, 105 | H23: Recommendation: UNCLEAR Response: The retrieved text does not provide explicit evidence that enrollees have the right to disenroll from their Managed Care Plan (MCP) without cause 90 days after initial enrollment or during the 90 days following notification of enrollment, whichever is later. While there are mentions of enrollees' rights to disenroll and specific timelines for certain actions, the exact requirement as stated is not clearly supported by the provided context. More specific information regarding the 90-day disenrollment period is needed to make a definitive determination. | I23: MCO | J23: HIO | K23: PIHP | L23: PAHP | M23: NEMT PAHP | O23: PCCME | P23: EXISTING | Q23: =IF(OR(AND($C$2="Base contract",$C$3="No, section requirements must be reviewed",#REF!= FALSE,#REF!=FALSE),AND($C$2="Contract amendment",$C$3="No, section requirements must be reviewed",#REF!=FALSE,#REF!=FALSE)),"MUNN") | U23: =IF(OR($E$19="N/A",AND(AU23=0,'Cover Sheet'!$B$29="Streamlined Review"),AND(E23="Met",F23<>""),AND(E23="Not met",G23<>""),AND(E23="Unsure",G23<>""),AND(E23="N/A",H23<>""),AND(Y23=TRUE)),1,0) | W23: =IF(OR(AND($H$6="Medicaid",MID($A23,1,FIND(".",$A23,1)-1)="II"),AND($H$6="CHIP",MID($A23,1,FIND(".",$A23,1)-1)="I")),TRUE,FALSE) | X23: =IF(OR(Y23=TRUE),TRUE,FALSE) | Y23: =IF(SUM(Z23:AE23)<1,TRUE,FALSE) | Z23: =IF($Z$2=I23,1,0) | AA23: =IF($AA$2=J23,1,0) | AB23: =IF($AB$2=K23,1,0) | AC23: =IF($AC$2=L23,1,0) | AD23: =IF($AD$2=M23,1,0) | AE23: =IF($AE$2=O23,1,0) | AM23: =IF(AL23=1,1,"") | AU23: 0
A24: I.B.5.09 | B24: 42 CFR 438.3(q)(5); 42 CFR 438.3(r); 42 CFR 438.56(c)(2)(ii) | C24: For states that limit disenrollment, the contract requires that enrollees have the right to disenroll from their MCP without cause at least once every 12 months. | F24: Source: Attachment - Core Contract Provisions 02012025: 39, 104 | CN-680000-FP122: 104, 124 | H24: Recommendation: MET Response: The contract explicitly states that the Managed Care Plan shall ensure that it does not restrict the enrollee's right to disenroll voluntarily in any way. This indicates that enrollees have the right to disenroll without cause. Additionally, the contract mentions that enrollees have the right to change their Managed Care Plan selections, subject to Medicaid limitations, which implies the right to disenroll at least once every 12 months. Evidence: - "The Managed Care Plan shall ensure that it does not restrict the enrollee's right to disenroll voluntarily in any way." [1] - "The enrollees' right to change their Managed Care Plan selections, subject to Medicaid limitations." [2] | I24: MCO | J24: HIO | K24: PIHP | L24: PAHP | M24: NEMT PAHP | O24: PCCME | P24: EXISTING | Q24: =IF(OR(AND($C$2="Base contract",$C$3="No, section requirements must be reviewed",#REF!= FALSE,#REF!=FALSE),AND($C$2="Contract amendment",$C$3="No, section requirements must be reviewed",#REF!=FALSE,#REF!=FALSE)),"MUNN") | U24: =IF(OR($E$19="N/A",AND(AU24=0,'Cover Sheet'!$B$29="Streamlined Review"),AND(E24="Met",F24<>""),AND(E24="Not met",G24<>""),AND(E24="Unsure",G24<>""),AND(E24="N/A",H24<>""),AND(Y24=TRUE)),1,0) | W24: =IF(OR(AND($H$6="Medicaid",MID($A24,1,FIND(".",$A24,1)-1)="II"),AND($H$6="CHIP",MID($A24,1,FIND(".",$A24,1)-1)="I")),TRUE,FALSE) | X24: =IF(OR(Y24=TRUE),TRUE,FALSE) | Y24: =IF(SUM(Z24:AE24)<1,TRUE,FALSE) | Z24: =IF($Z$2=I24,1,0) | AA24: =IF($AA$2=J24,1,0) | AB24: =IF($AB$2=K24,1,0) | AC24: =IF($AC$2=L24,1,0) | AD24: =IF($AD$2=M24,1,0) | AE24: =IF($AE$2=O24,1,0) | AM24: =IF(AL24=1,1,"") | AU24: 0
A25: I.B.5.10 | B25: 42 CFR 438.3(q)(5); 42 CFR 438.3(r); 42 CFR 438.56(c)(2)(iii) | C25: For states that limit disenrollment, the contract requires that enrollees have the right to disenroll from their MCP without cause upon reenrollment if a temporary loss of enrollment has caused the enrollee to miss the annual disenrollment period. | F25: Source: CN-680000-FP122: 124: 124 | H25: Recommendation: UNCLEAR Response: The retrieved text mentions that enrollees who lose eligibility and are disenrolled shall be automatically reinstated in the Managed Care Plan if eligibility is regained within the temporary loss period of one hundred eighty (180) days [1]. However, it does not explicitly state that enrollees have the right to disenroll without cause upon reenrollment if they missed the annual disenrollment period due to a temporary loss of enrollment. Therefore, the information provided is insufficient to determine if the requirement is met. [1] CN-680000-FP122: 124 | I25: MCO | J25: HIO | K25: PIHP | L25: PAHP | M25: NEMT PAHP | O25: PCCME | P25: EXISTING | Q25: =IF(OR(AND($C$2="Base contract",$C$3="No, section requirements must be reviewed",#REF!= FALSE,#REF!=FALSE),AND($C$2="Contract amendment",$C$3="No, section requirements must be reviewed",#REF!=FALSE,#REF!=FALSE)),"MUNN") | U25: =IF(OR($E$19="N/A",AND(AU25=0,'Cover Sheet'!$B$29="Streamlined Review"),AND(E25="Met",F25<>""),AND(E25="Not met",G25<>""),AND(E25="Unsure",G25<>""),AND(E25="N/A",H25<>""),AND(Y25=TRUE)),1,0) | W25: =IF(OR(AND($H$6="Medicaid",MID($A25,1,FIND(".",$A25,1)-1)="II"),AND($H$6="CHIP",MID($A25,1,FIND(".",$A25,1)-1)="I")),TRUE,FALSE) | X25: =IF(OR(Y25=TRUE),TRUE,FALSE) | Y25: =IF(SUM(Z25:AE25)<1,TRUE,FALSE) | Z25: =IF($Z$2=I25,1,0) | AA25: =IF($AA$2=J25,1,0) | AB25: =IF($AB$2=K25,1,0) | AC25: =IF($AC$2=L25,1,0) | AD25: =IF($AD$2=M25,1,0) | AE25: =IF($AE$2=O25,1,0) | AM25: =IF(AL25=1,1,"") | AU25: 0
A26: I.B.5.11 | B26: 42 CFR 438.3(q)(5); 42 CFR 438.3(r); 42 CFR 438.56(c)(2)(iv) | C26: For states that limit disenrollment, the contract requires that enrollees have the right to disenroll from their MCP without cause when the state imposes intermediate sanctions on the MCP. | D26: 2 | F26: Source: Attachment - Core Contract Provisions 02012025: 40, 105 | CN-680000-FP122: 40, 105 | H26: Recommendation: MET Response: The contract explicitly states that enrollees have the right to disenroll from the Managed Care Plan (MCP) without cause when the state imposes intermediate sanctions on the MCP. This is evidenced by the text: 'The Agency has posed intermediate sanctions on the Managed Care Plan (42 CFR 438.3(q)(5); 42 CFR 438.56(c)(2)(iv)).' [1][2] | I26: MCO | J26: HIO | O26: PCCME | P26: EXISTING | Q26: =IF(OR(AND($C$2="Base contract",$C$3="No, section requirements must be reviewed",#REF!= FALSE,#REF!=FALSE),AND($C$2="Contract amendment",$C$3="No, section requirements must be reviewed",#REF!=FALSE,#REF!=FALSE)),"MUNN") | U26: =IF(OR($E$19="N/A",AND(AU26=0,'Cover Sheet'!$B$29="Streamlined Review"),AND(E26="Met",F26<>""),AND(E26="Not met",G26<>""),AND(E26="Unsure",G26<>""),AND(E26="N/A",H26<>""),AND(Y26=TRUE)),1,0) | W26: =IF(OR(AND($H$6="Medicaid",MID($A26,1,FIND(".",$A26,1)-1)="II"),AND($H$6="CHIP",MID($A26,1,FIND(".",$A26,1)-1)="I")),TRUE,FALSE) | X26: =IF(OR(Y26=TRUE),TRUE,FALSE) | Y26: =IF(SUM(Z26:AE26)<1,TRUE,FALSE) | Z26: =IF($Z$2=I26,1,0) | AA26: =IF($AA$2=J26,1,0) | AB26: =IF($AB$2=K26,1,0) | AC26: =IF($AC$2=L26,1,0) | AD26: =IF($AD$2=M26,1,0) | AE26: =IF($AE$2=O26,1,0) | AM26: =IF(AL26=1,1,"") | AU26: 0
A27: I.B.5.12 | B27: 42 CFR 438.56(d)(2)(i) | C27: The contract allows enrollees to request disenrollment if the enrollee moves out of the service area. | F27: Source: CN-680000-FP122: 148, 104, 39, 85, 106, 41, 283, 223 | Attachment - Core Contract Provisions 02012025: 148, 104, 39, 85, 106, 41, 283, 223 | H27: Recommendation: NOT MET Response: The contract explicitly states that enrollees are not allowed to file an appeal on disenrollment if they move out of the region. This implies that moving out of the service area is a reason for automatic disenrollment without the need for a request. Evidence: - "All enrollees shall be afforded the right to file an appeal on disenrollment except for the following reasons: (1) Moving out of the region." [CN-680000-FP122: 148, 104, 39, 85, 106, 41, 283, 223] | I27: MCO | J27: HIO | K27: PIHP | L27: PAHP | M27: NEMT PAHP | P27: EXISTING | Q27: =IF(OR(AND($C$2="Base contract",$C$3="No, section requirements must be reviewed",#REF!= FALSE,#REF!=FALSE),AND($C$2="Contract amendment",$C$3="No, section requirements must be reviewed",#REF!=FALSE,#REF!=FALSE)),"MUNN") | U27: =IF(OR($E$19="N/A",AND(AU27=0,'Cover Sheet'!$B$29="Streamlined Review"),AND(E27="Met",F27<>""),AND(E27="Not met",G27<>""),AND(E27="Unsure",G27<>""),AND(E27="N/A",H27<>""),AND(Y27=TRUE)),1,0) | W27: =IF(OR(AND($H$6="Medicaid",MID($A27,1,FIND(".",$A27,1)-1)="II"),AND($H$6="CHIP",MID($A27,1,FIND(".",$A27,1)-1)="I")),TRUE,FALSE) | X27: =IF(OR(Y27=TRUE),TRUE,FALSE) | Y27: =IF(SUM(Z27:AE27)<1,TRUE,FALSE) | Z27: =IF($Z$2=I27,1,0) | AA27: =IF($AA$2=J27,1,0) | AB27: =IF($AB$2=K27,1,0) | AC27: =IF($AC$2=L27,1,0) | AD27: =IF($AD$2=M27,1,0) | AE27: =IF($AE$2=O27,1,0) | AM27: =IF(AL27=1,1,"") | AU27: 0
A28: I.B.5.13 | B28: 42 CFR 438.56(d)(2)(ii) | C28: The contract allows enrollees to request disenrollment if the plan does not cover the service the enrollee seeks because of moral or religious objections. | F28: Source: Attachment - Core Contract Provisions 02012025: 70, 134 | CN-680000-FP122: 70, 134 | CN-680000-FP122: 104 | Attachment - Core Contract Provisions 02012025: 39 | H28: Recommendation: UNCLEAR Response: The retrieved text mentions that the Managed Care Plan shall provide or arrange for the provision of all covered services and that if the Plan elects not to provide or reimburse for counseling or referral to a covered service because of an objection on moral or religious grounds, the Plan shall notify [1]. However, there is no explicit statement that enrollees are allowed to request disenrollment specifically because of moral or religious objections to covered services. The text does mention that enrollees have the right to disenroll voluntarily [2], but it does not specify the reasons for which disenrollment can be requested. Therefore, it is unclear whether the contract explicitly allows for disenrollment based on moral or religious objections to covered services. [1] Attachment - Core Contract Provisions 02012025: 70, 134 | CN-680000-FP122: 70, 134 [2] CN-680000-FP122: 104 | Attachment - Core Contract Provisions 02012025: 39 | I28: MCO | J28: HIO | K28: PIHP | L28: PAHP | M28: NEMT PAHP | P28: EXISTING | Q28: =IF(OR(AND($C$2="Base contract",$C$3="No, section requirements must be reviewed",#REF!= FALSE,#REF!=FALSE),AND($C$2="Contract amendment",$C$3="No, section requirements must be reviewed",#REF!=FALSE,#REF!=FALSE)),"MUNN") | U28: =IF(OR($E$19="N/A",AND(AU28=0,'Cover Sheet'!$B$29="Streamlined Review"),AND(E28="Met",F28<>""),AND(E28="Not met",G28<>""),AND(E28="Unsure",G28<>""),AND(E28="N/A",H28<>""),AND(Y28=TRUE)),1,0) | W28: =IF(OR(AND($H$6="Medicaid",MID($A28,1,FIND(".",$A28,1)-1)="II"),AND($H$6="CHIP",MID($A28,1,FIND(".",$A28,1)-1)="I")),TRUE,FALSE) | X28: =IF(OR(Y28=TRUE),TRUE,FALSE) | Y28: =IF(SUM(Z28:AE28)<1,TRUE,FALSE) | Z28: =IF($Z$2=I28,1,0) | AA28: =IF($AA$2=J28,1,0) | AB28: =IF($AB$2=K28,1,0) | AC28: =IF($AC$2=L28,1,0) | AD28: =IF($AD$2=M28,1,0) | AE28: =IF($AE$2=O28,1,0) | AM28: =IF(AL28=1,1,"") | AU28: 0
A29: I.B.5.14 | B29: 42 CFR 438.56(d)(2)(iii) | C29: The contract allows enrollees to request disenrollment if the enrollee needs related services to be performed at the same time and not all related services are available within the provider network. The enrollee's PCP or another provider must determine that receiving the services separately would subject the enrollee to unnecessary risk. | D29: 3 | F29: Source: Attachment - Core Contract Provisions 02012025: 39, 104 | CN-680000-FP122: 104, 167, 168 | H29: Recommendation: UNCLEAR Response: The retrieved text does not provide explicit evidence that enrollees can request disenrollment under the specified conditions. While the text mentions the enrollee's right to disenroll voluntarily and the process for disenrollment, it does not specify the conditions related to the availability of related services within the provider network or the requirement for a PCP or provider to determine unnecessary risk. [1][2][3] | I29: MCO | J29: HIO | K29: PIHP | L29: PAHP | P29: EXISTING | Q29: =IF(OR(AND($C$2="Base contract",$C$3="No, section requirements must be reviewed",#REF!= FALSE,#REF!=FALSE),AND($C$2="Contract amendment",$C$3="No, section requirements must be reviewed",#REF!=FALSE,#REF!=FALSE)),"MUNN") | U29: =IF(OR($E$19="N/A",AND(AU29=0,'Cover Sheet'!$B$29="Streamlined Review"),AND(E29="Met",F29<>""),AND(E29="Not met",G29<>""),AND(E29="Unsure",G29<>""),AND(E29="N/A",H29<>""),AND(Y29=TRUE)),1,0) | W29: =IF(OR(AND($H$6="Medicaid",MID($A29,1,FIND(".",$A29,1)-1)="II"),AND($H$6="CHIP",MID($A29,1,FIND(".",$A29,1)-1)="I")),TRUE,FALSE) | X29: =IF(OR(Y29=TRUE),TRUE,FALSE) | Y29: =IF(SUM(Z29:AE29)<1,TRUE,FALSE) | Z29: =IF($Z$2=I29,1,0) | AA29: =IF($AA$2=J29,1,0) | AB29: =IF($AB$2=K29,1,0) | AC29: =IF($AC$2=L29,1,0) | AD29: =IF($AD$2=M29,1,0) | AE29: =IF($AE$2=O29,1,0) | AM29: =IF(AL29=1,1,"") | AU29: 0
A30: I.B.5.15 | B30: 42 CFR 438.56(d)(2)(iv) | C30: The contract allows enrollees who use Managed Long-Term Services and Supports (MLTSS) to request disenrollment if a provider's change in status from an in-network to an out-of-network provider with the MCP would cause the enrollee to have to change their residential, institutional, or employment supports provider, and, as a result, the enrollee would experience a disruption in their residence or employment. | F30: Source: CN-680000-FP122: 43, 18, 284, 168, 105, 104, 413 | Attachment - Core Contract Provisions 02012025: 104, 39 | H30: Recommendation: UNCLEAR Response: The retrieved text does not provide explicit evidence that enrollees using MLTSS can request disenrollment under the specified conditions. While there are provisions regarding provider termination and enrollee notification, there is no specific mention of MLTSS enrollees' rights to disenroll due to a change in provider status that would disrupt their residence or employment. Additional specific information is needed to determine if this requirement is met. | I30: MCO | J30: HIO | K30: PIHP | L30: PAHP | P30: EXISTING | Q30: =IF(OR(AND($C$2="Base contract",$C$3="No, section requirements must be reviewed",#REF!= FALSE,#REF!=FALSE),AND($C$2="Contract amendment",$C$3="No, section requirements must be reviewed",#REF!=FALSE,#REF!=FALSE)),"MUNN") | R30: 42917 | U30: =IF(OR($E$19="N/A",AND(AU30=0,'Cover Sheet'!$B$29="Streamlined Review"),AND(E30="Met",F30<>""),AND(E30="Not met",G30<>""),AND(E30="Unsure",G30<>""),AND(E30="N/A",H30<>""),AND(Y30=TRUE)),1,0) | W30: =IF(OR(AND($H$6="Medicaid",MID($A30,1,FIND(".",$A30,1)-1)="II"),AND($H$6="CHIP",MID($A30,1,FIND(".",$A30,1)-1)="I")),TRUE,FALSE) | X30: =IF(OR(Y30=TRUE),TRUE,FALSE) | Y30: =IF(SUM(Z30:AE30)<1,TRUE,FALSE) | Z30: =IF($Z$2=I30,1,0) | AA30: =IF($AA$2=J30,1,0) | AB30: =IF($AB$2=K30,1,0) | AC30: =IF($AC$2=L30,1,0) | AD30: =IF($AD$2=M30,1,0) | AE30: =IF($AE$2=O30,1,0) | AM30: =IF(AL30=1,1,"") | AU30: 0
A31: I.B.5.16 | B31: 42 CFR 438.56(d)(2)(v) | C31: The contract allows enrollees to request disenrollment for other reasons, including poor quality of care, lack of access to services covered under the contract, or lack of access to providers experienced in dealing with the enrollee's care needs. | F31: Source: CN-680000-FP122: 148, 153, 40, 105, 104, 39, 41, 106 | Attachment - Core Contract Provisions 02012025: 39, 40, 41 | H31: Recommendation: UNCLEAR Response: The retrieved text does not provide explicit evidence that enrollees can request disenrollment for reasons such as poor quality of care, lack of access to services, or lack of access to providers experienced in dealing with the enrollee's care needs. The text mentions that enrollees have the right to request disenrollment voluntarily and that the Managed Care Plan shall not restrict this right, but it does not specify the reasons for which enrollees can request disenrollment. Further information is needed to determine if these specific reasons are covered under the contract. | I31: MCO | J31: HIO | K31: PIHP | L31: PAHP | M31: NEMT PAHP | P31: EXISTING | Q31: =IF(OR(AND($C$2="Base contract",$C$3="No, section requirements must be reviewed",#REF!= FALSE,#REF!=FALSE),AND($C$2="Contract amendment",$C$3="No, section requirements must be reviewed",#REF!=FALSE,#REF!=FALSE)),"MUNN") | U31: =IF(OR($E$19="N/A",AND(AU31=0,'Cover Sheet'!$B$29="Streamlined Review"),AND(E31="Met",F31<>""),AND(E31="Not met",G31<>""),AND(E31="Unsure",G31<>""),AND(E31="N/A",H31<>""),AND(Y31=TRUE)),1,0) | W31: =IF(OR(AND($H$6="Medicaid",MID($A31,1,FIND(".",$A31,1)-1)="II"),AND($H$6="CHIP",MID($A31,1,FIND(".",$A31,1)-1)="I")),TRUE,FALSE) | X31: =IF(OR(Y31=TRUE),TRUE,FALSE) | Y31: =IF(SUM(Z31:AE31)<1,TRUE,FALSE) | Z31: =IF($Z$2=I31,1,0) | AA31: =IF($AA$2=J31,1,0) | AB31: =IF($AB$2=K31,1,0) | AC31: =IF($AC$2=L31,1,0) | AD31: =IF($AD$2=M31,1,0) | AE31: =IF($AE$2=O31,1,0) | AM31: =IF(AL31=1,1,"") | AU31: 0
C32: I.B.6 Disenrollment Request Process | Z32: =IF($Z$2=I32,1,0) | AA32: =IF($AA$2=J32,1,0) | AB32: =IF($AB$2=K32,1,0) | AC32: =IF($AC$2=L32,1,0) | AD32: =IF($AD$2=M32,1,0) | AE32: =IF($AE$2=O32,1,0)
A33: I.B.6.01 | B33: 42 CFR 438.56(d)(1)(i)–(ii) | C33: The contract specifies that a recipient (or his or her representative) must request disenrollment by submitting an oral or written request, as required by the state, to the state (or its agent) or the MCP, if the state allows the MCP to process disenrollment requests. | F33: Source: CN-680000-FP122: 104, 106 | Attachment - Core Contract Provisions 02012025: 39, 41 | H33: Recommendation: UNCLEAR Response: The retrieved text mentions that the Agency shall notify enrollees of their right to request disenrollment and shall process all enrollee requests to disenroll from the Managed Care Plan (MCP). However, it does not explicitly state that the recipient or their representative must submit an oral or written request, nor does it specify that the MCP can process disenrollment requests if allowed by the state. Therefore, there is insufficient information to determine if the requirement is met. Evidence: - 'The Agency shall notify enrollees of their right to request disenrollment. The Agency shall process all enrollee requests to disenroll from the Managed Care Plan.' [CN-680000-FP122: 104, Attachment - Core Contract Provisions 02012025: 39] | I33: MCO | J33: HIO | K33: PIHP | L33: PAHP | M33: NEMT PAHP | P33: EXISTING | Q33: =IF(OR(AND($C$2="Base contract",$C$3="No, section requirements must be reviewed",#REF!= FALSE,#REF!=FALSE),AND($C$2="Contract amendment",$C$3="No, section requirements must be reviewed",#REF!=FALSE,#REF!=FALSE)),"MUNN") | U33: =IF(OR($E$32="N/A",AND(AU33=0,'Cover Sheet'!$B$29="Streamlined Review"),AND(E33="Met",F33<>""),AND(E33="Not met",G33<>""),AND(E33="Unsure",G33<>""),AND(E33="N/A",H33<>""),AND(Y33=TRUE)),1,0) | W33: =IF(OR(AND($H$6="Medicaid",MID($A33,1,FIND(".",$A33,1)-1)="II"),AND($H$6="CHIP",MID($A33,1,FIND(".",$A33,1)-1)="I")),TRUE,FALSE) | X33: =IF(OR(Y33=TRUE),TRUE,FALSE) | Y33: =IF(SUM(Z33:AE33)<1,TRUE,FALSE) | Z33: =IF($Z$2=I33,1,0) | AA33: =IF($AA$2=J33,1,0) | AB33: =IF($AB$2=K33,1,0) | AC33: =IF($AC$2=L33,1,0) | AD33: =IF($AD$2=M33,1,0) | AE33: =IF($AE$2=O33,1,0) | AM33: =IF(AL33=1,1,"") | AU33: 0
A34: I.B.6.02 | B34: 42 CFR 438.56(d)(3)(i) | C34: The contract specifies that the MCP may approve a request for disenrollment by or on behalf of the enrollee, if the state allows the MCP to process disenrollment requests, or refer the request to the state. | F34: Source: Attachment - Core Contract Provisions 02012025: 39, 104 | CN-680000-FP122: 39, 104 | H34: Recommendation: NOT MET Response: The retrieved text indicates that the Agency, not the Managed Care Plan (MCP), is responsible for processing and making final determinations about disenrollment requests. The text states, 'The Agency shall process all enrollee requests to disenroll from the Managed Care Plan. The Agency or its agent shall make final determinations about granting disenrollment requests...' (Attachment - Core Contract Provisions 02012025: 39, 104 | CN-680000-FP122: 39, 104). This suggests that the MCP does not have the authority to approve disenrollment requests unless explicitly allowed by the state, and even then, the final decision rests with the Agency. | I34: MCO | J34: HIO | K34: PIHP | L34: PAHP | M34: NEMT PAHP | P34: EXISTING | Q34: =IF(OR(AND($C$2="Base contract",$C$3="No, section requirements must be reviewed",#REF!= FALSE,#REF!=FALSE),AND($C$2="Contract amendment",$C$3="No, section requirements must be reviewed",#REF!=FALSE,#REF!=FALSE)),"MUNN") | U34: =IF(OR($E$32="N/A",AND(AU34=0,'Cover Sheet'!$B$29="Streamlined Review"),AND(E34="Met",F34<>""),AND(E34="Not met",G34<>""),AND(E34="Unsure",G34<>""),AND(E34="N/A",H34<>""),AND(Y34=TRUE)),1,0) | W34: =IF(OR(AND($H$6="Medicaid",MID($A34,1,FIND(".",$A34,1)-1)="II"),AND($H$6="CHIP",MID($A34,1,FIND(".",$A34,1)-1)="I")),TRUE,FALSE) | X34: =IF(OR(Y34=TRUE),TRUE,FALSE) | Y34: =IF(SUM(Z34:AE34)<1,TRUE,FALSE) | Z34: =IF($Z$2=I34,1,0) | AA34: =IF($AA$2=J34,1,0) | AB34: =IF($AB$2=K34,1,0) | AC34: =IF($AC$2=L34,1,0) | AD34: =IF($AD$2=M34,1,0) | AE34: =IF($AE$2=O34,1,0) | AM34: =IF(AL34=1,1,"") | AU34: 0
A35: I.B.6.03 | B35: 42 CFR 438.56(e)(1)–(2); 42 CFR 438.56(d)(3)(ii); 42 CFR 438.3(q); 42 CFR 438.3(r); 42 CFR 438.56(c) | C35: The contract requires that the effective date of an approved disenrollment must be no later than the first day of the second month following the month in which the enrollee requests disenrollment or the MCP refers the request to the state. | F35: Source: CN-680000-FP122: 105 | Attachment - Core Contract Provisions 02012025: 40 | H35: Recommendation: MET Response: The contract explicitly states that the Agency shall make disenrollment requests effective no later than the first day of the second month following the month in which the enrollee requests disenrollment or the Managed Care Plan refers the request for involuntary disenrollment to the Agency. This directly supports the requirement. [1][2] | I35: MCO | J35: HIO | K35: PIHP | L35: PAHP | M35: NEMT PAHP | O35: PCCME | P35: EXISTING | Q35: =IF(OR(AND($C$2="Base contract",$C$3="No, section requirements must be reviewed",#REF!= FALSE,#REF!=FALSE),AND($C$2="Contract amendment",$C$3="No, section requirements must be reviewed",#REF!=FALSE,#REF!=FALSE)),"MUNN") | R35: 42556 | U35: =IF(OR($E$32="N/A",AND(AU35=0,'Cover Sheet'!$B$29="Streamlined Review"),AND(E35="Met",F35<>""),AND(E35="Not met",G35<>""),AND(E35="Unsure",G35<>""),AND(E35="N/A",H35<>""),AND(Y35=TRUE)),1,0) | W35: =IF(OR(AND($H$6="Medicaid",MID($A35,1,FIND(".",$A35,1)-1)="II"),AND($H$6="CHIP",MID($A35,1,FIND(".",$A35,1)-1)="I")),TRUE,FALSE) | X35: =IF(OR(Y35=TRUE),TRUE,FALSE) | Y35: =IF(SUM(Z35:AE35)<1,TRUE,FALSE) | Z35: =IF($Z$2=I35,1,0) | AA35: =IF($AA$2=J35,1,0) | AB35: =IF($AB$2=K35,1,0) | AC35: =IF($AC$2=L35,1,0) | AD35: =IF($AD$2=M35,1,0) | AE35: =IF($AE$2=O35,1,0) | AM35: =IF(AL35=1,1,"") | AU35: 0
A36: I.B.6.04 | B36: 42 CFR 438.56(e)(1)–(2); 42 CFR 438.56(d)(3)(ii); 42 CFR 438.3(q); 42 CFR 438.3(r); 42 CFR 438.56(c) | C36: The contract requires that if the entity or state agency (whichever is responsible) fails to make a disenrollment determination within the specified timeframes (i.e., the first day of the second month following the month in which the enrollee requests disenrollment or the MCP refers the request to the state), the disenrollment is considered approved for the effective date that would have been established had the state or MCP made a determination in the specified timeframe. | F36: Source: Attachment - Core Contract Provisions 02012025: 40 | CN-680000-FP122: 105 | H36: Recommendation: MET Response: The contract explicitly states that if the Agency fails to make a disenrollment determination within the specified timeframes, the disenrollment shall be considered approved for the same effective date that would have been established had the Agency made a determination in the specified timeframe. This is supported by the text: 'If the Agency fails to make a disenrollment determination within the specified timeframes, the disenrollment shall be considered approved for the same effective date that would have been established had the Agency made a determination in the specified timeframe (42 CFR 438.56(e)(1) - (2); 42 CFR 438.56(d)(3)(ii); 42 CFR 438.3(q); 42 CFR 438.56(c))'. | I36: MCO | J36: HIO | K36: PIHP | L36: PAHP | M36: NEMT PAHP | O36: PCCME | P36: EXISTING | Q36: =IF(OR(AND($C$2="Base contract",$C$3="No, section requirements must be reviewed",#REF!= FALSE,#REF!=FALSE),AND($C$2="Contract amendment",$C$3="No, section requirements must be reviewed",#REF!=FALSE,#REF!=FALSE)),"MUNN") | R36: 42556 | U36: =IF(OR($E$32="N/A",AND(AU36=0,'Cover Sheet'!$B$29="Streamlined Review"),AND(E36="Met",F36<>""),AND(E36="Not met",G36<>""),AND(E36="Unsure",G36<>""),AND(E36="N/A",H36<>""),AND(Y36=TRUE)),1,0) | W36: =IF(OR(AND($H$6="Medicaid",MID($A36,1,FIND(".",$A36,1)-1)="II"),AND($H$6="CHIP",MID($A36,1,FIND(".",$A36,1)-1)="I")),TRUE,FALSE) | X36: =IF(OR(Y36=TRUE),TRUE,FALSE) | Y36: =IF(SUM(Z36:AE36)<1,TRUE,FALSE) | Z36: =IF($Z$2=I36,1,0) | AA36: =IF($AA$2=J36,1,0) | AB36: =IF($AB$2=K36,1,0) | AC36: =IF($AC$2=L36,1,0) | AD36: =IF($AD$2=M36,1,0) | AE36: =IF($AE$2=O36,1,0) | AM36: =IF(AL36=1,1,"") | AU36: 0
C37: I.B.7 Special Rules for American Indians | Z37: =IF($Z$2=I37,1,0) | AA37: =IF($AA$2=J37,1,0) | AB37: =IF($AB$2=K37,1,0) | AC37: =IF($AC$2=L37,1,0) | AD37: =IF($AD$2=M37,1,0) | AE37: =IF($AE$2=O37,1,0)
A38: I.B.7.01 | B38: Section 1932(h)(3) of the Act; 42 CFR 438.14(d); SMD #10-001 | C38: For Indian Managed Care Entities (IMCEs), the contract allows the MCP to restrict enrollment of Indians in the same manner as Indian Health Programs may restrict the delivery of services to Indians. | D38: 4 | F38: Source: CN-680000-FP122: 154, 420 | Attachment - Core Contract Provisions 02012025: 91, 134, 195, 234, 284 | H38: Recommendation: UNCLEAR Response: The retrieved text does not provide explicit evidence that the contract allows the Managed Care Plan (MCP) to restrict enrollment of Indians in the same manner as Indian Health Programs may restrict the delivery of services to Indians. The text discusses the maintenance of sufficient Indian Health Care Providers (IHCPs) and the provision of services to Indian enrollees, but it does not explicitly address enrollment restrictions for IMCEs. Evidence: - 'The Managed Care Plan must maintain sufficient Indian Health Care Providers (IHCPs) in the network to ensure timely access to services available under the Contract for Indian enrollees...' [CN-680000-FP122: 154] - 'The Managed Care Plan shall reimburse IHCPs, whether participating in the network or not, for covered managed care services provided to Indian enrollees...' [CN-680000-FP122: 420] | I38: MCO | J38: HIO | K38: PIHP | L38: PAHP | M38: NEMT PAHP | P38: EXISTING | Q38: =IF(OR(AND($C$2="Base contract",$C$3="No, section requirements must be reviewed",#REF!= FALSE,#REF!=FALSE),AND($C$2="Contract amendment",$C$3="No, section requirements must be reviewed",#REF!=FALSE,#REF!=FALSE)),"MUNN") | U38: =IF(OR($E$37="N/A",AND(AU38=0,'Cover Sheet'!$B$29="Streamlined Review"),AND(E38="Met",F38<>""),AND(E38="Not met",G38<>""),AND(E38="Unsure",G38<>""),AND(E38="N/A",H38<>""),AND(Y38=TRUE)),1,0) | W38: =IF(OR(AND($H$6="Medicaid",MID($A38,1,FIND(".",$A38,1)-1)="II"),AND($H$6="CHIP",MID($A38,1,FIND(".",$A38,1)-1)="I")),TRUE,FALSE) | X38: =IF(OR(Y38=TRUE),TRUE,FALSE) | Y38: =IF(SUM(Z38:AE38)<1,TRUE,FALSE) | Z38: =IF($Z$2=I38,1,0) | AA38: =IF($AA$2=J38,1,0) | AB38: =IF($AB$2=K38,1,0) | AC38: =IF($AC$2=L38,1,0) | AD38: =IF($AD$2=M38,1,0) | AE38: =IF($AE$2=O38,1,0) | AM38: =IF(AL38=1,1,"") | AU38: 0
A39: I.B.7.02 | B39: American Reinvestment and Recovery Act (ARRA) Section 5006(d); 42 CFR 438.14(b)(3); SMD #10-001 | C39: The contract requires that any Indian enrolled in an MCP, that is not a IMCE, and eligible to receive services from an IHCP PCP participating as a network provider, is permitted to choose that IHCP as their PCP, as long as that provider has capacity to provide the services. | F39: Source: CN-680000-FP122: 154, 364, 365: 154, 364, 365 | H39: Recommendation: MET Response: The contract explicitly states that the Managed Care Plan must maintain sufficient Indian Health Care Providers (IHCPs) in the network to ensure timely access to services for Indian enrollees who are eligible to receive services from such providers. It also permits out-of-network or out-of-state IHCPs to provide covered services and make referrals to network providers for Indian enrollees. Additionally, the contract allows enrollees to choose their PCP to the extent possible and appropriate, and assigns enrollees to a PCP unless the PCP no longer participates in the Managed Care Plan or is at capacity. Evidence: 1. "The Managed Care Plan must maintain sufficient Indian Health Care Providers (IHCPs) in the network to ensure timely access to services available under the Contract for Indian enrollees who are eligible to receive services from such providers..." (CN-680000-FP122: 154) 2. "The Managed Care Plan shall offer each enrollee a choice of PCPs. After making a choice, each enrollee shall have a single or group PCP." (CN-680000-FP122: 364) 3. "The Managed Care Plan shall assign all enrollees that are reinstated after a temporary loss of eligibility to the PCP who was treating them prior to loss of eligibility, unless the enrollee specifically requests another PCP, or the PCP no longer participates in the Managed Care Plan or is at capacity." (CN-680000-FP122: 365) | I39: MCO | J39: HIO | K39: PIHP | L39: PAHP | M39: NEMT PAHP | P39: EXISTING | Q39: =IF(OR(AND($C$2="Base contract",$C$3="No, section requirements must be reviewed",#REF!= FALSE,#REF!=FALSE),AND($C$2="Contract amendment",$C$3="No, section requirements must be reviewed",#REF!=FALSE,#REF!=FALSE)),"MUNN") | U39: =IF(OR($E$37="N/A",AND(AU39=0,'Cover Sheet'!$B$29="Streamlined Review"),AND(E39="Met",F39<>""),AND(E39="Not met",G39<>""),AND(E39="Unsure",G39<>""),AND(E39="N/A",H39<>""),AND(Y39=TRUE)),1,0) | W39: =IF(OR(AND($H$6="Medicaid",MID($A39,1,FIND(".",$A39,1)-1)="II"),AND($H$6="CHIP",MID($A39,1,FIND(".",$A39,1)-1)="I")),TRUE,FALSE) | X39: =IF(OR(Y39=TRUE),TRUE,FALSE) | Y39: =IF(SUM(Z39:AE39)<1,TRUE,FALSE) | Z39: =IF($Z$2=I39,1,0) | AA39: =IF($AA$2=J39,1,0) | AB39: =IF($AB$2=K39,1,0) | AC39: =IF($AC$2=L39,1,0) | AD39: =IF($AD$2=M39,1,0) | AE39: =IF($AE$2=O39,1,0) | AM39: =IF(AL39=1,1,"") | AU39: 1
A40: Tips and Additional Guidance
A41: 1 | B41: For information on whether a particular county is rural pursuant to 42 CFR 438.52(b), see the current Health Services Delivery (HSD) file here:
B42: https://www.cms.gov/Medicare/Medicare-Advantage/MedicareAdvantageApps/Downloads/HSD_Reference_File_01-10-2017.zip
A43: 2 | B43: A status of N/A is appropriate for PCCM entities if the state does not limit disenrollment and/or does not impose intermediate sanctions on PCCM entities.
A44: 3 | B44: Under 42 CFR 438.56(d)(2)(iii), an example of “related services” is a cesarean section and a tubal ligation.
A45: 4 | B45: Under 42 CFR 438.14(d), a status of “N/A” is appropriate for this item only when the MCP is not an IMCE.

Sheet C. Beneficiary Notification
A1: Subpart C - Beneficiary Notification | J1: Met | M1: =IF($C$2="Base contract","Blist",IF($C$2="Contract Amendment","Alist")) | Z1: This contract applies to the following entity types | AG1: Does the review include Medicaid and CHIP?
A2: Type of Review: | C2: ='Cover Sheet'!B6 | G2: Status of Medicaid Section: | H2: =I2 | I2: =IF(OR($C$3="Yes, section requirements are not applicable",$C$3="Yes, all requirements on the sheet are crosshatched",AND(E8="N/A",E25="N/A",E66="N/A",E68="N/A",E74="N/A",E78="N/A",E81="N/A",E89="N/A",E134="N/A")),"Section Review N/A",IF((COUNTA(A8:A135)+COUNTBLANK(A8:A135)=COUNTBLANK(E8:E135)),"Not Started",IF((COUNTA(A8:A135)>SUM(U8:U135)),"In Progress","Section Review Complete"))) | J2: Unsure | K2: Yes, section requirements are not applicable | Z2: =IF('Cover Sheet'!$B$13="Yes","MCO","--") | AA2: =IF('Cover Sheet'!$B$14="Yes","HIO","--") | AB2: =IF('Cover Sheet'!$B$15="Yes","PIHP","--") | AC2: =IF('Cover Sheet'!$B$16="Yes","PAHP","--") | AD2: =IF('Cover Sheet'!$B$17="Yes","NEMT PAHP","--") | AE2: =IF('Cover Sheet'!$B$18="Yes","PCCME","--") | AG2: =IF('Cover Sheet'!$B$4="BOTH",1,0) | AM2: N/A
A3: Mark all requirements as "N/A"? | C3: No, section requirements must be reviewed | G3: Medicaid Decision: | H3: =I3 | I3: =IF(OR($C$3="Yes, section requirements are not applicable",$C$3="Yes, all requirements on the sheet are crosshatched",AND(E8="N/A",E25="N/A",E66="N/A",E68="N/A",E74="N/A",E78="N/A",E81="N/A",E89="N/A",E134="N/A")),"Section Review N/A",IF((COUNTA(A8:A135)+COUNTBLANK(A8:A135))=COUNTBLANK(E8:E135),"Not Started",IF(OR(COUNTA(A9:A135)+COUNTBLANK(A8:A135)<>COUNTIF(E8:E135,"Yes")+COUNTIF(E8:E135,"Met")+COUNTIF(E8:E135,"N/A")+COUNTBLANK(E8:E135),COUNTA(A8:A135)<>SUM(U8:U135)),"Revisions Needed","Approved"))) | J3: Not met | K3: No, section requirements must be reviewed | X3: Shaded | Y3: Entity Not Applied
J4: N/A
R5: _EFFECTIVE | AM5: Medicaid_Only
I6: Applies to: | J6: N/A | P6: Std type (EXISTING or NEW) | Q6: List | X6: Shaded | Y6: Entity Not Applied
A7: Item | B7: Legal Cite | C7: Requirement | D7: Tip | E7: Status | F7: Where Found | G7: Follow-up Required | H7: General Comments | I7: MCO | J7: HIO | K7: PIHP | L7: PAHP | M7: NEMT PAHP | N7: PCCM | O7: PCCME | R7: Effective | U7: Row Completed? (1 if status = Unsure; status = Met and column G <>blank; or status = Not Met and column I<>not blank) | V7: If CHIP linking and no information in rows with gray shading in columns E through H; code as complete. If rows with gray shading have information in one or more cells, the status of the row will be counted as if gray shading did not appear. (See Column Descriptions for more information) | W7: (b4c) Section I vs II | Z7: MCO | AA7: HIO | AB7: PIHP | AC7: PAHP | AD7: NEMT PAHP | AE7: PCCME | AF7: CHIP Requirement | AG7: Does the CHIP section have a corresponding Medicaid section (Yes=1) | AH7: If yes, link the Medicaid section item: | AI7: If yes, link the Medicaid Requirement: | AJ7: Is the text the exact same? | AK7: Shading code | AL7: section1_no_link | AM7: Medicaid_Only | AN7: Linked Medicaid Requirement Status | AO7: Linked Medicaid Requirement Where Found | AP7: Linked Medicaid Requirement Followup Required | AQ7: Linked Medicaid General Comments | AR7: Row Started (1 if row has been started) | AS7: Requirement Met | AT7: All Required Medicaid Cols Filled (1=True) | AU7: Streamlined
C8: I.C.1 Language and Format
A9: I.C.1.01 | B9: 42 CFR 438.10(c)(1) | C9: The contract requires the MCP to provide all required information to enrollees and potential enrollees in a manner and format that may be easily understood and is readily accessible by such enrollees and potential enrollees. | F9: Source: Attachment - Core Contract Provisions 02012025: 58, 121 | CN-680000-FP122: 58, 113, 121, 122 | H9: Recommendation: MET Response: The contract explicitly states that the Managed Care Plan (MCP) shall provide all enrollee communications, including written materials, spoken scripts, and websites, in an easily understood language and format. Specifically, it mentions that enrollee communications shall be at or near the fourth (4th) grade comprehension level and lists several readability tests to ensure compliance ([1], [2]). Additionally, the MCP is required to make all written material available in multiple languages as prescribed by the Agency and to notify enrollees and potential enrollees about the availability of information in alternative formats and how to access them ([1], [2], [3], [4]). This indicates that the requirement is met. | I9: MCO | J9: HIO | K9: PIHP | L9: PAHP | M9: NEMT PAHP | O9: PCCME | P9: EXISTING | U9: =IF(OR($E$8="N/A",AND(AU9=0,'Cover Sheet'!$B$29="Streamlined Review"),AND(E9="Met",F9<>""),AND(E9="Not met",G9<>""),AND(E9="Unsure",G9<>""),AND(E9="N/A",H9<>""),AND(Y9=TRUE)),1,0) | W9: =IF(OR(AND($H$6="Medicaid",MID($A9,1,FIND(".",$A9,1)-1)="II"),AND($H$6="CHIP",MID($A9,1,FIND(".",$A9,1)-1)="I")),TRUE,FALSE) | X9: =IF(OR(Y9=TRUE),TRUE,FALSE) | Y9: =IF(SUM(Z9:AE9)<1,TRUE,FALSE) | Z9: =IF($Z$2=I9,1,0) | AA9: =IF($AA$2=J9,1,0) | AB9: =IF($AB$2=K9,1,0) | AC9: =IF($AC$2=L9,1,0) | AD9: =IF($AD$2=M9,1,0) | AE9: =IF($AE$2=O9,1,0) | AM9: =IF(AL9=1,1,"") | AU9: 0
A10: I.C.1.02 | B10: 42 CFR 438.10(c)(7) | C10: The contract requires the MCP to have in place mechanisms to help enrollees and potential enrollees understand the requirements and benefits of their plan. | F10: Source: CN-680000-FP122: 134 | Attachment - Core Contract Provisions 02012025: 70 | H10: Recommendation: MET Response: The contract explicitly states that the Managed Care Plan (MCP) shall develop educational materials for enrollees and providers that educate them about how benefits will be administered and provide information about any administrative requirements. This indicates that the MCP is required to have mechanisms in place to help enrollees understand the requirements and benefits of their plan. Evidence: - "The Managed Care Plan shall develop educational materials for enrollees and providers that educate them about how these benefits will be administered and provide information about any administrative requirements (e.g., copayment or prior authorization requirements)." [CN-680000-FP122: 134, Attachment - Core Contract Provisions 02012025: 70] | I10: MCO | J10: HIO | K10: PIHP | L10: PAHP | M10: NEMT PAHP | O10: PCCME | P10: EXISTING | U10: =IF(OR($E$8="N/A",AND(AU10=0,'Cover Sheet'!$B$29="Streamlined Review"),AND(E10="Met",F10<>""),AND(E10="Not met",G10<>""),AND(E10="Unsure",G10<>""),AND(E10="N/A",H10<>""),AND(Y10=TRUE)),1,0) | W10: =IF(OR(AND($H$6="Medicaid",MID($A10,1,FIND(".",$A10,1)-1)="II"),AND($H$6="CHIP",MID($A10,1,FIND(".",$A10,1)-1)="I")),TRUE,FALSE) | X10: =IF(OR(Y10=TRUE),TRUE,FALSE) | Y10: =IF(SUM(Z10:AE10)<1,TRUE,FALSE) | Z10: =IF($Z$2=I10,1,0) | AA10: =IF($AA$2=J10,1,0) | AB10: =IF($AB$2=K10,1,0) | AC10: =IF($AC$2=L10,1,0) | AD10: =IF($AD$2=M10,1,0) | AE10: =IF($AE$2=O10,1,0) | AM10: =IF(AL10=1,1,"") | AU10: 0
A11: I.C.1.03 | B11: 42 CFR 438.10(d)(3) | C11: The contract requires the MCP to make its written materials that are critical to obtaining services, including, at a minimum, provider directories, enrollee handbooks, appeal and grievance notices, and denial and termination notices, available in the prevalent non-English languages in its particular service area. | F11: Source: CN-680000-FP122: 128: 128 | H11: Recommendation: MET Response: The contract explicitly requires the Managed Care Plan (MCP) to ensure language translation quality in all enrollee materials and to provide interpretation services at all points of contact to any potential enrollee or enrollee who speaks any non-English language. This includes written translation, oral interpretation, and the use of auxiliary aids such as TTY/TDY and American Sign Language. Evidence: - "The Managed Care Plan shall ensure language translation quality in all enrollee materials." [CN-680000-FP122: 128] - "The Managed Care Plan is required to provide interpretation services at all points of contact to any potential enrollee or enrollee who speaks any non-English language regardless of whether the enrollee speaks a language that meets the threshold of a prevalent non-English language. This includes written translation, oral interpretation, and the use of auxiliary aids such as TTY/TDY and American Sign Language (42 CFR 438.10(d)(4); and 42 CFR 438.406(a))." [CN-680000-FP122: 128] | I11: MCO | J11: HIO | K11: PIHP | L11: PAHP | M11: NEMT PAHP | O11: PCCME | P11: EXISTING | R11: 42917 | U11: =IF(OR($E$8="N/A",AND(AU11=0,'Cover Sheet'!$B$29="Streamlined Review"),AND(E11="Met",F11<>""),AND(E11="Not met",G11<>""),AND(E11="Unsure",G11<>""),AND(E11="N/A",H11<>""),AND(Y11=TRUE)),1,0) | W11: =IF(OR(AND($H$6="Medicaid",MID($A11,1,FIND(".",$A11,1)-1)="II"),AND($H$6="CHIP",MID($A11,1,FIND(".",$A11,1)-1)="I")),TRUE,FALSE) | X11: =IF(OR(Y11=TRUE),TRUE,FALSE) | Y11: =IF(SUM(Z11:AE11)<1,TRUE,FALSE) | Z11: =IF($Z$2=I11,1,0) | AA11: =IF($AA$2=J11,1,0) | AB11: =IF($AB$2=K11,1,0) | AC11: =IF($AC$2=L11,1,0) | AD11: =IF($AD$2=M11,1,0) | AE11: =IF($AE$2=O11,1,0) | AM11: =IF(AL11=1,1,"") | AU11: 0
A12: I.C.1.04 | B12: 42 CFR 438.10(d)(3) | C12: The contract requires that the MCP’s written materials that are critical to obtaining services are available in alternative formats upon request of the potential enrollee or enrollee at no cost. | F12: Source: CN-680000-FP122: 113, 122 | Attachment - Core Contract Provisions 02012025: 58 | H12: Recommendation: MET Response: The contract explicitly states that the Managed Care Plan shall notify enrollees or potential enrollees that information is available in alternative formats and how to access those formats upon request. This indicates that the requirement is met. Evidence: - "Upon request, the Managed Care Plan shall notify enrollees or potential enrollees that information is available in alternative formats and how to access those formats (42 CFR 438.10(d)(3))." [CN-680000-FP122: 113] - "The Managed Care Plan shall notify all enrollees and, upon request, potential enrollees that information is available in alternative formats and how to access those formats (42 CFR 438.10(d)(3))." [CN-680000-FP122: 122 | Attachment - Core Contract Provisions 02012025: 58] | I12: MCO | J12: HIO | K12: PIHP | L12: PAHP | M12: NEMT PAHP | O12: PCCME | P12: EXISTING | R12: 44179 | U12: =IF(OR($E$8="N/A",AND(AU12=0,'Cover Sheet'!$B$29="Streamlined Review"),AND(E12="Met",F12<>""),AND(E12="Not met",G12<>""),AND(E12="Unsure",G12<>""),AND(E12="N/A",H12<>""),AND(Y12=TRUE)),1,0) | W12: =IF(OR(AND($H$6="Medicaid",MID($A12,1,FIND(".",$A12,1)-1)="II"),AND($H$6="CHIP",MID($A12,1,FIND(".",$A12,1)-1)="I")),TRUE,FALSE) | X12: =IF(OR(Y12=TRUE),TRUE,FALSE) | Y12: =IF(SUM(Z12:AE12)<1,TRUE,FALSE) | Z12: =IF($Z$2=I12,1,0) | AA12: =IF($AA$2=J12,1,0) | AB12: =IF($AB$2=K12,1,0) | AC12: =IF($AC$2=L12,1,0) | AD12: =IF($AD$2=M12,1,0) | AE12: =IF($AE$2=O12,1,0) | AM12: =IF(AL12=1,1,"") | AU12: 0
A13: I.C.1.05 | B13: 42 CFR 438.10(d)(3) | C13: The contract requires that the MCP’s written materials that are critical to obtaining services include taglines in the prevalent non-English languages in the state and are in a conspicuously visible font size explaining the availability of written translation or oral interpretation to understand the information provided. | F13: Source: CN-680000-FP122: 122 | Attachment - Core Contract Provisions 02012025: 58 | H13: Recommendation: MET Response: The contract explicitly states that the Managed Care Plan shall include taglines in the prevalent non-English languages in the State, as well as large print, explaining the availability of written translation or oral interpretation to understand the information provided. This is supported by the following quotes: - "The Managed Care Plan shall include taglines in the prevalent non-English languages in the State, as well as large print, explaining the availability of written translation or oral interpretation to understand the information provided." [CN-680000-FP122: 122] - "The Managed Care Plan shall include taglines in the prevalent non-English languages in the State, as well as large print, explaining the availability of written translation or oral interpretation to understand the information provided." [Attachment - Core Contract Provisions 02012025: 58] | I13: MCO | J13: HIO | K13: PIHP | L13: PAHP | M13: NEMT PAHP | O13: PCCME | P13: EXISTING | R13: 44179 | U13: =IF(OR($E$8="N/A",AND(AU13=0,'Cover Sheet'!$B$29="Streamlined Review"),AND(E13="Met",F13<>""),AND(E13="Not met",G13<>""),AND(E13="Unsure",G13<>""),AND(E13="N/A",H13<>""),AND(Y13=TRUE)),1,0) | W13: =IF(OR(AND($H$6="Medicaid",MID($A13,1,FIND(".",$A13,1)-1)="II"),AND($H$6="CHIP",MID($A13,1,FIND(".",$A13,1)-1)="I")),TRUE,FALSE) | X13: =IF(OR(Y13=TRUE),TRUE,FALSE) | Y13: =IF(SUM(Z13:AE13)<1,TRUE,FALSE) | Z13: =IF($Z$2=I13,1,0) | AA13: =IF($AA$2=J13,1,0) | AB13: =IF($AB$2=K13,1,0) | AC13: =IF($AC$2=L13,1,0) | AD13: =IF($AD$2=M13,1,0) | AE13: =IF($AE$2=O13,1,0) | AM13: =IF(AL13=1,1,"") | AU13: 0
A14: I.C.1.06 | B14: 42 CFR 438.10(d)(3) | C14: The contract requires that the MCP’s written materials that are critical to obtaining services include taglines in the prevalent non-English languages in the state and are in a conspicuously visible font size that provide information on how to request auxiliary aids and services. | F14: Source: CN-680000-FP122: 122 | H14: Recommendation: MET Response: The contract explicitly states that the Managed Care Plan shall include taglines in the prevalent non-English languages in the State, as well as large print, explaining the availability of written translation and interpretation services [1]. This indicates that the requirement for taglines in prevalent non-English languages and conspicuously visible font size is met. [1] "e. The Managed Care Plan shall include taglines in the prevalent non-English languages in the State, as well as large print, explaining the availability of written translation and interpretation services." (CN-680000-FP122: 122) | I14: MCO | J14: HIO | K14: PIHP | L14: PAHP | M14: NEMT PAHP | O14: PCCME | P14: EXISTING | R14: 44179 | U14: =IF(OR($E$8="N/A",AND(AU14=0,'Cover Sheet'!$B$29="Streamlined Review"),AND(E14="Met",F14<>""),AND(E14="Not met",G14<>""),AND(E14="Unsure",G14<>""),AND(E14="N/A",H14<>""),AND(Y14=TRUE)),1,0) | W14: =IF(OR(AND($H$6="Medicaid",MID($A14,1,FIND(".",$A14,1)-1)="II"),AND($H$6="CHIP",MID($A14,1,FIND(".",$A14,1)-1)="I")),TRUE,FALSE) | X14: =IF(OR(Y14=TRUE),TRUE,FALSE) | Y14: =IF(SUM(Z14:AE14)<1,TRUE,FALSE) | Z14: =IF($Z$2=I14,1,0) | AA14: =IF($AA$2=J14,1,0) | AB14: =IF($AB$2=K14,1,0) | AC14: =IF($AC$2=L14,1,0) | AD14: =IF($AD$2=M14,1,0) | AE14: =IF($AE$2=O14,1,0) | AM14: =IF(AL14=1,1,"") | AU14: 0
A15: I.C.1.07 | B15: 42 CFR 438.10(d)(3) | C15: The contract requires that the MCP’s written materials that are critical to obtaining services include taglines in the prevalent non-English languages in the state and are in a conspicuously visible font size that provide the toll-free and Teletypewriter Telephone/Text Telephone (TTY/TDY) telephone number of the MCP's member/customer service unit. | F15: Source: Attachment - Core Contract Provisions 02012025: 58 | CN-680000-FP122: 112 | H15: Recommendation: MET Response: The contract explicitly requires the Managed Care Plan (MCP) to include taglines in prevalent non-English languages and provide the toll-free and TTY/TDY telephone number in a conspicuously visible font size. Specifically, it states: - "The Managed Care Plan shall include taglines in the prevalent non-English languages in the State, as well as large print, explaining the availability of written translation services." [Attachment - Core Contract Provisions 02012025: 58] - "The Managed Care Plan shall include a Teletypewriter Telephone (TTY) number in conjunction with the Managed Care Plan's toll-free customer service number." [CN-680000-FP122: 112] These excerpts confirm that the requirement is met. | I15: MCO | J15: HIO | K15: PIHP | L15: PAHP | M15: NEMT PAHP | O15: PCCME | P15: EXISTING | R15: 44179 | U15: =IF(OR($E$8="N/A",AND(AU15=0,'Cover Sheet'!$B$29="Streamlined Review"),AND(E15="Met",F15<>""),AND(E15="Not met",G15<>""),AND(E15="Unsure",G15<>""),AND(E15="N/A",H15<>""),AND(Y15=TRUE)),1,0) | W15: =IF(OR(AND($H$6="Medicaid",MID($A15,1,FIND(".",$A15,1)-1)="II"),AND($H$6="CHIP",MID($A15,1,FIND(".",$A15,1)-1)="I")),TRUE,FALSE) | X15: =IF(OR(Y15=TRUE),TRUE,FALSE) | Y15: =IF(SUM(Z15:AE15)<1,TRUE,FALSE) | Z15: =IF($Z$2=I15,1,0) | AA15: =IF($AA$2=J15,1,0) | AB15: =IF($AB$2=K15,1,0) | AC15: =IF($AC$2=L15,1,0) | AD15: =IF($AD$2=M15,1,0) | AE15: =IF($AE$2=O15,1,0) | AM15: =IF(AL15=1,1,"") | AU15: 0
A16: I.C.1.08 | B16: 42 CFR 438.10(d)(3) | C16: The contract requires the MCP to make auxiliary aids and services available upon request of the potential enrollee or enrollee at no cost. | F16: Source: CN-680000-FP122: 121, 64 | Attachment - Core Contract Provisions 02012025: 57, 64 | H16: Recommendation: MET Response: The contract explicitly states that the Managed Care Plan (MCP) is required to provide auxiliary aids and services to enrollees to achieve effective communication, and these services are to be provided at no cost. Specifically, the text states: 'The Managed Care Plan shall provide language assistance services, including the provision of foreign language interpreter and translation services, and auxiliary aids and services to enrollees to achieve effective communication (42 CFR 438.10(d)(3))' [CN-680000-FP122: 121, Attachment - Core Contract Provisions 02012025: 57]. Additionally, it is mentioned that 'There shall be no charge to the enrollee for translation services' [Attachment - Core Contract Provisions 02012025: 64]. | I16: MCO | J16: HIO | K16: PIHP | L16: PAHP | M16: NEMT PAHP | O16: PCCME | P16: EXISTING | R16: 42917 | U16: =IF(OR($E$8="N/A",AND(AU16=0,'Cover Sheet'!$B$29="Streamlined Review"),AND(E16="Met",F16<>""),AND(E16="Not met",G16<>""),AND(E16="Unsure",G16<>""),AND(E16="N/A",H16<>""),AND(Y16=TRUE)),1,0) | W16: =IF(OR(AND($H$6="Medicaid",MID($A16,1,FIND(".",$A16,1)-1)="II"),AND($H$6="CHIP",MID($A16,1,FIND(".",$A16,1)-1)="I")),TRUE,FALSE) | X16: =IF(OR(Y16=TRUE),TRUE,FALSE) | Y16: =IF(SUM(Z16:AE16)<1,TRUE,FALSE) | Z16: =IF($Z$2=I16,1,0) | AA16: =IF($AA$2=J16,1,0) | AB16: =IF($AB$2=K16,1,0) | AC16: =IF($AC$2=L16,1,0) | AD16: =IF($AD$2=M16,1,0) | AE16: =IF($AE$2=O16,1,0) | AM16: =IF(AL16=1,1,"") | AU16: 0
A17: I.C.1.09 | B17: 42 CFR 438.10(d)(4) | C17: The contract requires the MCP to make interpretation services, including oral interpretation and the use of auxiliary aids such as TTY/TDY and American Sign Language (ASL), free of charge to each enrollee. | F17: Source: Attachment - Core Contract Provisions 02012025: 64 | CN-680000-FP122: 128 | H17: Recommendation: MET Response: The contract explicitly states that the Managed Care Plan (MCP) is required to provide interpretation services, including oral interpretation and auxiliary aids such as TTY/TDY and American Sign Language (ASL), free of charge to enrollees. The relevant text states: 'There shall be no charge to the enrollee for translation services (42 CFR 438.10(d)(5)(i)-(iii), 42 CFR 438.10(d)(4)). Upon request, the Managed Care Plan shall provide, free of charge, interpreters for potential enrollees or enrollees whose primary language is not English (42 CFR 438.10(d)(4)).' [1] [2] | I17: MCO | J17: HIO | K17: PIHP | L17: PAHP | M17: NEMT PAHP | O17: PCCME | P17: EXISTING | R17: 42917 | U17: =IF(OR($E$8="N/A",AND(AU17=0,'Cover Sheet'!$B$29="Streamlined Review"),AND(E17="Met",F17<>""),AND(E17="Not met",G17<>""),AND(E17="Unsure",G17<>""),AND(E17="N/A",H17<>""),AND(Y17=TRUE)),1,0) | W17: =IF(OR(AND($H$6="Medicaid",MID($A17,1,FIND(".",$A17,1)-1)="II"),AND($H$6="CHIP",MID($A17,1,FIND(".",$A17,1)-1)="I")),TRUE,FALSE) | X17: =IF(OR(Y17=TRUE),TRUE,FALSE) | Y17: =IF(SUM(Z17:AE17)<1,TRUE,FALSE) | Z17: =IF($Z$2=I17,1,0) | AA17: =IF($AA$2=J17,1,0) | AB17: =IF($AB$2=K17,1,0) | AC17: =IF($AC$2=L17,1,0) | AD17: =IF($AD$2=M17,1,0) | AE17: =IF($AE$2=O17,1,0) | AM17: =IF(AL17=1,1,"") | AU17: 0
A18: I.C.1.10 | B18: 42 CFR 438.10(d)(5)(i) and (iii) | C18: The contract requires the MCP to notify its enrollees that oral interpretation is available for any language, and how to access those services. | F18: Source: Attachment - Core Contract Provisions 02012025: 64 | CN-680000-FP122: 128 | H18: Recommendation: MET Response: The contract explicitly states that the Managed Care Plan (MCP) is required to notify its enrollees of the availability of interpretation services and to inform them of how to access such services. This is evidenced by the following quotes: - "The Managed Care Plan is required to notify its enrollees of the availability of interpretation services and to inform them of how to access such services." [Attachment - Core Contract Provisions 02012025: 64] - "The Managed Care Plan is required to notify its enrollees of the availability of interpretation services and to inform them of how to access such services." [CN-680000-FP122: 128] | I18: MCO | J18: HIO | K18: PIHP | L18: PAHP | M18: NEMT PAHP | O18: PCCME | P18: EXISTING | U18: =IF(OR($E$8="N/A",AND(AU18=0,'Cover Sheet'!$B$29="Streamlined Review"),AND(E18="Met",F18<>""),AND(E18="Not met",G18<>""),AND(E18="Unsure",G18<>""),AND(E18="N/A",H18<>""),AND(Y18=TRUE)),1,0) | W18: =IF(OR(AND($H$6="Medicaid",MID($A18,1,FIND(".",$A18,1)-1)="II"),AND($H$6="CHIP",MID($A18,1,FIND(".",$A18,1)-1)="I")),TRUE,FALSE) | X18: =IF(OR(Y18=TRUE),TRUE,FALSE) | Y18: =IF(SUM(Z18:AE18)<1,TRUE,FALSE) | Z18: =IF($Z$2=I18,1,0) | AA18: =IF($AA$2=J18,1,0) | AB18: =IF($AB$2=K18,1,0) | AC18: =IF($AC$2=L18,1,0) | AD18: =IF($AD$2=M18,1,0) | AE18: =IF($AE$2=O18,1,0) | AM18: =IF(AL18=1,1,"") | AU18: 0
A19: I.C.1.11 | B19: 42 CFR 438.10(d)(5)(i) and (iii) | C19: The contract requires the MCP to notify its enrollees that written translation is available in prevalent languages, and how to access those services. | F19: Source: CN-680000-FP122: 128 | H19: Recommendation: MET Response: The contract explicitly states that the Managed Care Plan (MCP) is required to notify its enrollees of the availability of interpretation services and to inform them of how to access such services. This includes written translation. The relevant text is: "The Managed Care Plan is required to notify its enrollees of the availability of interpretation services and to inform them of how to access such services. Interpretation services are required for all Managed Care Plan information provided to enrollees, including notices of adverse action. There shall be no charge to the enrollee for translation services (42 CFR 438.10(d)(5)(i)-(iii), 42 CFR 438.10(d)(4)). Upon request, the Managed Care Plan shall provide, free of charge, interpreters for potential enrollees or enrollees whose primary language is not English (42 CFR 438.10(d)(4))." [CN-680000-FP122: 128] | I19: MCO | J19: HIO | K19: PIHP | L19: PAHP | M19: NEMT PAHP | O19: PCCME | P19: EXISTING | U19: =IF(OR($E$8="N/A",AND(AU19=0,'Cover Sheet'!$B$29="Streamlined Review"),AND(E19="Met",F19<>""),AND(E19="Not met",G19<>""),AND(E19="Unsure",G19<>""),AND(E19="N/A",H19<>""),AND(Y19=TRUE)),1,0) | W19: =IF(OR(AND($H$6="Medicaid",MID($A19,1,FIND(".",$A19,1)-1)="II"),AND($H$6="CHIP",MID($A19,1,FIND(".",$A19,1)-1)="I")),TRUE,FALSE) | X19: =IF(OR(Y19=TRUE),TRUE,FALSE) | Y19: =IF(SUM(Z19:AE19)<1,TRUE,FALSE) | Z19: =IF($Z$2=I19,1,0) | AA19: =IF($AA$2=J19,1,0) | AB19: =IF($AB$2=K19,1,0) | AC19: =IF($AC$2=L19,1,0) | AD19: =IF($AD$2=M19,1,0) | AE19: =IF($AE$2=O19,1,0) | AM19: =IF(AL19=1,1,"") | AU19: 0
A20: I.C.1.12 | B20: 42 CFR 438.10(d)(5)(ii)–(iii) | C20: The contract requires the MCP to notify its enrollees that auxiliary aids and services are available upon request at no cost for enrollees with disabilities, and how to access those services. | F20: Source: Attachment - Core Contract Provisions 02012025: 64 | CN-680000-FP122: 64 | H20: Recommendation: MET Response: The contract explicitly requires the Managed Care Plan (MCP) to notify its enrollees of the availability of interpretation services and to inform them of how to access such services. It also specifies that there shall be no charge to the enrollee for these services. This includes the provision of interpreters for potential enrollees or enrollees whose primary language is not English, as well as the use of auxiliary aids such as TTY/TDD and American Sign Language. Evidence: - "The Managed Care Plan is required to notify its enrollees of the availability of interpretation services and to inform them of how to access such services. Interpretation services are required for all Managed Care Plan information provided to enrollees, including notices of adverse action. There shall be no charge to the enrollee for translation services (42 CFR 438.10(d)(5)(i)-(iii), 42 CFR 438.10(d)(4)). Upon request, the Managed Care Plan shall provide, free of charge, interpreters for potential enrollees or enrollees whose primary language is not English (42 CFR 438.10(d)(4))." [Attachment - Core Contract Provisions 02012025: 64] - "The Managed Care Plan is required to provide interpretation services at all points of contact to any potential enrollee or enrollee who speaks any non-English language regardless of whether the enrollee speaks a language that meets the threshold of a prevalent non-English language. This includes written translation, oral interpretation, and the use of auxiliary aids such as TTY/TDY and American Sign Language (42 CFR 438.10(d)(4); and 42 CFR 438.406(a))." [CN-680000-FP122: 64] | I20: MCO | J20: HIO | K20: PIHP | L20: PAHP | M20: NEMT PAHP | O20: PCCME | P20: EXISTING | U20: =IF(OR($E$8="N/A",AND(AU20=0,'Cover Sheet'!$B$29="Streamlined Review"),AND(E20="Met",F20<>""),AND(E20="Not met",G20<>""),AND(E20="Unsure",G20<>""),AND(E20="N/A",H20<>""),AND(Y20=TRUE)),1,0) | W20: =IF(OR(AND($H$6="Medicaid",MID($A20,1,FIND(".",$A20,1)-1)="II"),AND($H$6="CHIP",MID($A20,1,FIND(".",$A20,1)-1)="I")),TRUE,FALSE) | X20: =IF(OR(Y20=TRUE),TRUE,FALSE) | Y20: =IF(SUM(Z20:AE20)<1,TRUE,FALSE) | Z20: =IF($Z$2=I20,1,0) | AA20: =IF($AA$2=J20,1,0) | AB20: =IF($AB$2=K20,1,0) | AC20: =IF($AC$2=L20,1,0) | AD20: =IF($AD$2=M20,1,0) | AE20: =IF($AE$2=O20,1,0) | AM20: =IF(AL20=1,1,"") | AU20: 0
A21: I.C.1.13 | B21: 42 CFR 438.10(d)(6)(i) | C21: The contract requires the MCP to provide all written materials for potential enrollees and enrollees in an easily understood language and format. | F21: Source: Attachment - Core Contract Provisions 02012025: 58, 122 | CN-680000-FP122: 58, 122 | H21: Recommendation: MET Response: The contract explicitly states that the Managed Care Plan (MCP) shall provide all enrollee communications, including written materials, in an easily understood language and format. Specifically, it mentions that enrollee communications shall be at or near the fourth (4th) grade comprehension level and lists several readability tests to determine compliance with this requirement. Additionally, the MCP is required to make all written material available in multiple languages and notify enrollees and potential enrollees about the availability of information in alternative formats. Evidence: - "The Managed Care Plan shall provide all enrollee communications, including written materials, spoken scripts, and websites in an easily understood language and format." [Attachment - Core Contract Provisions 02012025: 58, 122] - "The Managed Care Plan shall make all written material available in multiple languages, as prescribed by the Agency. The Managed Care Plan shall notify all enrollees and, upon request, potential enrollees that information is available in alternative formats and how to access those formats (42 CFR 438.10(d)(3))." [Attachment - Core Contract Provisions 02012025: 58, 122] | I21: MCO | J21: HIO | K21: PIHP | L21: PAHP | M21: NEMT PAHP | O21: PCCME | P21: EXISTING | U21: =IF(OR($E$8="N/A",AND(AU21=0,'Cover Sheet'!$B$29="Streamlined Review"),AND(E21="Met",F21<>""),AND(E21="Not met",G21<>""),AND(E21="Unsure",G21<>""),AND(E21="N/A",H21<>""),AND(Y21=TRUE)),1,0) | W21: =IF(OR(AND($H$6="Medicaid",MID($A21,1,FIND(".",$A21,1)-1)="II"),AND($H$6="CHIP",MID($A21,1,FIND(".",$A21,1)-1)="I")),TRUE,FALSE) | X21: =IF(OR(Y21=TRUE),TRUE,FALSE) | Y21: =IF(SUM(Z21:AE21)<1,TRUE,FALSE) | Z21: =IF($Z$2=I21,1,0) | AA21: =IF($AA$2=J21,1,0) | AB21: =IF($AB$2=K21,1,0) | AC21: =IF($AC$2=L21,1,0) | AD21: =IF($AD$2=M21,1,0) | AE21: =IF($AE$2=O21,1,0) | AM21: =IF(AL21=1,1,"") | AU21: 0
A22: I.C.1.14 | B22: 42 CFR 438.10(d)(6)(ii) | C22: The contract requires the MCP to provide all written materials for potential enrollees and enrollees in a font size no smaller than 12 point. | F22: Source: CN-680000-FP122: 121, 57, 58, 122 | Attachment - Core Contract Provisions 02012025: 57, 58, 54 | H22: Recommendation: UNCLEAR Response: The retrieved text does not provide explicit evidence regarding the font size requirement for written materials. While there are provisions about the submission, review, and readability of written materials, there is no specific mention of a minimum font size of 12 point. | I22: MCO | J22: HIO | K22: PIHP | L22: PAHP | M22: NEMT PAHP | O22: PCCME | P22: EXISTING | R22: 42917 | U22: =IF(OR($E$8="N/A",AND(AU22=0,'Cover Sheet'!$B$29="Streamlined Review"),AND(E22="Met",F22<>""),AND(E22="Not met",G22<>""),AND(E22="Unsure",G22<>""),AND(E22="N/A",H22<>""),AND(Y22=TRUE)),1,0) | W22: =IF(OR(AND($H$6="Medicaid",MID($A22,1,FIND(".",$A22,1)-1)="II"),AND($H$6="CHIP",MID($A22,1,FIND(".",$A22,1)-1)="I")),TRUE,FALSE) | X22: =IF(OR(Y22=TRUE),TRUE,FALSE) | Y22: =IF(SUM(Z22:AE22)<1,TRUE,FALSE) | Z22: =IF($Z$2=I22,1,0) | AA22: =IF($AA$2=J22,1,0) | AB22: =IF($AB$2=K22,1,0) | AC22: =IF($AC$2=L22,1,0) | AD22: =IF($AD$2=M22,1,0) | AE22: =IF($AE$2=O22,1,0) | AM22: =IF(AL22=1,1,"") | AU22: 0
A23: I.C.1.15 | B23: 42 CFR 438.10(d)(6)(iii) | C23: The contract requires the MCP to make written materials for potential enrollees and enrollees available in alternative formats in an appropriate manner that takes into consideration the special needs of enrollees or potential enrollees with disabilities or limited English proficiency. | F23: Source: CN-680000-FP122: 113, 122 | Attachment - Core Contract Provisions 02012025: 137 | H23: Recommendation: MET Response: The contract explicitly states that the Managed Care Plan shall notify enrollees or potential enrollees that information is available in alternative formats and how to access those formats (42 CFR 438.10(d)(3)). Additionally, the contract requires the Managed Care Plan to provide all enrollee communications in an easily understood language and format, and to make written material available in multiple languages as prescribed by the Agency. The contract also mandates that the Managed Care Plan's non-discrimination compliance plan shall include written procedures that demonstrate non-discrimination in the provision of language assistance services for members with limited English proficiency and those requiring communication assistance in alternative formats. Evidence: - 'languages, as prescribed by the Agency. Upon request, the Managed Care Plan shall notify enrollees or potential enrollees that information is available in alternative formats and how to access those formats (42 CFR 438.10(d)(3)).' [CN-680000-FP122: 113] - 'The Managed Care Plan shall make all written material available in multiple languages, as prescribed by the Agency. The Managed Care Plan shall notify all enrollees and, upon request, potential enrollees that information is available in alternative formats and how to access those formats (42 CFR 438.10(d)(3)).' [CN-680000-FP122: 122] - 'The policy shall also demonstrate non-discrimination in the provision of language assistance services for members with limited English proficiency and those requiring communication assistance in alternative formats.' [Attachment - Core Contract Provisions 02012025: 137] | I23: MCO | J23: HIO | K23: PIHP | L23: PAHP | M23: NEMT PAHP | O23: PCCME | P23: EXISTING | R23: 42917 | U23: =IF(OR($E$8="N/A",AND(AU23=0,'Cover Sheet'!$B$29="Streamlined Review"),AND(E23="Met",F23<>""),AND(E23="Not met",G23<>""),AND(E23="Unsure",G23<>""),AND(E23="N/A",H23<>""),AND(Y23=TRUE)),1,0) | W23: =IF(OR(AND($H$6="Medicaid",MID($A23,1,FIND(".",$A23,1)-1)="II"),AND($H$6="CHIP",MID($A23,1,FIND(".",$A23,1)-1)="I")),TRUE,FALSE) | X23: =IF(OR(Y23=TRUE),TRUE,FALSE) | Y23: =IF(SUM(Z23:AE23)<1,TRUE,FALSE) | Z23: =IF($Z$2=I23,1,0) | AA23: =IF($AA$2=J23,1,0) | AB23: =IF($AB$2=K23,1,0) | AC23: =IF($AC$2=L23,1,0) | AD23: =IF($AD$2=M23,1,0) | AE23: =IF($AE$2=O23,1,0) | AM23: =IF(AL23=1,1,"") | AU23: 0
A24: I.C.1.16 | B24: 42 CFR 438.10(d)(6)(iii) | C24: The contract requires the MCP to make written materials for potential enrollees and enrollees available through auxiliary aids and services in an appropriate manner that takes into consideration the special needs of enrollees or potential enrollees with disabilities or limited English proficiency. | F24: Source: Attachment - Core Contract Provisions 02012025: 64, 122 | CN-680000-FP122: 128, 58 | H24: Recommendation: MET Response: The contract explicitly states that the Managed Care Plan is required to provide interpretation services at all points of contact to any potential enrollee or enrollee who speaks any non-English language. This includes written translation, oral interpretation, and the use of auxiliary aids such as TTY/TDY and American Sign Language (42 CFR 438.10(d)(4); and 42 CFR 438.406(a)). Additionally, the contract requires the Managed Care Plan to make all written material available in multiple languages and to notify enrollees and potential enrollees that information is available in alternative formats and how to access those formats (42 CFR 438.10(d)(3)). This indicates that the contract supports the requirement to make written materials available through auxiliary aids and services for enrollees or potential enrollees with disabilities or limited English proficiency. Evidence: - "The Managed Care Plan is required to provide interpretation services at all points of contact to any potential enrollee or enrollee who speaks any non-English language... This includes written translation, oral interpretation, and the use of auxiliary aids such as TTY/TDY and American Sign Language (42 CFR 438.10(d)(4); and 42 CFR 438.406(a))." [1] - "The Managed Care Plan shall make all written material available in multiple languages... The Managed Care Plan shall notify all enrollees and, upon request, potential enrollees that information is available in alternative formats and how to access those formats (42 CFR 438.10(d)(3))." [2] | I24: MCO | J24: HIO | K24: PIHP | L24: PAHP | M24: NEMT PAHP | O24: PCCME | P24: EXISTING | R24: 42917 | U24: =IF(OR($E$8="N/A",AND(AU24=0,'Cover Sheet'!$B$29="Streamlined Review"),AND(E24="Met",F24<>""),AND(E24="Not met",G24<>""),AND(E24="Unsure",G24<>""),AND(E24="N/A",H24<>""),AND(Y24=TRUE)),1,0) | W24: =IF(OR(AND($H$6="Medicaid",MID($A24,1,FIND(".",$A24,1)-1)="II"),AND($H$6="CHIP",MID($A24,1,FIND(".",$A24,1)-1)="I")),TRUE,FALSE) | X24: =IF(OR(Y24=TRUE),TRUE,FALSE) | Y24: =IF(SUM(Z24:AE24)<1,TRUE,FALSE) | Z24: =IF($Z$2=I24,1,0) | AA24: =IF($AA$2=J24,1,0) | AB24: =IF($AB$2=K24,1,0) | AC24: =IF($AC$2=L24,1,0) | AD24: =IF($AD$2=M24,1,0) | AE24: =IF($AE$2=O24,1,0) | AM24: =IF(AL24=1,1,"") | AU24: 0
C25: I.C.2 Enrollee Handbook
A26: I.C.2.01 | B26: 42 CFR 438.10(c)(4)(ii) | C26: The contract requires the MCP to use the state developed model enrollee handbook. | D26: 1 | F26: Source: Attachment - Core Contract Provisions 02012025: 61, 121, 156 | CN-680000-FP122: 125, 121, 134 | H26: Recommendation: MET Response: The contract explicitly states that the Managed Care Plan (MCP) shall furnish each new enrollee an enrollee handbook using the model enrollee handbook template provided by the Agency. This indicates that the MCP is required to use the state developed model enrollee handbook. [1][2] | I26: MCO | J26: HIO | K26: PIHP | L26: PAHP | M26: NEMT PAHP | O26: PCCME | P26: EXISTING | R26: 42917 | U26: =IF(OR($E$25="N/A",AND(AU26=0,'Cover Sheet'!$B$29="Streamlined Review"),AND(E26="Met",F26<>""),AND(E26="Not met",G26<>""),AND(E26="Unsure",G26<>""),AND(E26="N/A",H26<>""),AND(Y26=TRUE)),1,0) | W26: =IF(OR(AND($H$6="Medicaid",MID($A26,1,FIND(".",$A26,1)-1)="II"),AND($H$6="CHIP",MID($A26,1,FIND(".",$A26,1)-1)="I")),TRUE,FALSE) | X26: =IF(OR(Y26=TRUE),TRUE,FALSE) | Y26: =IF(SUM(Z26:AE26)<1,TRUE,FALSE) | Z26: =IF($Z$2=I26,1,0) | AA26: =IF($AA$2=J26,1,0) | AB26: =IF($AB$2=K26,1,0) | AC26: =IF($AC$2=L26,1,0) | AD26: =IF($AD$2=M26,1,0) | AE26: =IF($AE$2=O26,1,0) | AM26: =IF(AL26=1,1,"") | AU26: 0
A27: I.C.2.02 | B27: 42 CFR 438.10(g)(1); 45 CFR 147.200(a) | C27: The contract requires the MCP to provide each enrollee an enrollee handbook, which serves as a summary of benefits and coverage, within a reasonable time after receiving notice of the beneficiary's enrollment. | D27: 1 | F27: Source: Attachment - Core Contract Provisions 02012025: 61 | CN-680000-FP122: 123 | H27: Recommendation: MET Response: The contract explicitly states that the Managed Care Plan (MCP) shall furnish each new enrollee an enrollee handbook using the model enrollee handbook template provided by the Agency. This handbook shall comply with various federal regulations, including those related to summary of benefits and coverage. Additionally, the MCP is required to furnish enrollee materials, including the enrollee handbook, to the new enrollee within a reasonable time after receiving notice of enrollment. Evidence: 1. "The Managed Care Plan shall furnish each new enrollee an enrollee handbook using the model enrollee handbook template provided by the Agency. The model enrollee handbook shall comply with the provisions of 42 CFR 438.3(j), 42 CFR 438.102(b)(2), 42 CFR 438.10(c)(4)(ii), 42 CFR 438.10(g). 42 CFR 438.62(b)(3), 42 CFR 489.102(a), and 45 CFR 147.200(a)." [Attachment - Core Contract Provisions 02012025: 61] 2. "The Managed Care Plan shall furnish enrollee materials to the new enrollee: (3) A current enrollee handbook." [CN-680000-FP122: 123] | I27: MCO | J27: HIO | K27: PIHP | L27: PAHP | M27: NEMT PAHP | O27: PCCME | P27: EXISTING | R27: 42917 | U27: =IF(OR($E$25="N/A",AND(AU27=0,'Cover Sheet'!$B$29="Streamlined Review"),AND(E27="Met",F27<>""),AND(E27="Not met",G27<>""),AND(E27="Unsure",G27<>""),AND(E27="N/A",H27<>""),AND(Y27=TRUE)),1,0) | W27: =IF(OR(AND($H$6="Medicaid",MID($A27,1,FIND(".",$A27,1)-1)="II"),AND($H$6="CHIP",MID($A27,1,FIND(".",$A27,1)-1)="I")),TRUE,FALSE) | X27: =IF(OR(Y27=TRUE),TRUE,FALSE) | Y27: =IF(SUM(Z27:AE27)<1,TRUE,FALSE) | Z27: =IF($Z$2=I27,1,0) | AA27: =IF($AA$2=J27,1,0) | AB27: =IF($AB$2=K27,1,0) | AC27: =IF($AC$2=L27,1,0) | AD27: =IF($AD$2=M27,1,0) | AE27: =IF($AE$2=O27,1,0) | AM27: =IF(AL27=1,1,"") | AU27: 0
A28: I.C.2.03 | B28: 42 CFR 438.10(g)(2) | C28: The content of the enrollee handbook must include information that enables the enrollee to understand how to effectively use the managed care program. | D28: 1 | F28: Source: Attachment - Core Contract Provisions 02012025: 61 | CN-680000-FP122: 125 | H28: Recommendation: MET Response: The contract text explicitly states that the Managed Care Plan shall furnish each new enrollee an enrollee handbook using the model enrollee handbook template provided by the Agency. The model enrollee handbook shall comply with the provisions of 42 CFR 438.3(j), 42 CFR 438.102(b)(2), 42 CFR 438.10(c)(4)(ii), 42 CFR 438.10(g), 42 CFR 438.62(b)(3), 42 CFR 489.102(a), and 45 CFR 147.200(a). This indicates that the handbook is designed to provide necessary information for enrollees to understand and use the managed care program effectively. [1][2] | I28: MCO | J28: HIO | K28: PIHP | L28: PAHP | M28: NEMT PAHP | O28: PCCME | P28: EXISTING | R28: 42917 | U28: =IF(OR($E$25="N/A",AND(AU28=0,'Cover Sheet'!$B$29="Streamlined Review"),AND(E28="Met",F28<>""),AND(E28="Not met",G28<>""),AND(E28="Unsure",G28<>""),AND(E28="N/A",H28<>""),AND(Y28=TRUE)),1,0) | W28: =IF(OR(AND($H$6="Medicaid",MID($A28,1,FIND(".",$A28,1)-1)="II"),AND($H$6="CHIP",MID($A28,1,FIND(".",$A28,1)-1)="I")),TRUE,FALSE) | X28: =IF(OR(Y28=TRUE),TRUE,FALSE) | Y28: =IF(SUM(Z28:AE28)<1,TRUE,FALSE) | Z28: =IF($Z$2=I28,1,0) | AA28: =IF($AA$2=J28,1,0) | AB28: =IF($AB$2=K28,1,0) | AC28: =IF($AC$2=L28,1,0) | AD28: =IF($AD$2=M28,1,0) | AE28: =IF($AE$2=O28,1,0) | AM28: =IF(AL28=1,1,"") | AU28: 0
A29: I.C.2.04 | B29: 42 CFR 438.10(g)(2)(i) | C29: The MCP is required to utilize the model enrollee handbook developed by the state that includes information on benefits provided by the MCP. This includes information about the Early and Periodic Screening, Diagnostic and Treatment (EPSDT) benefit and how to access component services if individuals under age 21 entitled to the EPSDT benefit are enrolled in the MCP. | D29: 1 | F29: Source: CN-680000-FP122: 125, 121 | Attachment - Core Contract Provisions 02012025: 61, 57 | H29: Recommendation: MET Response: The contract explicitly states that the Managed Care Plan (MCP) shall furnish each new enrollee an enrollee handbook using the model enrollee handbook template provided by the Agency. This handbook is required to comply with various federal regulations, which likely include provisions for the EPSDT benefit. The contract also mentions that the enrollee handbook should incorporate information on enrollees' rights and responsibilities, which would include benefits such as EPSDT. Evidence: - "The Managed Care Plan shall furnish each new enrollee an enrollee handbook using the model enrollee handbook template provided by the Agency." [CN-680000-FP122: 125, Attachment - Core Contract Provisions 02012025: 61] - "The Managed Care Plan shall establish and maintain an enrollee services function with the capability to answer enrollee inquiries and ensure that enrollees are notified of their rights and responsibilities, as described in 42 CFR 438.100, and incorporated in the model enrollee handbook." [CN-680000-FP122: 121, Attachment - Core Contract Provisions 02012025: 57] | I29: MCO | J29: HIO | K29: PIHP | L29: PAHP | M29: NEMT PAHP | O29: PCCME | P29: EXISTING | R29: 42917 | U29: =IF(OR($E$25="N/A",AND(AU29=0,'Cover Sheet'!$B$29="Streamlined Review"),AND(E29="Met",F29<>""),AND(E29="Not met",G29<>""),AND(E29="Unsure",G29<>""),AND(E29="N/A",H29<>""),AND(Y29=TRUE)),1,0) | W29: =IF(OR(AND($H$6="Medicaid",MID($A29,1,FIND(".",$A29,1)-1)="II"),AND($H$6="CHIP",MID($A29,1,FIND(".",$A29,1)-1)="I")),TRUE,FALSE) | X29: =IF(OR(Y29=TRUE),TRUE,FALSE) | Y29: =IF(SUM(Z29:AE29)<1,TRUE,FALSE) | Z29: =IF($Z$2=I29,1,0) | AA29: =IF($AA$2=J29,1,0) | AB29: =IF($AB$2=K29,1,0) | AC29: =IF($AC$2=L29,1,0) | AD29: =IF($AD$2=M29,1,0) | AE29: =IF($AE$2=O29,1,0) | AM29: =IF(AL29=1,1,"") | AU29: 0
A30: I.C.2.05 | B30: 42 CFR 438.10(g)(2)(ii) | C30: The MCP is required to utilize the model enrollee handbook developed by the state that includes information about how and where to access any benefits provided by the state, including EPSDT benefits delivered outside the MCP, if any. | D30: 1 | F30: Source: CN-680000-FP122: 125 | Attachment - Core Contract Provisions 02012025: 57 | H30: Recommendation: MET Response: The contract explicitly states that the Managed Care Plan (MCP) shall furnish each new enrollee an enrollee handbook using the model enrollee handbook template provided by the Agency. This indicates that the MCP is required to utilize the model enrollee handbook developed by the state. Additionally, the model enrollee handbook is required to comply with various federal regulations, which likely include provisions for informing enrollees about accessing benefits, including EPSDT benefits. Evidence: - "The Managed Care Plan shall furnish each new enrollee an enrollee handbook using the model enrollee handbook template provided by the Agency." [CN-680000-FP122: 125] - "The Managed Care Plan shall establish and maintain an enrollee services function with the capability to answer enrollee inquiries and ensure that enrollees are notified of their rights and responsibilities, as described in 42 CFR 438.100, and incorporated in the model enrollee handbook." [Attachment - Core Contract Provisions 02012025: 57] | I30: MCO | J30: HIO | K30: PIHP | L30: PAHP | M30: NEMT PAHP | O30: PCCME | P30: EXISTING | R30: 42917 | U30: =IF(OR($E$25="N/A",AND(AU30=0,'Cover Sheet'!$B$29="Streamlined Review"),AND(E30="Met",F30<>""),AND(E30="Not met",G30<>""),AND(E30="Unsure",G30<>""),AND(E30="N/A",H30<>""),AND(Y30=TRUE)),1,0) | W30: =IF(OR(AND($H$6="Medicaid",MID($A30,1,FIND(".",$A30,1)-1)="II"),AND($H$6="CHIP",MID($A30,1,FIND(".",$A30,1)-1)="I")),TRUE,FALSE) | X30: =IF(OR(Y30=TRUE),TRUE,FALSE) | Y30: =IF(SUM(Z30:AE30)<1,TRUE,FALSE) | Z30: =IF($Z$2=I30,1,0) | AA30: =IF($AA$2=J30,1,0) | AB30: =IF($AB$2=K30,1,0) | AC30: =IF($AC$2=L30,1,0) | AD30: =IF($AD$2=M30,1,0) | AE30: =IF($AE$2=O30,1,0) | AM30: =IF(AL30=1,1,"") | AU30: 0
A31: I.C.2.06 | B31: 42 CFR 438.10(g)(2)(ii) | C31: The MCP is required to utilize the model enrollee handbook developed by the state that includes information about cost sharing on any benefits carved out of the MCP contract and provided by the state. | D31: 1 | F31: Source: CN-680000-FP122: 125, 61 | Attachment - Core Contract Provisions 02012025: 61 | H31: Recommendation: MET Response: The contract explicitly states that the Managed Care Plan (MCP) shall furnish each new enrollee an enrollee handbook using the model enrollee handbook template provided by the Agency. This indicates that the MCP is required to utilize the model enrollee handbook developed by the state. Additionally, the model enrollee handbook is required to comply with various federal regulations, which likely include provisions for cost sharing and benefits. Evidence: - "The Managed Care Plan shall furnish each new enrollee an enrollee handbook using the model enrollee handbook template provided by the Agency." [CN-680000-FP122: 125, 61] - "The model enrollee handbook shall comply with the provisions of 42 CFR 438.3(j), 42 CFR 438.102(b)(2), 42 CFR 438.10(c)(4)(ii), 42 CFR 438.10(g). 42 CFR 438.62(b)(3), 42 CFR 489.102(a), and 45 CFR 147.200(a)." [CN-680000-FP122: 125, 61] | I31: MCO | J31: HIO | K31: PIHP | L31: PAHP | M31: NEMT PAHP | O31: PCCME | P31: EXISTING | R31: 42917 | U31: =IF(OR($E$25="N/A",AND(AU31=0,'Cover Sheet'!$B$29="Streamlined Review"),AND(E31="Met",F31<>""),AND(E31="Not met",G31<>""),AND(E31="Unsure",G31<>""),AND(E31="N/A",H31<>""),AND(Y31=TRUE)),1,0) | W31: =IF(OR(AND($H$6="Medicaid",MID($A31,1,FIND(".",$A31,1)-1)="II"),AND($H$6="CHIP",MID($A31,1,FIND(".",$A31,1)-1)="I")),TRUE,FALSE) | X31: =IF(OR(Y31=TRUE),TRUE,FALSE) | Y31: =IF(SUM(Z31:AE31)<1,TRUE,FALSE) | Z31: =IF($Z$2=I31,1,0) | AA31: =IF($AA$2=J31,1,0) | AB31: =IF($AB$2=K31,1,0) | AC31: =IF($AC$2=L31,1,0) | AD31: =IF($AD$2=M31,1,0) | AE31: =IF($AE$2=O31,1,0) | AM31: =IF(AL31=1,1,"") | AU31: 0
A32: I.C.2.07 | B32: 42 CFR 438.10(g)(2)(ii) | C32: The MCP is required to utilize the model enrollee handbook developed by the state that includes information about how transportation is provided for any benefits carved out of the MCP contract and provided by the state. | D32: 1 | F32: Source: Attachment - Core Contract Provisions 02012025: 61, 125 | CN-680000-FP122: 125 | H32: Recommendation: MET Response: The contract explicitly states that the Managed Care Plan (MCP) shall furnish each new enrollee an enrollee handbook using the model enrollee handbook template provided by the Agency. This indicates that the MCP is required to utilize the model enrollee handbook developed by the state. However, the contract does not explicitly mention that the handbook includes information about how transportation is provided for benefits carved out of the MCP contract and provided by the state. Therefore, while the requirement to use the state-developed handbook is met, the specific inclusion of transportation information is not explicitly confirmed. Evidence: - "The Managed Care Plan shall furnish each new enrollee an enrollee handbook using the model enrollee handbook template provided by the Agency." [Attachment - Core Contract Provisions 02012025: 61, 125 | CN-680000-FP122: 125] | I32: MCO | J32: HIO | K32: PIHP | L32: PAHP | M32: NEMT PAHP | O32: PCCME | P32: EXISTING | R32: 42917 | U32: =IF(OR($E$25="N/A",AND(AU32=0,'Cover Sheet'!$B$29="Streamlined Review"),AND(E32="Met",F32<>""),AND(E32="Not met",G32<>""),AND(E32="Unsure",G32<>""),AND(E32="N/A",H32<>""),AND(Y32=TRUE)),1,0) | W32: =IF(OR(AND($H$6="Medicaid",MID($A32,1,FIND(".",$A32,1)-1)="II"),AND($H$6="CHIP",MID($A32,1,FIND(".",$A32,1)-1)="I")),TRUE,FALSE) | X32: =IF(OR(Y32=TRUE),TRUE,FALSE) | Y32: =IF(SUM(Z32:AE32)<1,TRUE,FALSE) | Z32: =IF($Z$2=I32,1,0) | AA32: =IF($AA$2=J32,1,0) | AB32: =IF($AB$2=K32,1,0) | AC32: =IF($AC$2=L32,1,0) | AD32: =IF($AD$2=M32,1,0) | AE32: =IF($AE$2=O32,1,0) | AM32: =IF(AL32=1,1,"") | AU32: 0
A33: I.C.2.08 | B33: 42 CFR 438.10(g)(2)(ii)(A)–(B); 42 CFR 438.102(b)(2) | C33: The MCP is required to utilize the model enrollee handbook developed by the state that includes detail that in the case of a counseling or referral service that the MCP does not cover because of moral or religious objections, the MCP informs enrollees that: 1) That the service is not covered by the MCP; and 2) How they can obtain information from the state about how to access those services. | D33: 1 | F33: Source: Attachment - Core Contract Provisions 02012025: 70 | CN-680000-FP122: 134 | H33: Recommendation: MET Response: The contract explicitly states that if the Managed Care Plan (MCP) chooses not to cover or furnish counseling or referral service information to enrollees due to moral or religious objections, the Agency shall be responsible for providing information on how and where to obtain the service (42 CFR 438.102(b)(1)(ii)(A)(1)) [1]. This indicates that the MCP is required to inform enrollees that the service is not covered and how they can obtain information from the state about accessing those services. [1] "Attachment - Core Contract Provisions 02012025: 70 | CN-680000-FP122: 134" | I33: MCO | J33: HIO | K33: PIHP | L33: PAHP | O33: PCCME | P33: EXISTING | R33: 42917 | U33: =IF(OR($E$25="N/A",AND(AU33=0,'Cover Sheet'!$B$29="Streamlined Review"),AND(E33="Met",F33<>""),AND(E33="Not met",G33<>""),AND(E33="Unsure",G33<>""),AND(E33="N/A",H33<>""),AND(Y33=TRUE)),1,0) | W33: =IF(OR(AND($H$6="Medicaid",MID($A33,1,FIND(".",$A33,1)-1)="II"),AND($H$6="CHIP",MID($A33,1,FIND(".",$A33,1)-1)="I")),TRUE,FALSE) | X33: =IF(OR(Y33=TRUE),TRUE,FALSE) | Y33: =IF(SUM(Z33:AE33)<1,TRUE,FALSE) | Z33: =IF($Z$2=I33,1,0) | AA33: =IF($AA$2=J33,1,0) | AB33: =IF($AB$2=K33,1,0) | AC33: =IF($AC$2=L33,1,0) | AD33: =IF($AD$2=M33,1,0) | AE33: =IF($AE$2=O33,1,0) | AM33: =IF(AL33=1,1,"") | AU33: 1
